Workbook
Name IQ_CH: 110000
Name IQ_CQ: 5000
Name IQ_CY: 10000
Name IQ_DAILY: 500000
Name IQ_FH: 100000
Name IQ_FQ: 500
Name IQ_FY: 1000
Name IQ_LTM: 2000
Name IQ_MONTH: 15000
Name IQ_NTM: 6000
Name IQ_WEEK: 50000
Name IQ_YTD: 3000
Name UPDATE: '[1]Data Sheet'!$E$1
Name UPDATE: 'Data Sheet'!$E$1

Sheet Historical FS
B2: ="Historical Financial Statements- "&'Data Sheet'!B1 -> Historical Financial Statements- HINDUSTAN AERONAUTICS LTD
B3: Years | C3: =IFERROR('Data Sheet'!B16,0) -> 42460 | D3: =IFERROR('Data Sheet'!C16,0) -> 42825 | E3: =IFERROR('Data Sheet'!D16,0) -> 43190 | F3: =IFERROR('Data Sheet'!E16,0) -> 43555 | G3: =IFERROR('Data Sheet'!F16,0) -> 43921 | H3: =IFERROR('Data Sheet'!G16,0) -> 44286 | I3: =IFERROR('Data Sheet'!H16,0) -> 44651 | J3: =IFERROR('Data Sheet'!I16,0) -> 45016 | ... L3: =IFERROR('Data Sheet'!K16,0) -> 45747 | M3: LTM
A5: # | B5: Income Statement
B6: ='Data Sheet'!A17 -> Sales | C6: =IFERROR('Data Sheet'!B17,0) -> 16758.5 | D6: =IFERROR('Data Sheet'!C17,0) -> 17949.92 | E6: =IFERROR('Data Sheet'!D17,0) -> 18519.74 | F6: =IFERROR('Data Sheet'!E17,0) -> 20008 | G6: =IFERROR('Data Sheet'!F17,0) -> 21445.16 | H6: =IFERROR('Data Sheet'!G17,0) -> 22882.32 | I6: =IFERROR('Data Sheet'!H17,0) -> 24620.02 | J6: =IFERROR('Data Sheet'!I17,0) -> 26927.46 | ... L6: =IFERROR('Data Sheet'!K17,0) -> 30980.95 | M6: =IFERROR(SUM('Data Sheet'!H42:K42),0) -> 32104.78
B7: Sales Growth | C7: - | D7: =D6/C6-1 -> 0.071093475 | E7: =E6/D6-1 -> 0.031744988 | F7: =F6/E6-1 -> 0.080360739 | G7: =G6/F6-1 -> 0.071829268 | H7: =H6/G6-1 -> 0.067015588 | I7: =I6/H6-1 -> 0.075940726 | J7: =J6/I6-1 -> 0.093722101 | K7: =K6/J6-1 -> 0.12825643 | ... M7: =M6/L6-1 -> 0.036274872
B9: COGS | C9: =IFERROR(SUM('Data Sheet'!B18,'Data Sheet'!B20,'Data Sheet'!B21,'Data Sheet'!B22)-1*'Data Sheet'!B19,0) -> 12512.9 | D9: =IFERROR(SUM('Data Sheet'!C18,'Data Sheet'!C20,'Data Sheet'!C21,'Data Sheet'!C22)-1*'Data Sheet'!C19,0) -> 13838.91 | E9: =IFERROR(SUM('Data Sheet'!D18,'Data Sheet'!D20,'Data Sheet'!D21,'Data Sheet'!D22)-1*'Data Sheet'!D19,0) -> 14219.92 | F9: =IFERROR(SUM('Data Sheet'!E18,'Data Sheet'!E20,'Data Sheet'!E21,'Data Sheet'!E22)-1*'Data Sheet'!E19,0) -> 14087.52 | G9: =IFERROR(SUM('Data Sheet'!F18,'Data Sheet'!F20,'Data Sheet'!F21,'Data Sheet'!F22)-1*'Data Sheet'!F19,0) -> 14937.2 | H9: =IFERROR(SUM('Data Sheet'!G18,'Data Sheet'!G20,'Data Sheet'!G21,'Data Sheet'!G22)-1*'Data Sheet'!G19,0) -> 16337.81 | I9: =IFERROR(SUM('Data Sheet'!H18,'Data Sheet'!H20,'Data Sheet'!H21,'Data Sheet'!H22)-1*'Data Sheet'!H19,0) -> 15494.02 | J9: =IFERROR(SUM('Data Sheet'!I18,'Data Sheet'!I20,'Data Sheet'!I21,'Data Sheet'!I22)-1*'Data Sheet'!I19,0) -> 16160.85 | ... L9: =IFERROR(SUM('Data Sheet'!K18,'Data Sheet'!K20,'Data Sheet'!K21,'Data Sheet'!K22)-1*'Data Sheet'!K19,0) -> 19124.16 | M9: =IFERROR(SUM('Data Sheet'!H43:K43),0) -> 22287.08
B10: COGS % of Sales | C10: =IFERROR(C9/C6,0) -> 0.7466599 | D10: =IFERROR(D9/D6,0) -> 0.77097335 | E10: =IFERROR(E9/E6,0) -> 0.76782503 | F10: =IFERROR(F9/F6,0) -> 0.70409436 | G10: =IFERROR(G9/G6,0) -> 0.69653013 | H10: =IFERROR(H9/H6,0) -> 0.71399272 | I10: =IFERROR(I9/I6,0) -> 0.62932605 | J10: =IFERROR(J9/J6,0) -> 0.60016244 | ... M10: =IFERROR(M9/M6,0) -> 0.69419818
B12: Gross Profit | C12: =C6-C9 -> 4245.6 | D12: =D6-D9 -> 4111.01 | E12: =E6-E9 -> 4299.82 | F12: =F6-F9 -> 5920.48 | G12: =G6-G9 -> 6507.96 | H12: =H6-H9 -> 6544.51 | I12: =I6-I9 -> 9126 | J12: =J6-J9 -> 10766.61 | ... M12: =M6-M9 -> 9817.7
B13: Gross Profit % of sales | C13: =IFERROR(C12/C6,0) -> 0.2533401 | D13: =IFERROR(D12/D6,0) -> 0.22902665 | E13: =IFERROR(E12/E6,0) -> 0.23217497 | F13: =IFERROR(F12/F6,0) -> 0.29590564 | G13: =IFERROR(G12/G6,0) -> 0.30346987 | H13: =IFERROR(H12/H6,0) -> 0.28600728 | I13: =IFERROR(I12/I6,0) -> 0.37067395 | J13: =IFERROR(J12/J6,0) -> 0.39983756 | ... M13: =IFERROR(M12/M6,0) -> 0.30580182
B15: Selling & General Expenses | C15: =IFERROR(SUM('Data Sheet'!B23:B24),0) -> 1771.7 | D15: =IFERROR(SUM('Data Sheet'!C23:C24),0) -> 880.32 | E15: =IFERROR(SUM('Data Sheet'!D23:D24),0) -> 851.13 | F15: =IFERROR(SUM('Data Sheet'!E23:E24),0) -> 1369.45 | G15: =IFERROR(SUM('Data Sheet'!F23:F24),0) -> 1593.72 | H15: =IFERROR(SUM('Data Sheet'!G23:G24),0) -> 1200.53 | I15: =IFERROR(SUM('Data Sheet'!H23:H24),0) -> 3710.63 | J15: =IFERROR(SUM('Data Sheet'!I23:I24),0) -> 4080.95 | ... L15: =IFERROR(SUM('Data Sheet'!K23:K24),0) -> 2235.77 | M15: =M18-M12 -> 1424.29
B16: S&G % of sales | C16: =IFERROR(C15/C6,0) -> 0.10571949 | D16: =IFERROR(D15/D6,0) -> 0.049043116 | E16: =IFERROR(E15/E6,0) -> 0.045957989 | F16: =IFERROR(F15/F6,0) -> 0.068445122 | G16: =IFERROR(G15/G6,0) -> 0.074316069 | H16: =IFERROR(H15/H6,0) -> 0.052465397 | I16: =IFERROR(I15/I6,0) -> 0.15071596 | J16: =IFERROR(J15/J6,0) -> 0.15155347 | ... M16: =IFERROR(M15/M6,0) -> 0.044363799
B18: EBITDA | C18: =C12-C15 -> 2473.9 | D18: =D12-D15 -> 3230.69 | E18: =E12-E15 -> 3448.69 | F18: =F12-F15 -> 4551.03 | G18: =G12-G15 -> 4914.24 | H18: =H12-H15 -> 5343.98 | I18: =I12-I15 -> 5415.37 | J18: =J12-J15 -> 6685.66 | ... L18: =L12-L15 -> 9621.02 | M18: =SUM('Data Sheet'!H50:K50)+SUM('Data Sheet'!H45:K45) -> 11241.99
B19: EBITDA % of Sales | C19: =IFERROR(C18/C6,0) -> 0.14762061 | D19: =IFERROR(D18/D6,0) -> 0.17998353 | E19: =IFERROR(E18/E6,0) -> 0.18621698 | F19: =IFERROR(F18/F6,0) -> 0.22746052 | G19: =IFERROR(G18/G6,0) -> 0.2291538 | H19: =IFERROR(H18/H6,0) -> 0.23354188 | I19: =IFERROR(I18/I6,0) -> 0.21995799 | J19: =IFERROR(J18/J6,0) -> 0.24828409 | ... M19: =IFERROR(M18/M6,0) -> 0.35016561
B21: Other Income | C21: =IFERROR('Data Sheet'!B25,0) -> 1608.1 | D21: =IFERROR('Data Sheet'!C25,0) -> 1058.2 | E21: =IFERROR('Data Sheet'!D25,0) -> 775.7 | F21: =IFERROR('Data Sheet'!E25,0) -> 376.26 | G21: =IFERROR('Data Sheet'!F25,0) -> 422.51 | H21: =IFERROR('Data Sheet'!G25,0) -> 364.28 | I21: =IFERROR('Data Sheet'!H25,0) -> 984.93 | J21: =IFERROR('Data Sheet'!I25,0) -> 1672.92 | ... L21: =IFERROR('Data Sheet'!K25,0) -> 2608.23 | M21: =IFERROR(SUM('Data Sheet'!I44:K44),0) -> 2321.07
B22: % of Sales | C22: =IFERROR(C21/C6,0) -> 0.095957275 | D22: =IFERROR(D21/D6,0) -> 0.058952909 | E22: =IFERROR(E21/E6,0) -> 0.041885037 | F22: =IFERROR(F21/F6,0) -> 0.018805478 | G22: =IFERROR(G21/G6,0) -> 0.019701881 | H22: =IFERROR(H21/H6,0) -> 0.015919714 | I22: =IFERROR(I21/I6,0) -> 0.040005248 | J22: =IFERROR(J21/J6,0) -> 0.062126914 | ... M22: =IFERROR(M21/M6,0) -> 0.072296711
B24: Interest | C24: =IFERROR('Data Sheet'!B27,0) -> 5.9 | D24: =IFERROR('Data Sheet'!C27,0) -> 16.45 | E24: =IFERROR('Data Sheet'!D27,0) -> 34.62 | F24: =IFERROR('Data Sheet'!E27,0) -> 177.6 | G24: =IFERROR('Data Sheet'!F27,0) -> 359.59 | H24: =IFERROR('Data Sheet'!G27,0) -> 266.89 | I24: =IFERROR('Data Sheet'!H27,0) -> 65.24 | J24: =IFERROR('Data Sheet'!I27,0) -> 64.41 | ... L24: =IFERROR('Data Sheet'!K27,0) -> 21.62 | M24: =IFERROR(SUM('Data Sheet'!H46:K46),0) -> 9.18
B25: Interest % of Sales | C25: =IFERROR(C24/C6,0) -> 0.00035206015 | D25: =IFERROR(D24/D6,0) -> 0.00091643862 | E25: =IFERROR(E24/E6,0) -> 0.0018693567 | F25: =IFERROR(F24/F6,0) -> 0.0088764494 | G25: =IFERROR(G24/G6,0) -> 0.016767886 | H25: =IFERROR(H24/H6,0) -> 0.01166359 | I25: =IFERROR(I24/I6,0) -> 0.002649876 | J25: =IFERROR(J24/J6,0) -> 0.002391982 | ... M25: =IFERROR(M24/M6,0) -> 0.00028593873
B27: Depreciation | C27: =IFERROR('Data Sheet'!B26,0) -> 862.8 | D27: =IFERROR('Data Sheet'!C26,0) -> 680.68 | E27: =IFERROR('Data Sheet'!D26,0) -> 947.09 | F27: =IFERROR('Data Sheet'!E26,0) -> 1025.26 | G27: =IFERROR('Data Sheet'!F26,0) -> 998.52 | H27: =IFERROR('Data Sheet'!G26,0) -> 1157.89 | I27: =IFERROR('Data Sheet'!H26,0) -> 1110.53 | J27: =IFERROR('Data Sheet'!I26,0) -> 1784.67 | ... L27: =IFERROR('Data Sheet'!K26,0) -> 1340.37 | M27: =IFERROR(SUM('Data Sheet'!H45:K45),0) -> 1424.29
B28: Depreciation % of Sales | C28: =IFERROR(C27/C6,0) -> 0.051484321 | D28: =IFERROR(D27/D6,0) -> 0.03792106 | E28: =IFERROR(E27/E6,0) -> 0.051139487 | F28: =IFERROR(F27/F6,0) -> 0.051242503 | G28: =IFERROR(G27/G6,0) -> 0.046561555 | H28: =IFERROR(H27/H6,0) -> 0.050601949 | I28: =IFERROR(I27/I6,0) -> 0.045106787 | J28: =IFERROR(J27/J6,0) -> 0.066276953 | ... M28: =IFERROR(M27/M6,0) -> 0.044363799
B30: Profit Before Tax | C30: =IFERROR(SUM(C18,C21)-(SUM(C24,C27)),0) -> 3213.3 | D30: =IFERROR(SUM(D18,D21)-(SUM(D24,D27)),0) -> 3591.76 | E30: =IFERROR(SUM(E18,E21)-(SUM(E24,E27)),0) -> 3242.68 | F30: =IFERROR(SUM(F18,F21)-(SUM(F24,F27)),0) -> 3724.43 | G30: =IFERROR(SUM(G18,G21)-(SUM(G24,G27)),0) -> 3978.64 | H30: =IFERROR(SUM(H18,H21)-(SUM(H24,H27)),0) -> 4283.48 | I30: =IFERROR(SUM(I18,I21)-(SUM(I24,I27)),0) -> 5224.53 | J30: =IFERROR(SUM(J18,J21)-(SUM(J24,J27)),0) -> 6509.5 | ... M30: =IFERROR(SUM(M18,M21)-(SUM(M24,M27)),0) -> 12129.59
B31: PBT % of sales | C31: =IFERROR(C30/C6,0) -> 0.1917415 | D31: =IFERROR(D30/D6,0) -> 0.20009894 | E31: =IFERROR(E30/E6,0) -> 0.17509317 | F31: =IFERROR(F30/F6,0) -> 0.18614704 | G31: =IFERROR(G30/G6,0) -> 0.18552624 | H31: =IFERROR(H30/H6,0) -> 0.18719605 | I31: =IFERROR(I30/I6,0) -> 0.21220657 | J31: =IFERROR(J30/J6,0) -> 0.24174207 | ... M31: =IFERROR(M30/M6,0) -> 0.37781259
B33: Tax | C33: =IFERROR('Data Sheet'!B29,0) -> 1209 | D33: =IFERROR('Data Sheet'!C29,0) -> 966.95 | E33: =IFERROR('Data Sheet'!D29,0) -> 1252.43 | F33: =IFERROR('Data Sheet'!E29,0) -> 1396.28 | G33: =IFERROR('Data Sheet'!F29,0) -> 1095.99 | H33: =IFERROR('Data Sheet'!G29,0) -> 1037.93 | I33: =IFERROR('Data Sheet'!H29,0) -> 144.65 | J33: =IFERROR('Data Sheet'!I29,0) -> 681.77 | ... L33: =IFERROR('Data Sheet'!K29,0) -> 2503.21 | M33: =IFERROR(SUM('Data Sheet'!H48:K48),0) -> 2872.89
B34: Effective Tax Rate | C34: =IFERROR(C33/C30,0) -> 0.37624872 | D34: =IFERROR(D33/D30,0) -> 0.26921342 | E34: =IFERROR(E33/E30,0) -> 0.38623299 | F34: =IFERROR(F33/F30,0) -> 0.37489764 | G34: =IFERROR(G33/G30,0) -> 0.2754685 | H34: =IFERROR(H33/H30,0) -> 0.24230999 | I34: =IFERROR(I33/I30,0) -> 0.027686701 | J34: =IFERROR(J33/J30,0) -> 0.10473462 | ... M34: =IFERROR(M33/M30,0) -> 0.23684972
B36: Net Profit | C36: =C30-C33 -> 2004.3 | D36: =D30-D33 -> 2624.81 | E36: =E30-E33 -> 1990.25 | F36: =F30-F33 -> 2328.15 | G36: =G30-G33 -> 2882.65 | H36: =H30-H33 -> 3245.55 | I36: =I30-I33 -> 5079.88 | J36: =J30-J33 -> 5827.73 | ... M36: =M30-M33 -> 9256.7
B37: Net Margins | C37: =IFERROR(C36/C6,0) -> 0.11959901 | D37: =IFERROR(D36/D6,0) -> 0.14622962 | E37: =IFERROR(E36/E6,0) -> 0.10746641 | F37: =IFERROR(F36/F6,0) -> 0.11636096 | G37: =IFERROR(G36/G6,0) -> 0.13441961 | H37: =IFERROR(H36/H6,0) -> 0.14183658 | I37: =IFERROR(I36/I6,0) -> 0.20633127 | J37: =IFERROR(J36/J6,0) -> 0.21642331 | ... M37: =IFERROR(M36/M6,0) -> 0.28832778
B39: No. of Equity Shares | C39: =IFERROR('Data Sheet'!B93,0) -> 72.3 | D39: =IFERROR('Data Sheet'!C93,0) -> 72.3 | E39: =IFERROR('Data Sheet'!D93,0) -> 66.88 | F39: =IFERROR('Data Sheet'!E93,0) -> 66.88 | G39: =IFERROR('Data Sheet'!F93,0) -> 66.88 | H39: =IFERROR('Data Sheet'!G93,0) -> 66.88 | I39: =IFERROR('Data Sheet'!H93,0) -> 66.88 | J39: =IFERROR('Data Sheet'!I93,0) -> 66.88 | ... M39: =IFERROR('Data Sheet'!L93,0) -> 0
B41: Earnings Per Share | C41: =IFERROR(C36/C39,0) -> 27.721992 | D41: =IFERROR(D36/D39,0) -> 36.304426 | E41: =IFERROR(E36/E39,0) -> 29.758523 | F41: =IFERROR(F36/F39,0) -> 34.810855 | G41: =IFERROR(G36/G39,0) -> 43.101824 | H41: =IFERROR(H36/H39,0) -> 48.527961 | I41: =IFERROR(I36/I39,0) -> 75.955144 | J41: =IFERROR(J36/J39,0) -> 87.137111 | ... M41: =IFERROR(M36/M39,0) -> 0
B42: EPS growth | C42: - | D42: =IFERROR(D41/C41-1,0) -> 0.30958938 | E42: =IFERROR(E41/D41-1,0) -> -0.18030593 | F42: =IFERROR(F41/E41-1,0) -> 0.16977767 | G42: =IFERROR(G41/F41-1,0) -> 0.23817194 | H42: =IFERROR(H41/G41-1,0) -> 0.12589111 | I42: =IFERROR(I41/H41-1,0) -> 0.5651831 | J42: =IFERROR(J41/I41-1,0) -> 0.14721804 | K42: =IFERROR(K41/J41-1,0) -> 0.30770472 | ... M42: =IFERROR(M41/L41-1,0) -> -1
B44: Dividend Per Share | C44: =IFERROR('Data Sheet'!B31/'Historical FS'!C39,0) -> 8.7 | D44: =IFERROR('Data Sheet'!C31/'Historical FS'!D39,0) -> 11.065007 | E44: =IFERROR('Data Sheet'!D31/'Historical FS'!E39,0) -> 16.08448 | F44: =IFERROR('Data Sheet'!E31/'Historical FS'!F39,0) -> 9.8996711 | G44: =IFERROR('Data Sheet'!F31/'Historical FS'!G39,0) -> 16.624551 | H44: =IFERROR('Data Sheet'!G31/'Historical FS'!H39,0) -> 14.999551 | I44: =IFERROR('Data Sheet'!H31/'Historical FS'!I39,0) -> 19.999402 | J44: =IFERROR('Data Sheet'!I31/'Historical FS'!J39,0) -> 27.499103 | ... M44: =IFERROR('Data Sheet'!L31/'Historical FS'!M39,0) -> 0
B45: DPS Growth | C45: - | D45: =IFERROR(D44/C44-1,0) -> 0.27183988 | E45: =IFERROR(E44/D44-1,0) -> 0.45363485 | F45: =IFERROR(F44/E44-1,0) -> -0.38452028 | G45: =IFERROR(G44/F44-1,0) -> 0.67930342 | H45: =IFERROR(H44/G44-1,0) -> -0.097746998 | I45: =IFERROR(I44/H44-1,0) -> 0.33333333 | J45: =IFERROR(J44/I44-1,0) -> 0.37499626 | K45: =IFERROR(K44/J44-1,0) -> 0.27273073 | ... M45: =IFERROR(M44/L44-1,0) -> -1
B46: Dividend Payout Ratio | C46: =IFERROR(C44/C41,0) -> 0.31383026 | D46: =IFERROR(D44/D41,0) -> 0.30478397 | E46: =IFERROR(E44/E41,0) -> 0.54049994 | F46: =IFERROR(F44/F41,0) -> 0.2843846 | G46: =IFERROR(G44/G41,0) -> 0.38570413 | H46: =IFERROR(H44/H41,0) -> 0.30909091 | I46: =IFERROR(I44/I41,0) -> 0.26330543 | J46: =IFERROR(J44/J41,0) -> 0.31558428 | ... M46: =IFERROR(M44/M41,0) -> 0
B47: Retained Earnings | C47: =IFERROR(1-C46,0) -> 0.68616974 | D47: =IFERROR(1-D46,0) -> 0.69521603 | E47: =IFERROR(1-E46,0) -> 0.45950006 | F47: =IFERROR(1-F46,0) -> 0.7156154 | G47: =IFERROR(1-G46,0) -> 0.61429587 | H47: =IFERROR(1-H46,0) -> 0.69090909 | I47: =IFERROR(1-I46,0) -> 0.73669457 | J47: =IFERROR(1-J46,0) -> 0.68441572 | ... M47: =IFERROR(1-M46,0) -> 1
A50: # | B50: Balance Sheet
B51: Equity Share Capital | C51: =IFERROR('Data Sheet'!B57,0) -> 361.5 | D51: =IFERROR('Data Sheet'!C57,0) -> 361.5 | E51: =IFERROR('Data Sheet'!D57,0) -> 334.39 | F51: =IFERROR('Data Sheet'!E57,0) -> 334.39 | G51: =IFERROR('Data Sheet'!F57,0) -> 334.39 | H51: =IFERROR('Data Sheet'!G57,0) -> 334.39 | I51: =IFERROR('Data Sheet'!H57,0) -> 334.39 | J51: =IFERROR('Data Sheet'!I57,0) -> 334.39 | ... L51: =IFERROR('Data Sheet'!K57,0) -> 334.39
B52: Reserves | C52: =IFERROR('Data Sheet'!B58,0) -> 10670.9 | D52: =IFERROR('Data Sheet'!C58,0) -> 12197.61 | E52: =IFERROR('Data Sheet'!D58,0) -> 9176.86 | F52: =IFERROR('Data Sheet'!E58,0) -> 11747.73 | G52: =IFERROR('Data Sheet'!F58,0) -> 12914.12 | H52: =IFERROR('Data Sheet'!G58,0) -> 15089.51 | I52: =IFERROR('Data Sheet'!H58,0) -> 18978.74 | J52: =IFERROR('Data Sheet'!I58,0) -> 23237.76 | ... L52: =IFERROR('Data Sheet'!K58,0) -> 34647.22
B53: Borrowings | C53: =IFERROR('Data Sheet'!B59,0) -> 79.8 | D53: =IFERROR('Data Sheet'!C59,0) -> 1022.03 | E53: =IFERROR('Data Sheet'!D59,0) -> 904.52 | F53: =IFERROR('Data Sheet'!E59,0) -> 4116.2 | G53: =IFERROR('Data Sheet'!F59,0) -> 5926.97 | H53: =IFERROR('Data Sheet'!G59,0) -> 53.28 | I53: =IFERROR('Data Sheet'!H59,0) -> 49.27 | J53: =IFERROR('Data Sheet'!I59,0) -> 51.69 | ... L53: =IFERROR('Data Sheet'!K59,0) -> 51.44
B54: Other Liabilities | C54: =IFERROR('Data Sheet'!B60,0) -> 45419.7 | D54: =IFERROR('Data Sheet'!C60,0) -> 38162.56 | E54: =IFERROR('Data Sheet'!D60,0) -> 38046.84 | F54: =IFERROR('Data Sheet'!E60,0) -> 35298.01 | G54: =IFERROR('Data Sheet'!F60,0) -> 35027.18 | H54: =IFERROR('Data Sheet'!G60,0) -> 37619.24 | I54: =IFERROR('Data Sheet'!H60,0) -> 40891.94 | J54: =IFERROR('Data Sheet'!I60,0) -> 45652.16 | ... L54: =IFERROR('Data Sheet'!K60,0) -> 73665.41
B55: Total Liabilities | C55: =IFERROR(SUM(C51:C54),0) -> 56531.9 | D55: =IFERROR(SUM(D51:D54),0) -> 51743.7 | E55: =IFERROR(SUM(E51:E54),0) -> 48462.61 | F55: =IFERROR(SUM(F51:F54),0) -> 51496.33 | G55: =IFERROR(SUM(G51:G54),0) -> 54202.66 | H55: =IFERROR(SUM(H51:H54),0) -> 53096.42 | I55: =IFERROR(SUM(I51:I54),0) -> 60254.34 | J55: =IFERROR(SUM(J51:J54),0) -> 69276 | ... L55: =IFERROR(SUM(L51:L54),0) -> 108698.46
B57: Non Current Assets Net Block | C57: =IFERROR('Data Sheet'!B62,0) -> 6925.2 | D57: =IFERROR('Data Sheet'!C62,0) -> 7349.56 | E57: =IFERROR('Data Sheet'!D62,0) -> 7566.22 | F57: =IFERROR('Data Sheet'!E62,0) -> 7459.35 | G57: =IFERROR('Data Sheet'!F62,0) -> 7357.49 | H57: =IFERROR('Data Sheet'!G62,0) -> 7165.88 | I57: =IFERROR('Data Sheet'!H62,0) -> 6765.88 | J57: =IFERROR('Data Sheet'!I62,0) -> 6834.4 | ... L57: =IFERROR('Data Sheet'!K62,0) -> 6670.8
B58: Capital Work in Progress | C58: =IFERROR('Data Sheet'!B63,0) -> 1025.4 | D58: =IFERROR('Data Sheet'!C63,0) -> 1389.4 | E58: =IFERROR('Data Sheet'!D63,0) -> 1461.72 | F58: =IFERROR('Data Sheet'!E63,0) -> 1502.11 | G58: =IFERROR('Data Sheet'!F63,0) -> 2042.69 | H58: =IFERROR('Data Sheet'!G63,0) -> 1949.6 | I58: =IFERROR('Data Sheet'!H63,0) -> 2472.94 | J58: =IFERROR('Data Sheet'!I63,0) -> 1885 | ... L58: =IFERROR('Data Sheet'!K63,0) -> 3097.75
B59: Investments | C59: =IFERROR('Data Sheet'!B64,0) -> 915.8 | D59: =IFERROR('Data Sheet'!C64,0) -> 993.99 | E59: =IFERROR('Data Sheet'!D64,0) -> 1010.11 | F59: =IFERROR('Data Sheet'!E64,0) -> 909.64 | G59: =IFERROR('Data Sheet'!F64,0) -> 990.8 | H59: =IFERROR('Data Sheet'!G64,0) -> 1121.32 | I59: =IFERROR('Data Sheet'!H64,0) -> 1362.7 | J59: =IFERROR('Data Sheet'!I64,0) -> 1457.92 | ... L59: =IFERROR('Data Sheet'!K64,0) -> 1754.2
B60: Other Assets | C60: =IFERROR('Data Sheet'!B65-SUM('Data Sheet'!B67:B69),0) -> 5543.5 | D60: =IFERROR('Data Sheet'!C65-SUM('Data Sheet'!C67:C69),0) -> 5121.8 | E60: =IFERROR('Data Sheet'!D65-SUM('Data Sheet'!D67:D69),0) -> 4996.77 | F60: =IFERROR('Data Sheet'!E65-SUM('Data Sheet'!E67:E69),0) -> 8596.77 | G60: =IFERROR('Data Sheet'!F65-SUM('Data Sheet'!F67:F69),0) -> 11899.21 | H60: =IFERROR('Data Sheet'!G65-SUM('Data Sheet'!G67:G69),0) -> 12008.81 | I60: =IFERROR('Data Sheet'!H65-SUM('Data Sheet'!H67:H69),0) -> 14453.93 | J60: =IFERROR('Data Sheet'!I65-SUM('Data Sheet'!I67:I69),0) -> 19842 | ... L60: =IFERROR('Data Sheet'!K65-SUM('Data Sheet'!K67:K69),0) -> 30238.36
B61: Total Non Current Assets | C61: =IFERROR(SUM(C57:C60),0) -> 14409.9 | D61: =IFERROR(SUM(D57:D60),0) -> 14854.75 | E61: =IFERROR(SUM(E57:E60),0) -> 15034.82 | F61: =IFERROR(SUM(F57:F60),0) -> 18467.87 | G61: =IFERROR(SUM(G57:G60),0) -> 22290.19 | H61: =IFERROR(SUM(H57:H60),0) -> 22245.61 | I61: =IFERROR(SUM(I57:I60),0) -> 25055.45 | J61: =IFERROR(SUM(J57:J60),0) -> 30019.32 | ... L61: =IFERROR(SUM(L57:L60),0) -> 41761.11
B63: Receivables | C63: =IFERROR('Data Sheet'!B67,0) -> 4836.9 | D63: =IFERROR('Data Sheet'!C67,0) -> 4220.16 | E63: =IFERROR('Data Sheet'!D67,0) -> 6751.54 | F63: =IFERROR('Data Sheet'!E67,0) -> 12458 | G63: =IFERROR('Data Sheet'!F67,0) -> 11234.73 | H63: =IFERROR('Data Sheet'!G67,0) -> 5668.05 | I63: =IFERROR('Data Sheet'!H67,0) -> 4641.53 | J63: =IFERROR('Data Sheet'!I67,0) -> 4719.18 | ... L63: =IFERROR('Data Sheet'!K67,0) -> 4647.79
B64: Inventory | C64: =IFERROR('Data Sheet'!B68,0) -> 23981.7 | D64: =IFERROR('Data Sheet'!C68,0) -> 21519.73 | E64: =IFERROR('Data Sheet'!D68,0) -> 20130.73 | F64: =IFERROR('Data Sheet'!E68,0) -> 20446.8 | G64: =IFERROR('Data Sheet'!F68,0) -> 20361.18 | H64: =IFERROR('Data Sheet'!G68,0) -> 18005.41 | I64: =IFERROR('Data Sheet'!H68,0) -> 16209.64 | J64: =IFERROR('Data Sheet'!I68,0) -> 14220.89 | ... L64: =IFERROR('Data Sheet'!K68,0) -> 24107.31
B65: Cash & Bank | C65: =IFERROR('Data Sheet'!B69,0) -> 13303.4 | D65: =IFERROR('Data Sheet'!C69,0) -> 11149.06 | E65: =IFERROR('Data Sheet'!D69,0) -> 6545.52 | F65: =IFERROR('Data Sheet'!E69,0) -> 123.66 | G65: =IFERROR('Data Sheet'!F69,0) -> 316.56 | H65: =IFERROR('Data Sheet'!G69,0) -> 7177.35 | I65: =IFERROR('Data Sheet'!H69,0) -> 14347.72 | J65: =IFERROR('Data Sheet'!I69,0) -> 20316.61 | ... L65: =IFERROR('Data Sheet'!K69,0) -> 38182.25
B66: Total Current Assets | C66: =IFERROR(SUM(C63:C65),0) -> 42122 | D66: =IFERROR(SUM(D63:D65),0) -> 36888.95 | E66: =IFERROR(SUM(E63:E65),0) -> 33427.79 | F66: =IFERROR(SUM(F63:F65),0) -> 33028.46 | G66: =IFERROR(SUM(G63:G65),0) -> 31912.47 | H66: =IFERROR(SUM(H63:H65),0) -> 30850.81 | I66: =IFERROR(SUM(I63:I65),0) -> 35198.89 | J66: =IFERROR(SUM(J63:J65),0) -> 39256.68 | ... L66: =IFERROR(SUM(L63:L65),0) -> 66937.35
B68: Total Assets | C68: =IFERROR(C61+C66,0) -> 56531.9 | D68: =IFERROR(D61+D66,0) -> 51743.7 | E68: =IFERROR(E61+E66,0) -> 48462.61 | F68: =IFERROR(F61+F66,0) -> 51496.33 | G68: =IFERROR(G61+G66,0) -> 54202.66 | H68: =IFERROR(H61+H66,0) -> 53096.42 | I68: =IFERROR(I61+I66,0) -> 60254.34 | J68: =IFERROR(J61+J66,0) -> 69276 | ... L68: =IFERROR(L61+L66,0) -> 108698.46
B69: Check | C69: =C68=C55 -> TRUE | D69: =D68=D55 -> TRUE | E69: =E68=E55 -> TRUE | F69: =F68=F55 -> TRUE | G69: =G68=G55 -> TRUE | H69: =H68=H55 -> TRUE | I69: =I68=I55 -> TRUE | J69: =J68=J55 -> TRUE | ... L69: =L68=L55 -> TRUE
A71: # | B71: Cash Flow Statement
B72: Cash from Operating Activity | C72: =IFERROR('Cash Flow Data'!C23,0) -> 0 | D72: =IFERROR('Data Sheet'!C82,0) -> -404.5 | E72: =IFERROR('Data Sheet'!D82,0) -> -747.6 | F72: =IFERROR('Data Sheet'!E82,0) -> -7700.28 | G72: =IFERROR('Data Sheet'!F82,0) -> 1527.39 | H72: =IFERROR('Data Sheet'!G82,0) -> 15117 | I72: =IFERROR('Data Sheet'!H82,0) -> 10173.13 | J72: =IFERROR('Data Sheet'!I82,0) -> 8829.72 | K72: =IFERROR('Data Sheet'!J82,0) -> 8222.82 | ... M72: =IFERROR('Data Sheet'!L82,0) -> 0
B74: Cash from Investing Activity | C74: =IFERROR('Cash Flow Data'!C25,0) -> 0 | D74: =IFERROR('Data Sheet'!C83,0) -> 3011.8 | E74: =IFERROR('Data Sheet'!D83,0) -> 597 | F74: =IFERROR('Data Sheet'!E83,0) -> 5294.17 | G74: =IFERROR('Data Sheet'!F83,0) -> -1338.88 | H74: =IFERROR('Data Sheet'!G83,0) -> -1179.99 | I74: =IFERROR('Data Sheet'!H83,0) -> -12785.23 | J74: =IFERROR('Data Sheet'!I83,0) -> -5728.02 | K74: =IFERROR('Data Sheet'!J83,0) -> -6410.05 | ... M74: =IFERROR('Data Sheet'!L83,0) -> 0
B76: Cash from Financing Activity | C76: =IFERROR('Cash Flow Data'!C27,0) -> 0 | D76: =IFERROR('Data Sheet'!C84,0) -> -164.28 | E76: =IFERROR('Data Sheet'!D84,0) -> -2540.35 | F76: =IFERROR('Data Sheet'!E84,0) -> 2326.11 | G76: =IFERROR('Data Sheet'!F84,0) -> 63.94 | H76: =IFERROR('Data Sheet'!G84,0) -> -7070.18 | I76: =IFERROR('Data Sheet'!H84,0) -> -1463.68 | J76: =IFERROR('Data Sheet'!I84,0) -> -1731.3 | K76: =IFERROR('Data Sheet'!J84,0) -> -1998.85 | ... M76: =IFERROR('Data Sheet'!L84,0) -> 0
B77: Net Cash Flow | C77: =IFERROR('Cash Flow Data'!C29,0) -> 0 | D77: =IFERROR('Data Sheet'!C85,0) -> 2443.02 | E77: =IFERROR('Data Sheet'!D85,0) -> -2690.95 | F77: =IFERROR('Data Sheet'!E85,0) -> -80 | G77: =IFERROR('Data Sheet'!F85,0) -> 252.45 | H77: =IFERROR('Data Sheet'!G85,0) -> 6866.83 | I77: =IFERROR('Data Sheet'!H85,0) -> -4075.78 | J77: =IFERROR('Data Sheet'!I85,0) -> 1370.4 | K77: =IFERROR('Data Sheet'!J85,0) -> -186.08 | ... M77: =IFERROR('Data Sheet'!L85,0) -> 0
A79: # | B79: Common Size Statement Income Statement
B81: Particulars | C81: 42460 | D81: 42825 | E81: 43190 | F81: 43555 | G81: 43921 | H81: 44286 | I81: 44651 | J81: 45016 | K81: 45382 | L81: 45747
B83: ='Data Sheet'!A17 -> Sales | C83: ='Data Sheet'!B17/'Data Sheet'!B$17 -> 1 | D83: ='Data Sheet'!C17/'Data Sheet'!C$17 -> 1 | E83: ='Data Sheet'!D17/'Data Sheet'!D$17 -> 1 | F83: ='Data Sheet'!C17/'Data Sheet'!C$17 -> 1 | G83: ='Data Sheet'!F17/'Data Sheet'!F$17 -> 1 | H83: ='Data Sheet'!G17/'Data Sheet'!G$17 -> 1 | I83: ='Data Sheet'!H17/'Data Sheet'!H$17 -> 1 | J83: ='Data Sheet'!I17/'Data Sheet'!I$17 -> 1 | K83: ='Data Sheet'!J17/'Data Sheet'!J$17 -> 1 | L83: ='Data Sheet'!K17/'Data Sheet'!K$17 -> 1
B84: ='Data Sheet'!A18 -> Raw Material Cost | C84: ='Data Sheet'!B18/'Data Sheet'!B$17 -> 0.54751917 | D84: ='Data Sheet'!C18/'Data Sheet'!C$17 -> 0.46939541 | E84: ='Data Sheet'!D18/'Data Sheet'!D$17 -> 0.41646373 | F84: ='Data Sheet'!E18/'Data Sheet'!C$17 -> 0.40678454 | G84: ='Data Sheet'!F18/'Data Sheet'!F$17 -> 0.3955783 | H84: ='Data Sheet'!G18/'Data Sheet'!G$17 -> 0.37006125 | I84: ='Data Sheet'!H18/'Data Sheet'!H$17 -> 0.37171944 | J84: ='Data Sheet'!I18/'Data Sheet'!I$17 -> 0.39130909 | K84: ='Data Sheet'!J18/'Data Sheet'!J$17 -> 0.41864509 | L84: ='Data Sheet'!K18/'Data Sheet'!K$17 -> 0.63229694
B85: ='Data Sheet'!A19 -> Change in Inventory | C85: ='Data Sheet'!B19/'Data Sheet'!B$17 -> 0.033559089 | D85: ='Data Sheet'!C19/'Data Sheet'!C$17 -> -0.028463637 | E85: ='Data Sheet'!D19/'Data Sheet'!D$17 -> -0.039343965 | F85: ='Data Sheet'!E19/'Data Sheet'!C$17 -> -0.065301127 | G85: ='Data Sheet'!F19/'Data Sheet'!F$17 -> -0.02964212 | H85: ='Data Sheet'!G19/'Data Sheet'!G$17 -> -0.1074253 | I85: ='Data Sheet'!H19/'Data Sheet'!H$17 -> -0.024057657 | J85: ='Data Sheet'!I19/'Data Sheet'!I$17 -> 0.025651138 | K85: ='Data Sheet'!J19/'Data Sheet'!J$17 -> 0.064469071 | L85: ='Data Sheet'!K19/'Data Sheet'!K$17 -> 0.24614449
B86: ='Data Sheet'!A20 -> Power and Fuel | C86: ='Data Sheet'!B20/'Data Sheet'!B$17 -> 0.013951129 | D86: ='Data Sheet'!C20/'Data Sheet'!C$17 -> 0.009574973 | E86: ='Data Sheet'!D20/'Data Sheet'!D$17 -> 0.0094914939 | F86: ='Data Sheet'!E20/'Data Sheet'!C$17 -> 0.01015102 | G86: ='Data Sheet'!F20/'Data Sheet'!F$17 -> 0.0070584691 | H86: ='Data Sheet'!G20/'Data Sheet'!G$17 -> 0.0080144845 | I86: ='Data Sheet'!H20/'Data Sheet'!H$17 -> 0.0081425604 | J86: ='Data Sheet'!I20/'Data Sheet'!I$17 -> 0.0075220611 | K86: ='Data Sheet'!J20/'Data Sheet'!J$17 -> 0.006927996 | L86: ='Data Sheet'!K20/'Data Sheet'!K$17 -> 0.0068422692
B87: ='Data Sheet'!A21 -> Other Mfr. Exp | C87: ='Data Sheet'!B21/'Data Sheet'!B$17 -> 0.023355312 | D87: ='Data Sheet'!C21/'Data Sheet'!C$17 -> 0.064625358 | E87: ='Data Sheet'!D21/'Data Sheet'!D$17 -> 0.069764478 | F87: ='Data Sheet'!E21/'Data Sheet'!C$17 -> 0.062416991 | G87: ='Data Sheet'!F21/'Data Sheet'!F$17 -> 0.041468098 | H87: ='Data Sheet'!G21/'Data Sheet'!G$17 -> 0.040347744 | I87: ='Data Sheet'!H21/'Data Sheet'!H$17 -> 0.038387052 | J87: ='Data Sheet'!I21/'Data Sheet'!I$17 -> 0.044626935 | K87: ='Data Sheet'!J21/'Data Sheet'!J$17 -> 0.039757309 | L87: ='Data Sheet'!K21/'Data Sheet'!K$17 -> 0.039328684
B88: ='Data Sheet'!A22 -> Employee Cost | C88: ='Data Sheet'!B22/'Data Sheet'!B$17 -> 0.19539338 | D88: ='Data Sheet'!C22/'Data Sheet'!C$17 -> 0.19891398 | E88: ='Data Sheet'!D22/'Data Sheet'!D$17 -> 0.23276137 | F88: ='Data Sheet'!E22/'Data Sheet'!C$17 -> 0.24016987 | G88: ='Data Sheet'!F22/'Data Sheet'!F$17 -> 0.22278314 | H88: ='Data Sheet'!G22/'Data Sheet'!G$17 -> 0.18814395 | I88: ='Data Sheet'!H22/'Data Sheet'!H$17 -> 0.18701934 | J88: ='Data Sheet'!I22/'Data Sheet'!I$17 -> 0.18235548 | K88: ='Data Sheet'!J22/'Data Sheet'!J$17 -> 0.17414424 | L88: ='Data Sheet'!K22/'Data Sheet'!K$17 -> 0.18496431
B89: ='Data Sheet'!A23 -> Selling and admin | C89: ='Data Sheet'!B23/'Data Sheet'!B$17 -> 0.013520303 | D89: ='Data Sheet'!C23/'Data Sheet'!C$17 -> 0.012384456 | E89: ='Data Sheet'!D23/'Data Sheet'!D$17 -> 0.011333852 | F89: ='Data Sheet'!E23/'Data Sheet'!C$17 -> 0.019612901 | G89: ='Data Sheet'!F23/'Data Sheet'!F$17 -> 0.0072533849 | H89: ='Data Sheet'!G23/'Data Sheet'!G$17 -> 0.0060461527 | I89: ='Data Sheet'!H23/'Data Sheet'!H$17 -> 0.0073070615 | J89: ='Data Sheet'!I23/'Data Sheet'!I$17 -> 0.0080066965 | K89: ='Data Sheet'!J23/'Data Sheet'!J$17 -> 0.0079552801 | L89: ='Data Sheet'!K23/'Data Sheet'!K$17 -> 0.010009054
B90: ='Data Sheet'!A24 -> Other Expenses | C90: ='Data Sheet'!B24/'Data Sheet'!B$17 -> 0.092199183 | D90: ='Data Sheet'!C24/'Data Sheet'!C$17 -> 0.036658659 | E90: ='Data Sheet'!D24/'Data Sheet'!D$17 -> 0.034624136 | F90: ='Data Sheet'!E24/'Data Sheet'!C$17 -> 0.056679918 | G90: ='Data Sheet'!F24/'Data Sheet'!F$17 -> 0.067062685 | H90: ='Data Sheet'!G24/'Data Sheet'!G$17 -> 0.046419244 | I90: ='Data Sheet'!H24/'Data Sheet'!H$17 -> 0.1434089 | J90: ='Data Sheet'!I24/'Data Sheet'!I$17 -> 0.14354677 | K90: ='Data Sheet'!J24/'Data Sheet'!J$17 -> 0.096063734 | L90: ='Data Sheet'!K24/'Data Sheet'!K$17 -> 0.062156906
B91: ='Data Sheet'!A25 -> Other Income | C91: ='Data Sheet'!B25/'Data Sheet'!B$17 -> 0.095957275 | D91: ='Data Sheet'!C25/'Data Sheet'!C$17 -> 0.058952909 | E91: ='Data Sheet'!D25/'Data Sheet'!D$17 -> 0.041885037 | F91: ='Data Sheet'!E25/'Data Sheet'!C$17 -> 0.020961653 | G91: ='Data Sheet'!F25/'Data Sheet'!F$17 -> 0.019701881 | H91: ='Data Sheet'!G25/'Data Sheet'!G$17 -> 0.015919714 | I91: ='Data Sheet'!H25/'Data Sheet'!H$17 -> 0.040005248 | J91: ='Data Sheet'!I25/'Data Sheet'!I$17 -> 0.062126914 | K91: ='Data Sheet'!J25/'Data Sheet'!J$17 -> 0.063299264 | L91: ='Data Sheet'!K25/'Data Sheet'!K$17 -> 0.084188187
B92: ='Data Sheet'!A26 -> Depreciation | C92: ='Data Sheet'!B26/'Data Sheet'!B$17 -> 0.051484321 | D92: ='Data Sheet'!C26/'Data Sheet'!C$17 -> 0.03792106 | E92: ='Data Sheet'!D26/'Data Sheet'!D$17 -> 0.051139487 | F92: ='Data Sheet'!E26/'Data Sheet'!C$17 -> 0.057117803 | G92: ='Data Sheet'!F26/'Data Sheet'!F$17 -> 0.046561555 | H92: ='Data Sheet'!G26/'Data Sheet'!G$17 -> 0.050601949 | I92: ='Data Sheet'!H26/'Data Sheet'!H$17 -> 0.045106787 | J92: ='Data Sheet'!I26/'Data Sheet'!I$17 -> 0.066276953 | K92: ='Data Sheet'!J26/'Data Sheet'!J$17 -> 0.046317313 | L92: ='Data Sheet'!K26/'Data Sheet'!K$17 -> 0.043264329
B93: ='Data Sheet'!A27 -> Interest | C93: ='Data Sheet'!B27/'Data Sheet'!B$17 -> 0.00035206015 | D93: ='Data Sheet'!C27/'Data Sheet'!C$17 -> 0.00091643862 | E93: ='Data Sheet'!D27/'Data Sheet'!D$17 -> 0.0018693567 | F93: ='Data Sheet'!E27/'Data Sheet'!C$17 -> 0.0098941945 | G93: ='Data Sheet'!F27/'Data Sheet'!F$17 -> 0.016767886 | H93: ='Data Sheet'!G27/'Data Sheet'!G$17 -> 0.01166359 | I93: ='Data Sheet'!H27/'Data Sheet'!H$17 -> 0.002649876 | J93: ='Data Sheet'!I27/'Data Sheet'!I$17 -> 0.002391982 | K93: ='Data Sheet'!J27/'Data Sheet'!J$17 -> 0.0014031759 | L93: ='Data Sheet'!K27/'Data Sheet'!K$17 -> 0.00069784819
B94: ='Data Sheet'!A28 -> Profit before tax | C94: ='Data Sheet'!B28/'Data Sheet'!B$17 -> 0.1917415 | D94: ='Data Sheet'!C28/'Data Sheet'!C$17 -> 0.20009894 | E94: ='Data Sheet'!D28/'Data Sheet'!D$17 -> 0.17509317 | F94: ='Data Sheet'!E28/'Data Sheet'!C$17 -> 0.20750287 | G94: ='Data Sheet'!F28/'Data Sheet'!F$17 -> 0.18552624 | H94: ='Data Sheet'!G28/'Data Sheet'!G$17 -> 0.18719605 | I94: ='Data Sheet'!H28/'Data Sheet'!H$17 -> 0.21220657 | J94: ='Data Sheet'!I28/'Data Sheet'!I$17 -> 0.24174207 | K94: ='Data Sheet'!J28/'Data Sheet'!J$17 -> 0.3365542 | L94: ='Data Sheet'!K28/'Data Sheet'!K$17 -> 0.35077233
B95: ='Data Sheet'!A29 -> Tax | C95: ='Data Sheet'!B29/'Data Sheet'!B$17 -> 0.072142495 | D95: ='Data Sheet'!C29/'Data Sheet'!C$17 -> 0.053869321 | E95: ='Data Sheet'!D29/'Data Sheet'!D$17 -> 0.067626759 | F95: ='Data Sheet'!E29/'Data Sheet'!C$17 -> 0.077787533 | G95: ='Data Sheet'!F29/'Data Sheet'!F$17 -> 0.051106637 | H95: ='Data Sheet'!G29/'Data Sheet'!G$17 -> 0.045359474 | I95: ='Data Sheet'!H29/'Data Sheet'!H$17 -> 0.0058752999 | J95: ='Data Sheet'!I29/'Data Sheet'!I$17 -> 0.025318764 | K95: ='Data Sheet'!J29/'Data Sheet'!J$17 -> 0.085708935 | L95: ='Data Sheet'!K29/'Data Sheet'!K$17 -> 0.080798362
... B97: ='Data Sheet'!A31 -> Dividend Amount | C97: ='Data Sheet'!B31/'Data Sheet'!B$17 -> 0.037533789 | D97: ='Data Sheet'!C31/'Data Sheet'!C$17 -> 0.044568444 | E97: ='Data Sheet'!D31/'Data Sheet'!D$17 -> 0.058085589 | F97: ='Data Sheet'!E31/'Data Sheet'!C$17 -> 0.036885401 | G97: ='Data Sheet'!F31/'Data Sheet'!F$17 -> 0.051846197 | H97: ='Data Sheet'!G31/'Data Sheet'!G$17 -> 0.043840397 | I97: ='Data Sheet'!H31/'Data Sheet'!H$17 -> 0.054328144 | J97: ='Data Sheet'!I31/'Data Sheet'!I$17 -> 0.068299795 | K97: ='Data Sheet'!J31/'Data Sheet'!J$17 -> 0.077045648 | L97: ='Data Sheet'!K31/'Data Sheet'!K$17 -> 0.086347255
B98: =B18 -> EBITDA | C98: =C18/'Data Sheet'!B$17 -> 0.14762061 | D98: =D18/'Data Sheet'!C$17 -> 0.17998353 | E98: =E18/'Data Sheet'!D$17 -> 0.18621698 | F98: =F18/'Data Sheet'!C$17 -> 0.25354041 | G98: =G18/'Data Sheet'!F$17 -> 0.2291538 | H98: =H18/'Data Sheet'!G$17 -> 0.23354188 | I98: =I18/'Data Sheet'!H$17 -> 0.21995799 | J98: =J18/'Data Sheet'!I$17 -> 0.24828409 | K98: =K18/'Data Sheet'!J$17 -> 0.32097542 | L98: =L18/'Data Sheet'!K$17 -> 0.31054632
A101: # | B101: Common Size Statement Balance Sheett
C103: 42460 | D103: 42825 | E103: 43190 | F103: 43555 | G103: 43921 | H103: 44286 | I103: 44651 | J103: 45016 | K103: 45382 | L103: 45747
B105: ='Data Sheet'!A57 -> Equity Share Capital | C105: ='Data Sheet'!B57/'Data Sheet'!B$61 -> 0.0063946197 | D105: ='Data Sheet'!C57/'Data Sheet'!C$61 -> 0.0069863578 | E105: ='Data Sheet'!D57/'Data Sheet'!D$61 -> 0.0068999585 | F105: ='Data Sheet'!E57/'Data Sheet'!E$61 -> 0.0064934724 | G105: ='Data Sheet'!F57/'Data Sheet'!F$61 -> 0.0061692544 | H105: ='Data Sheet'!G57/'Data Sheet'!G$61 -> 0.0062977881 | I105: ='Data Sheet'!H57/'Data Sheet'!H$61 -> 0.0055496417 | J105: ='Data Sheet'!I57/'Data Sheet'!I$61 -> 0.0048269242 | ... L105: ='Data Sheet'!K57/'Data Sheet'!K$61 -> 0.0030763085
B106: ='Data Sheet'!A58 -> Reserves | C106: ='Data Sheet'!B58/'Data Sheet'!B$61 -> 0.18875891 | D106: ='Data Sheet'!C58/'Data Sheet'!C$61 -> 0.23573131 | E106: ='Data Sheet'!D58/'Data Sheet'!D$61 -> 0.18935959 | F106: ='Data Sheet'!E58/'Data Sheet'!E$61 -> 0.22812752 | G106: ='Data Sheet'!F58/'Data Sheet'!F$61 -> 0.2382562 | H106: ='Data Sheet'!G58/'Data Sheet'!G$61 -> 0.28419072 | I106: ='Data Sheet'!H58/'Data Sheet'!H$61 -> 0.31497715 | J106: ='Data Sheet'!I58/'Data Sheet'!I$61 -> 0.33543738 | ... L106: ='Data Sheet'!K58/'Data Sheet'!K$61 -> 0.31874619
B107: ='Data Sheet'!A59 -> Borrowings | C107: ='Data Sheet'!B59/'Data Sheet'!B$61 -> 0.0014115924 | D107: ='Data Sheet'!C59/'Data Sheet'!C$61 -> 0.019751777 | E107: ='Data Sheet'!D59/'Data Sheet'!D$61 -> 0.018664286 | F107: ='Data Sheet'!E59/'Data Sheet'!E$61 -> 0.07993191 | G107: ='Data Sheet'!F59/'Data Sheet'!F$61 -> 0.10934832 | H107: ='Data Sheet'!G59/'Data Sheet'!G$61 -> 0.0010034575 | I107: ='Data Sheet'!H59/'Data Sheet'!H$61 -> 0.00081770043 | J107: ='Data Sheet'!I59/'Data Sheet'!I$61 -> 0.00074614585 | ... L107: ='Data Sheet'!K59/'Data Sheet'!K$61 -> 0.00047323578
B108: ='Data Sheet'!A60 -> Other Liabilities | C108: ='Data Sheet'!B60/'Data Sheet'!B$61 -> 0.80343487 | D108: ='Data Sheet'!C60/'Data Sheet'!C$61 -> 0.73753056 | E108: ='Data Sheet'!D60/'Data Sheet'!D$61 -> 0.78507616 | F108: ='Data Sheet'!E60/'Data Sheet'!E$61 -> 0.6854471 | G108: ='Data Sheet'!F60/'Data Sheet'!F$61 -> 0.64622622 | H108: ='Data Sheet'!G60/'Data Sheet'!G$61 -> 0.70850803 | I108: ='Data Sheet'!H60/'Data Sheet'!H$61 -> 0.67865551 | J108: ='Data Sheet'!I60/'Data Sheet'!I$61 -> 0.65898955 | ... L108: ='Data Sheet'!K60/'Data Sheet'!K$61 -> 0.67770427
B109: Total Liabilities | C109: ='Data Sheet'!B61/'Data Sheet'!B$61 -> 1 | D109: ='Data Sheet'!C61/'Data Sheet'!C$61 -> 1 | E109: ='Data Sheet'!D61/'Data Sheet'!D$61 -> 1 | F109: ='Data Sheet'!E61/'Data Sheet'!E$61 -> 1 | G109: ='Data Sheet'!F61/'Data Sheet'!F$61 -> 1 | H109: ='Data Sheet'!G61/'Data Sheet'!G$61 -> 1 | I109: ='Data Sheet'!H61/'Data Sheet'!H$61 -> 1 | J109: ='Data Sheet'!I61/'Data Sheet'!I$61 -> 1 | ... L109: ='Data Sheet'!K61/'Data Sheet'!K$61 -> 1
B111: ='Data Sheet'!A62 -> Net Block | C111: ='Data Sheet'!B62/'Data Sheet'!B$66 -> 0.12250075 | D111: ='Data Sheet'!C62/'Data Sheet'!C$66 -> 0.14203777 | E111: ='Data Sheet'!D62/'Data Sheet'!D$66 -> 0.1561249 | F111: ='Data Sheet'!E62/'Data Sheet'!E$66 -> 0.14485207 | G111: ='Data Sheet'!F62/'Data Sheet'!F$66 -> 0.13574039 | H111: ='Data Sheet'!G62/'Data Sheet'!G$66 -> 0.13495976 | I111: ='Data Sheet'!H62/'Data Sheet'!H$66 -> 0.11228867 | J111: ='Data Sheet'!I62/'Data Sheet'!I$66 -> 0.098654657 | ... L111: ='Data Sheet'!K62/'Data Sheet'!K$66 -> 0.061369775
B112: ='Data Sheet'!A63 -> Capital Work in Progress | C112: ='Data Sheet'!B63/'Data Sheet'!B$66 -> 0.018138432 | D112: ='Data Sheet'!C63/'Data Sheet'!C$66 -> 0.026851578 | E112: ='Data Sheet'!D63/'Data Sheet'!D$66 -> 0.030161809 | F112: ='Data Sheet'!E63/'Data Sheet'!E$66 -> 0.029169263 | G112: ='Data Sheet'!F63/'Data Sheet'!F$66 -> 0.037686158 | H112: ='Data Sheet'!G63/'Data Sheet'!G$66 -> 0.036718106 | I112: ='Data Sheet'!H63/'Data Sheet'!H$66 -> 0.041041691 | J112: ='Data Sheet'!I63/'Data Sheet'!I$66 -> 0.027210001 | ... L112: ='Data Sheet'!K63/'Data Sheet'!K$66 -> 0.028498564
B113: ='Data Sheet'!A64 -> Investments | C113: ='Data Sheet'!B64/'Data Sheet'!B$66 -> 0.016199703 | D113: ='Data Sheet'!C64/'Data Sheet'!C$66 -> 0.019209875 | E113: ='Data Sheet'!D64/'Data Sheet'!D$66 -> 0.020843079 | F113: ='Data Sheet'!E64/'Data Sheet'!E$66 -> 0.017664171 | G113: ='Data Sheet'!F64/'Data Sheet'!F$66 -> 0.018279546 | H113: ='Data Sheet'!G64/'Data Sheet'!G$66 -> 0.021118561 | I113: ='Data Sheet'!H64/'Data Sheet'!H$66 -> 0.022615798 | J113: ='Data Sheet'!I64/'Data Sheet'!I$66 -> 0.021045095 | ... L113: ='Data Sheet'!K64/'Data Sheet'!K$66 -> 0.016138223
B114: ='Data Sheet'!A65 -> Other Assets | C114: =('Data Sheet'!B65-SUM('Data Sheet'!B67:B69))/'Data Sheet'!B$66 -> 0.09805968 | D114: =('Data Sheet'!C65-SUM('Data Sheet'!C67:C69))/'Data Sheet'!C$66 -> 0.098984031 | E114: =('Data Sheet'!D65-SUM('Data Sheet'!D67:D69))/'Data Sheet'!D$66 -> 0.10310567 | F114: =('Data Sheet'!E65-SUM('Data Sheet'!E67:E69))/'Data Sheet'!E$66 -> 0.16693947 | G114: =('Data Sheet'!F65-SUM('Data Sheet'!F67:F69))/'Data Sheet'!F$66 -> 0.21953185 | H114: =('Data Sheet'!G65-SUM('Data Sheet'!G67:G69))/'Data Sheet'!G$66 -> 0.22616986 | I114: =('Data Sheet'!H65-SUM('Data Sheet'!H67:H69))/'Data Sheet'!H$66 -> 0.23988197 | J114: =('Data Sheet'!I65-SUM('Data Sheet'!I67:I69))/'Data Sheet'!I$66 -> 0.28641954 | ... L114: =('Data Sheet'!K65-SUM('Data Sheet'!K67:K69))/'Data Sheet'!K$66 -> 0.27818573
B115: ='Data Sheet'!A67 -> Receivables | C115: ='Data Sheet'!B67/'Data Sheet'!B$66 -> 0.085560542 | D115: ='Data Sheet'!C67/'Data Sheet'!C$66 -> 0.081558914 | E115: ='Data Sheet'!D67/'Data Sheet'!D$66 -> 0.13931441 | F115: ='Data Sheet'!E67/'Data Sheet'!E$66 -> 0.24192015 | G115: ='Data Sheet'!F67/'Data Sheet'!F$66 -> 0.20727267 | H115: ='Data Sheet'!G67/'Data Sheet'!G$66 -> 0.10675013 | I115: ='Data Sheet'!H67/'Data Sheet'!H$66 -> 0.077032293 | J115: ='Data Sheet'!I67/'Data Sheet'!I$66 -> 0.068121427 | ... L115: ='Data Sheet'!K67/'Data Sheet'!K$66 -> 0.042758563
B116: ='Data Sheet'!A68 -> Inventory | C116: ='Data Sheet'!B68/'Data Sheet'!B$66 -> 0.42421535 | D116: ='Data Sheet'!C68/'Data Sheet'!C$66 -> 0.41589082 | E116: ='Data Sheet'!D68/'Data Sheet'!D$66 -> 0.41538683 | F116: ='Data Sheet'!E68/'Data Sheet'!E$66 -> 0.39705354 | G116: ='Data Sheet'!F68/'Data Sheet'!F$66 -> 0.37564909 | H116: ='Data Sheet'!G68/'Data Sheet'!G$66 -> 0.3391078 | I116: ='Data Sheet'!H68/'Data Sheet'!H$66 -> 0.26902029 | J116: ='Data Sheet'!I68/'Data Sheet'!I$66 -> 0.20527874 | ... L116: ='Data Sheet'!K68/'Data Sheet'!K$66 -> 0.22178152
B117: ='Data Sheet'!A69 -> Cash & Bank | C117: ='Data Sheet'!B69/'Data Sheet'!B$66 -> 0.23532554 | D117: ='Data Sheet'!C69/'Data Sheet'!C$66 -> 0.215467 | E117: ='Data Sheet'!D69/'Data Sheet'!D$66 -> 0.1350633 | F117: ='Data Sheet'!E69/'Data Sheet'!E$66 -> 0.0024013362 | G117: ='Data Sheet'!F69/'Data Sheet'!F$66 -> 0.0058403038 | H117: ='Data Sheet'!G69/'Data Sheet'!G$66 -> 0.13517578 | I117: ='Data Sheet'!H69/'Data Sheet'!H$66 -> 0.23811928 | J117: ='Data Sheet'!I69/'Data Sheet'!I$66 -> 0.29327054 | ... L117: ='Data Sheet'!K69/'Data Sheet'!K$66 -> 0.35126763
B118: Total Assets | C118: ='Data Sheet'!B66/'Data Sheet'!B$66 -> 1 | D118: ='Data Sheet'!C66/'Data Sheet'!C$66 -> 1 | E118: ='Data Sheet'!D66/'Data Sheet'!D$66 -> 1 | F118: ='Data Sheet'!E66/'Data Sheet'!E$66 -> 1 | G118: ='Data Sheet'!F66/'Data Sheet'!F$66 -> 1 | H118: ='Data Sheet'!G66/'Data Sheet'!G$66 -> 1 | I118: ='Data Sheet'!H66/'Data Sheet'!H$66 -> 1 | J118: ='Data Sheet'!I66/'Data Sheet'!I$66 -> 1 | ... L118: ='Data Sheet'!K66/'Data Sheet'!K$66 -> 1

Sheet Financial Ratios
B2: ="Ratio Analysis- "&'Data Sheet'!B1 -> Ratio Analysis- HINDUSTAN AERONAUTICS LTD
B3: Years | C3: =IFERROR('Data Sheet'!B16,0) -> 42460 | D3: =IFERROR('Data Sheet'!C16,0) -> 42825 | E3: =IFERROR('Data Sheet'!D16,0) -> 43190 | F3: =IFERROR('Data Sheet'!E16,0) -> 43555 | G3: =IFERROR('Data Sheet'!F16,0) -> 43921 | H3: =IFERROR('Data Sheet'!G16,0) -> 44286 | I3: =IFERROR('Data Sheet'!H16,0) -> 44651 | J3: =IFERROR('Data Sheet'!I16,0) -> 45016 | ... L3: =IFERROR('Data Sheet'!K16,0) -> 45747 | M3: ='Historical FS'!M3 -> LTM | N3: Trend | O3: Mean | P3: Median
B5: Sales Growth | C5: =IFERROR('Historical FS'!C6/0-1,0) -> 0 | D5: =IFERROR('Historical FS'!D7,0) -> 0.071093475 | E5: =IFERROR('Historical FS'!E7,0) -> 0.031744988 | F5: =IFERROR('Historical FS'!F7,0) -> 0.080360739 | G5: =IFERROR('Historical FS'!G7,0) -> 0.071829268 | H5: =IFERROR('Historical FS'!H7,0) -> 0.067015588 | I5: =IFERROR('Historical FS'!I7,0) -> 0.075940726 | J5: =IFERROR('Historical FS'!J7,0) -> 0.093722101 | K5: =IFERROR('Historical FS'!K7,0) -> 0.12825643 | ... M5: =IFERROR('Historical FS'!M7,0) -> 0.036274872 | O5: =IFERROR(AVERAGE(D5:M5),0) -> 0.067598305 | P5: =IFERROR(MEDIAN(C5:M5),0) -> 0.071093475
B6: EBITDA | C6: =IFERROR('Historical FS'!C7/0-1,0) -> 0 | D6: =IFERROR('Historical FS'!D18/'Historical FS'!C18-1,0) -> 0.3059097 | E6: =IFERROR('Historical FS'!E18/'Historical FS'!D18-1,0) -> 0.067477845 | F6: =IFERROR('Historical FS'!F18/'Historical FS'!E18-1,0) -> 0.31964021 | G6: =IFERROR('Historical FS'!G18/'Historical FS'!F18-1,0) -> 0.079808307 | H6: =IFERROR('Historical FS'!H18/'Historical FS'!G18-1,0) -> 0.087447906 | I6: =IFERROR('Historical FS'!I18/'Historical FS'!H18-1,0) -> 0.013358957 | J6: =IFERROR('Historical FS'!J18/'Historical FS'!I18-1,0) -> 0.23457123 | K6: =IFERROR('Historical FS'!K18/'Historical FS'!J18-1,0) -> 0.4585815 | ... M6: =IFERROR('Historical FS'!M18/'Historical FS'!L18-1,0) -> 0.16848214 | O6: =IFERROR(AVERAGE(D6:M6),0) -> 0.17218892 | P6: =IFERROR(MEDIAN(C6:M6),0) -> 0.087447906
B7: PBT Growth | C7: =IFERROR('Historical FS'!C8/0-1,0) -> 0 | D7: =IFERROR('Historical FS'!D30/'Historical FS'!C30-1,0) -> 0.11777923 | E7: =IFERROR('Historical FS'!E30/'Historical FS'!D30-1,0) -> -0.097189122 | F7: =IFERROR('Historical FS'!F30/'Historical FS'!E30-1,0) -> 0.14856538 | G7: =IFERROR('Historical FS'!G30/'Historical FS'!F30-1,0) -> 0.06825474 | H7: =IFERROR('Historical FS'!H30/'Historical FS'!G30-1,0) -> 0.076619146 | I7: =IFERROR('Historical FS'!I30/'Historical FS'!H30-1,0) -> 0.21969287 | J7: =IFERROR('Historical FS'!J30/'Historical FS'!I30-1,0) -> 0.2459494 | K7: =IFERROR('Historical FS'!K30/'Historical FS'!J30-1,0) -> 0.57076273 | ... M7: =IFERROR('Historical FS'!M30/'Historical FS'!L30-1,0) -> 0.11615899 | O7: =IFERROR(AVERAGE(D7:M7),0) -> 0.15294186 | P7: =IFERROR(MEDIAN(C7:M7),0) -> 0.11615899
B8: Net Profit Growth | C8: =IFERROR('Historical FS'!C9/0-1,0) -> 0 | D8: =IFERROR('Historical FS'!D36/'Historical FS'!C36-1,0) -> 0.30958938 | E8: =IFERROR('Historical FS'!E36/'Historical FS'!D36-1,0) -> -0.24175464 | F8: =IFERROR('Historical FS'!F36/'Historical FS'!E36-1,0) -> 0.16977767 | G8: =IFERROR('Historical FS'!G36/'Historical FS'!F36-1,0) -> 0.23817194 | H8: =IFERROR('Historical FS'!H36/'Historical FS'!G36-1,0) -> 0.12589111 | I8: =IFERROR('Historical FS'!I36/'Historical FS'!H36-1,0) -> 0.5651831 | J8: =IFERROR('Historical FS'!J36/'Historical FS'!I36-1,0) -> 0.14721804 | K8: =IFERROR('Historical FS'!K36/'Historical FS'!J36-1,0) -> 0.30770472 | ... M8: =IFERROR('Historical FS'!M36/'Historical FS'!L36-1,0) -> 0.10672461 | O8: =IFERROR(AVERAGE(D8:M8),0) -> 0.18260135 | P8: =IFERROR(MEDIAN(C8:M8),0) -> 0.14721804
B9: Dividend Growth | C9: =IFERROR('Historical FS'!C10/0-1,0) -> 0 | D9: =IFERROR('Historical FS'!D44/'Historical FS'!C44-1,0) -> 0.27183988 | E9: =IFERROR('Historical FS'!E44/'Historical FS'!D44-1,0) -> 0.45363485 | F9: =IFERROR('Historical FS'!F44/'Historical FS'!E44-1,0) -> -0.38452028 | G9: =IFERROR('Historical FS'!G44/'Historical FS'!F44-1,0) -> 0.67930342 | H9: =IFERROR('Historical FS'!H44/'Historical FS'!G44-1,0) -> -0.097746998 | I9: =IFERROR('Historical FS'!I44/'Historical FS'!H44-1,0) -> 0.33333333 | J9: =IFERROR('Historical FS'!J44/'Historical FS'!I44-1,0) -> 0.37499626 | K9: =IFERROR('Historical FS'!K44/'Historical FS'!J44-1,0) -> 0.27273073 | ... M9: =IFERROR('Historical FS'!M44/'Historical FS'!L44-1,0) -> -1 | O9: =IFERROR(AVERAGE(D9:M9),0) -> 0.10464283 | P9: =IFERROR(MEDIAN(C9:M9),0) -> 0.27183988
B11: Gross Margin | C11: ='Historical FS'!C13 -> 0.2533401 | D11: ='Historical FS'!D13 -> 0.22902665 | E11: ='Historical FS'!E13 -> 0.23217497 | F11: ='Historical FS'!F13 -> 0.29590564 | G11: ='Historical FS'!G13 -> 0.30346987 | H11: ='Historical FS'!H13 -> 0.28600728 | I11: ='Historical FS'!I13 -> 0.37067395 | J11: ='Historical FS'!J13 -> 0.39983756 | ... M11: ='Historical FS'!M13 -> 0.30580182 | O11: =IFERROR(AVERAGE(C11:M11),0) -> 0.31672223 | P11: =IFERROR(MEDIAN(C11:M11),0) -> 0.30346987
B12: EBITDA Margin | C12: ='Historical FS'!C19 -> 0.14762061 | D12: ='Historical FS'!D19 -> 0.17998353 | E12: ='Historical FS'!E19 -> 0.18621698 | F12: ='Historical FS'!F19 -> 0.22746052 | G12: ='Historical FS'!G19 -> 0.2291538 | H12: ='Historical FS'!H19 -> 0.23354188 | I12: ='Historical FS'!I19 -> 0.21995799 | J12: ='Historical FS'!J19 -> 0.24828409 | ... M12: ='Historical FS'!M19 -> 0.35016561 | O12: =IFERROR(AVERAGE(C12:M12),0) -> 0.24126425 | P12: =IFERROR(MEDIAN(C12:M12),0) -> 0.2291538
B13: PBIT Margin | C13: =IFERROR((('Historical FS'!C18-'Historical FS'!C27)/'Historical FS'!C6),0) -> 0.096136289 | D13: =IFERROR((('Historical FS'!D18-'Historical FS'!D27)/'Historical FS'!D6),0) -> 0.14206247 | E13: =IFERROR((('Historical FS'!E18-'Historical FS'!E27)/'Historical FS'!E6),0) -> 0.13507749 | F13: =IFERROR((('Historical FS'!F18-'Historical FS'!F27)/'Historical FS'!F6),0) -> 0.17621801 | G13: =IFERROR((('Historical FS'!G18-'Historical FS'!G27)/'Historical FS'!G6),0) -> 0.18259225 | H13: =IFERROR((('Historical FS'!H18-'Historical FS'!H27)/'Historical FS'!H6),0) -> 0.18293993 | I13: =IFERROR((('Historical FS'!I18-'Historical FS'!I27)/'Historical FS'!I6),0) -> 0.1748512 | J13: =IFERROR((('Historical FS'!J18-'Historical FS'!J27)/'Historical FS'!J6),0) -> 0.18200714 | ... M13: =IFERROR((('Historical FS'!M18-'Historical FS'!M27)/'Historical FS'!M6),0) -> 0.30580182 | O13: =IFERROR(AVERAGE(C13:M13),0) -> 0.19269334 | P13: =IFERROR(MEDIAN(C13:M13),0) -> 0.18200714
B14: PBT Margin | C14: ='Historical FS'!C31 -> 0.1917415 | D14: ='Historical FS'!D31 -> 0.20009894 | E14: ='Historical FS'!E31 -> 0.17509317 | F14: ='Historical FS'!F31 -> 0.18614704 | G14: ='Historical FS'!G31 -> 0.18552624 | H14: ='Historical FS'!H31 -> 0.18719605 | I14: ='Historical FS'!I31 -> 0.21220657 | J14: ='Historical FS'!J31 -> 0.24174207 | ... M14: ='Historical FS'!M31 -> 0.37781259 | O14: =IFERROR(AVERAGE(C14:M14),0) -> 0.24044461 | P14: =IFERROR(MEDIAN(C14:M14),0) -> 0.20009894
B15: Net Profit Margin | C15: ='Historical FS'!C37 -> 0.11959901 | D15: ='Historical FS'!D37 -> 0.14622962 | E15: ='Historical FS'!E37 -> 0.10746641 | F15: ='Historical FS'!F37 -> 0.11636096 | G15: ='Historical FS'!G37 -> 0.13441961 | H15: ='Historical FS'!H37 -> 0.14183658 | I15: ='Historical FS'!I37 -> 0.20633127 | J15: ='Historical FS'!J37 -> 0.21642331 | ... M15: ='Historical FS'!M37 -> 0.28832778 | O15: =IFERROR(AVERAGE(C15:M15),0) -> 0.18161943 | P15: =IFERROR(MEDIAN(C15:M15),0) -> 0.14622962
B17: Sales Expenses (% of Sales) | C17: ='Historical FS'!C16 -> 0.10571949 | D17: ='Historical FS'!D16 -> 0.049043116 | E17: ='Historical FS'!E16 -> 0.045957989 | F17: ='Historical FS'!F16 -> 0.068445122 | G17: ='Historical FS'!G16 -> 0.074316069 | H17: ='Historical FS'!H16 -> 0.052465397 | I17: ='Historical FS'!I16 -> 0.15071596 | J17: ='Historical FS'!J16 -> 0.15155347 | ... M17: ='Historical FS'!M16 -> 0.044363799 | O17: =IFERROR(AVERAGE(C17:M17),0) -> 0.083524126 | P17: =IFERROR(MEDIAN(C17:M17),0) -> 0.07216596
B18: Depreciation (% of Sales) | C18: ='Historical FS'!C28 -> 0.051484321 | D18: ='Historical FS'!D28 -> 0.03792106 | E18: ='Historical FS'!E28 -> 0.051139487 | F18: ='Historical FS'!F28 -> 0.051242503 | G18: ='Historical FS'!G28 -> 0.046561555 | H18: ='Historical FS'!H28 -> 0.050601949 | I18: ='Historical FS'!I28 -> 0.045106787 | J18: ='Historical FS'!J28 -> 0.066276953 | ... M18: ='Historical FS'!M28 -> 0.044363799 | O18: =IFERROR(AVERAGE(C18:M18),0) -> 0.048570914 | P18: =IFERROR(MEDIAN(C18:M18),0) -> 0.046561555
B19: Operating Income (% of Sales) | C19: =C13 -> 0.096136289 | D19: =D13 -> 0.14206247 | E19: =E13 -> 0.13507749 | F19: =F13 -> 0.17621801 | G19: =G13 -> 0.18259225 | H19: =H13 -> 0.18293993 | I19: =I13 -> 0.1748512 | J19: =J13 -> 0.18200714 | ... M19: =M13 -> 0.30580182 | O19: =IFERROR(AVERAGE(C19:M19),0) -> 0.19269334 | P19: =IFERROR(MEDIAN(C19:M19),0) -> 0.18200714
B21: Return on Capital Employed | C21: =IFERROR(('Historical FS'!C18-'Historical FS'!C27)/(SUM('Historical FS'!C51:C53)),0) -> 0.14498479 | D21: =IFERROR(('Historical FS'!D18-'Historical FS'!D27)/(SUM('Historical FS'!D51:D53)),0) -> 0.18776112 | E21: =IFERROR(('Historical FS'!E18-'Historical FS'!E27)/(SUM('Historical FS'!E51:E53)),0) -> 0.24017427 | F21: =IFERROR(('Historical FS'!F18-'Historical FS'!F27)/(SUM('Historical FS'!F51:F53)),0) -> 0.2176627 | G21: =IFERROR(('Historical FS'!G18-'Historical FS'!G27)/(SUM('Historical FS'!G51:G53)),0) -> 0.20420454 | H21: =IFERROR(('Historical FS'!H18-'Historical FS'!H27)/(SUM('Historical FS'!H51:H53)),0) -> 0.27046852 | I21: =IFERROR(('Historical FS'!I18-'Historical FS'!I27)/(SUM('Historical FS'!I51:I53)),0) -> 0.22232988 | J21: =IFERROR(('Historical FS'!J18-'Historical FS'!J27)/(SUM('Historical FS'!J51:J53)),0) -> 0.2074595 | ... M21: =IFERROR(('Historical FS'!M18-'Historical FS'!M27)/(SUM('Historical FS'!M51:M53)),0) -> 0 | O21: =IFERROR(AVERAGE(C21:M21),0) -> 0.2015722 | P21: =IFERROR(MEDIAN(C21:M21),0) -> 0.2176627
B22: Retained Earnings % | C22: ='Historical FS'!C47 -> 0.68616974 | D22: ='Historical FS'!D47 -> 0.69521603 | E22: ='Historical FS'!E47 -> 0.45950006 | F22: ='Historical FS'!F47 -> 0.7156154 | G22: ='Historical FS'!G47 -> 0.61429587 | H22: ='Historical FS'!H47 -> 0.69090909 | I22: ='Historical FS'!I47 -> 0.73669457 | J22: ='Historical FS'!J47 -> 0.68441572 | ... M22: ='Historical FS'!M47 -> 1 | O22: =IFERROR(AVERAGE(C22:M22),0) -> 0.69598517 | P22: =IFERROR(MEDIAN(C22:M22),0) -> 0.69090909
B23: Return on Equity % | C23: =IFERROR('Historical FS'!C36/SUM('Historical FS'!C51:C53),0) -> 0.18036932 | D23: =IFERROR('Historical FS'!D36/SUM('Historical FS'!D51:D53),0) -> 0.19326875 | E23: =IFERROR('Historical FS'!E36/SUM('Historical FS'!E51:E53),0) -> 0.19108045 | F23: =IFERROR('Historical FS'!F36/SUM('Historical FS'!F51:F53),0) -> 0.14372787 | G23: =IFERROR('Historical FS'!G36/SUM('Historical FS'!G51:G53),0) -> 0.15033 | H23: =IFERROR('Historical FS'!H36/SUM('Historical FS'!H51:H53),0) -> 0.20969905 | I23: =IFERROR('Historical FS'!I36/SUM('Historical FS'!I51:I53),0) -> 0.26235797 | J23: =IFERROR('Historical FS'!J36/SUM('Historical FS'!J51:J53),0) -> 0.24668851 | ... M23: =IFERROR('Historical FS'!M36/SUM('Historical FS'!M51:M53),0) -> 0 | O23: =IFERROR(AVERAGE(C23:M23),0) -> 0.18885141 | P23: =IFERROR(MEDIAN(C23:M23),0) -> 0.19326875
B24: Self Sustained Growth Rate | C24: =IFERROR(C22*C23,0) -> 0.12376397 | D24: =IFERROR(D22*D23,0) -> 0.13436354 | E24: =IFERROR(E22*E23,0) -> 0.087801478 | F24: =IFERROR(F22*F23,0) -> 0.10285388 | G24: =IFERROR(G22*G23,0) -> 0.092347102 | H24: =IFERROR(H22*H23,0) -> 0.14488298 | I24: =IFERROR(I22*I23,0) -> 0.19327769 | J24: =IFERROR(J22*J23,0) -> 0.1688375 | ... M24: =IFERROR(M22*M23,0) -> 0 | O24: =IFERROR(AVERAGE(C24:M24),0) -> 0.12649251 | P24: =IFERROR(MEDIAN(C24:M24),0) -> 0.13436354
B25: Interest Coverage Ratio | C25: =IFERROR(('Historical FS'!C18-'Historical FS'!C27)/'Historical FS'!C24,0) -> 273.0678 | D25: =IFERROR(('Historical FS'!D18-'Historical FS'!D27)/'Historical FS'!D24,0) -> 155.01581 | E25: =IFERROR(('Historical FS'!E18-'Historical FS'!E27)/'Historical FS'!E24,0) -> 72.25881 | F25: =IFERROR(('Historical FS'!F18-'Historical FS'!F27)/'Historical FS'!F24,0) -> 19.852309 | G25: =IFERROR(('Historical FS'!G18-'Historical FS'!G27)/'Historical FS'!G24,0) -> 10.889402 | H25: =IFERROR(('Historical FS'!H18-'Historical FS'!H27)/'Historical FS'!H24,0) -> 15.684702 | I25: =IFERROR(('Historical FS'!I18-'Historical FS'!I27)/'Historical FS'!I24,0) -> 65.984672 | J25: =IFERROR(('Historical FS'!J18-'Historical FS'!J27)/'Historical FS'!J24,0) -> 76.090514 | ... M25: =IFERROR(('Historical FS'!M18-'Historical FS'!M27)/'Historical FS'!M24,0) -> 1069.4662 | O25: =IFERROR(AVERAGE(C25:M25),0) -> 212.45994 | P25: =IFERROR(MEDIAN(C25:M25),0) -> 76.090514
B27: Debtor Turnover Ratio | C27: =IFERROR('Historical FS'!C6/'Historical FS'!C63,0) -> 3.4647191 | D27: =IFERROR('Historical FS'!D6/(('Historical FS'!D63+'Historical FS'!C63)/2),0) -> 3.963741 | E27: =IFERROR('Historical FS'!E6/(('Historical FS'!E63+'Historical FS'!D63)/2),0) -> 3.3759108 | F27: =IFERROR('Historical FS'!F6/(('Historical FS'!F63+'Historical FS'!E63)/2),0) -> 2.0831316 | G27: =IFERROR('Historical FS'!G6/(('Historical FS'!G63+'Historical FS'!F63)/2),0) -> 1.8102734 | H27: =IFERROR('Historical FS'!H6/(('Historical FS'!H63+'Historical FS'!G63)/2),0) -> 2.7075215 | I27: =IFERROR('Historical FS'!I6/(('Historical FS'!I63+'Historical FS'!H63)/2),0) -> 4.7761441 | J27: =IFERROR('Historical FS'!J6/(('Historical FS'!J63+'Historical FS'!I63)/2),0) -> 5.7532944 | K27: =IFERROR('Historical FS'!K6/(('Historical FS'!K63+'Historical FS'!J63)/2),0) -> 6.508351 | ... M27: =IFERROR('Historical FS'!M6/(('Historical FS'!M63+'Historical FS'!L63)/2),0) -> 13.815073 | O27: =IFERROR(AVERAGE(C27:M27),0) -> 4.9951054 | P27: =IFERROR(MEDIAN(C27:M27),0) -> 3.963741
B28: Creditor Turnover Ratio | C28: =IFERROR('Historical FS'!C6/'Historical FS'!C54,0) -> 0.36896985 | D28: =IFERROR('Historical FS'!D6/(('Historical FS'!D54+'Historical FS'!C54)/2),0) -> 0.42951507 | E28: =IFERROR('Historical FS'!E6/(('Historical FS'!E54+'Historical FS'!D54)/2),0) -> 0.48602246 | F28: =IFERROR('Historical FS'!F6/(('Historical FS'!F54+'Historical FS'!E54)/2),0) -> 0.54558705 | G28: =IFERROR('Historical FS'!G6/(('Historical FS'!G54+'Historical FS'!F54)/2),0) -> 0.60988559 | H28: =IFERROR('Historical FS'!H6/(('Historical FS'!H54+'Historical FS'!G54)/2),0) -> 0.62996415 | I28: =IFERROR('Historical FS'!I6/(('Historical FS'!I54+'Historical FS'!H54)/2),0) -> 0.62717233 | J28: =IFERROR('Historical FS'!J6/(('Historical FS'!J54+'Historical FS'!I54)/2),0) -> 0.62228297 | K28: =IFERROR('Historical FS'!K6/(('Historical FS'!K54+'Historical FS'!J54)/2),0) -> 0.6240035 | ... M28: =IFERROR('Historical FS'!M6/(('Historical FS'!M54+'Historical FS'!L54)/2),0) -> 0.87163786 | O28: =IFERROR(AVERAGE(C28:M28),0) -> 0.57356385 | P28: =IFERROR(MEDIAN(C28:M28),0) -> 0.60988559
B29: Inventory Turnover Ratio | C29: =IFERROR('Historical FS'!C6/'Historical FS'!C64,0) -> 0.69880367 | D29: =IFERROR('Historical FS'!D6/(('Historical FS'!D64+'Historical FS'!C64)/2),0) -> 0.78898268 | E29: =IFERROR('Historical FS'!E6/(('Historical FS'!E64+'Historical FS'!D64)/2),0) -> 0.88929342 | F29: =IFERROR('Historical FS'!F6/(('Historical FS'!F64+'Historical FS'!E64)/2),0) -> 0.98616155 | G29: =IFERROR('Historical FS'!G6/(('Historical FS'!G64+'Historical FS'!F64)/2),0) -> 1.0510278 | H29: =IFERROR('Historical FS'!H6/(('Historical FS'!H64+'Historical FS'!G64)/2),0) -> 1.1928253 | I29: =IFERROR('Historical FS'!I6/(('Historical FS'!I64+'Historical FS'!H64)/2),0) -> 1.4391339 | J29: =IFERROR('Historical FS'!J6/(('Historical FS'!J64+'Historical FS'!I64)/2),0) -> 1.7697661 | K29: =IFERROR('Historical FS'!K6/(('Historical FS'!K64+'Historical FS'!J64)/2),0) -> 2.0083949 | ... M29: =IFERROR('Historical FS'!M6/(('Historical FS'!M64+'Historical FS'!L64)/2),0) -> 2.6634892 | O29: =IFERROR(AVERAGE(C29:M29),0) -> 1.3665003 | P29: =IFERROR(MEDIAN(C29:M29),0) -> 1.1928253
B30: Fixed Asset Turnover Ratio | C30: =IFERROR('Historical FS'!C6/'Historical FS'!C57,0) -> 2.4199301 | D30: =IFERROR('Historical FS'!D6/(('Historical FS'!D57+'Historical FS'!C57)/2),0) -> 2.5149172 | E30: =IFERROR('Historical FS'!E6/(('Historical FS'!E57+'Historical FS'!D57)/2),0) -> 2.4832412 | F30: =IFERROR('Historical FS'!F6/(('Historical FS'!F57+'Historical FS'!E57)/2),0) -> 2.6631935 | G30: =IFERROR('Historical FS'!G6/(('Historical FS'!G57+'Historical FS'!F57)/2),0) -> 2.8947009 | H30: =IFERROR('Historical FS'!H6/(('Historical FS'!H57+'Historical FS'!G57)/2),0) -> 3.1511034 | I30: =IFERROR('Historical FS'!I6/(('Historical FS'!I57+'Historical FS'!H57)/2),0) -> 3.5343733 | J30: =IFERROR('Historical FS'!J6/(('Historical FS'!J57+'Historical FS'!I57)/2),0) -> 3.9598391 | K30: =IFERROR('Historical FS'!K6/(('Historical FS'!K57+'Historical FS'!J57)/2),0) -> 4.4772575 | ... M30: =IFERROR('Historical FS'!M6/(('Historical FS'!M57+'Historical FS'!L57)/2),0) -> 9.6254662 | O30: =IFERROR(AVERAGE(C30:M30),0) -> 3.8495811 | P30: =IFERROR(MEDIAN(C30:M30),0) -> 3.1511034
B31: Capital Turnover Ratio | C31: =IFERROR(('Historical FS'!C6)/('Historical FS'!C51+'Historical FS'!C52),0) -> 1.5190258 | D31: =IFERROR(('Historical FS'!D6)/(('Historical FS'!D51+'Historical FS'!D52)+('Historical FS'!C51+'Historical FS'!C52)/2),0) -> 0.99306291 | E31: =IFERROR(('Historical FS'!E6)/(('Historical FS'!E51+'Historical FS'!E52)+('Historical FS'!D51+'Historical FS'!D52)/2),0) -> 1.172818 | F31: =IFERROR(('Historical FS'!F6)/(('Historical FS'!F51+'Historical FS'!F52)+('Historical FS'!E51+'Historical FS'!E52)/2),0) -> 1.1882826 | G31: =IFERROR(('Historical FS'!G6)/(('Historical FS'!G51+'Historical FS'!G52)+('Historical FS'!F51+'Historical FS'!F52)/2),0) -> 1.111749 | H31: =IFERROR(('Historical FS'!H6)/(('Historical FS'!H51+'Historical FS'!H52)+('Historical FS'!G51+'Historical FS'!G52)/2),0) -> 1.0378338 | I31: =IFERROR(('Historical FS'!I6)/(('Historical FS'!I51+'Historical FS'!I52)+('Historical FS'!H51+'Historical FS'!H52)/2),0) -> 0.91100637 | J31: =IFERROR(('Historical FS'!J6)/(('Historical FS'!J51+'Historical FS'!J52)+('Historical FS'!I51+'Historical FS'!I52)/2),0) -> 0.81036718 | K31: =IFERROR(('Historical FS'!K6)/(('Historical FS'!K51+'Historical FS'!K52)+('Historical FS'!J51+'Historical FS'!J52)/2),0) -> 0.74237362 | ... M31: =IFERROR(('Historical FS'!M6)/(('Historical FS'!M51+'Historical FS'!M52)+('Historical FS'!L51+'Historical FS'!L52)/2),0) -> 1.8355233 | O31: =IFERROR(AVERAGE(C31:M31),0) -> 1.0861164 | P31: =IFERROR(MEDIAN(C31:M31),0) -> 1.0378338
B33: Debtors Days | C33: =IFERROR(365/C27:C27,0) -> 105.34764 | D33: =IFERROR(365/D27:D27,0) -> 92.084725 | E33: =IFERROR(365/E27:E27,0) -> 108.11897 | F33: =IFERROR(365/F27:F27,0) -> 175.21697 | G33: =IFERROR(365/G27:G27,0) -> 201.627 | H33: =IFERROR(365/H27:H27,0) -> 134.80964 | I33: =IFERROR(365/I27:I27,0) -> 76.421479 | J33: =IFERROR(365/J27:J27,0) -> 63.441913 | ... M33: =IFERROR(365/M27:M27,0) -> 26.420417 | O33: =IFERROR(AVERAGE(C33:M33),0) -> 99.467811 | P33: =IFERROR(MEDIAN(C33:M33),0) -> 92.084725
B34: Payable Days | C34: =IFERROR(365/C28,0) -> 989.24071 | D34: =IFERROR(365/D28,0) -> 849.79557 | E34: =IFERROR(365/E28,0) -> 750.9941 | F34: =IFERROR(365/F28,0) -> 669.00415 | G34: =IFERROR(365/G28,0) -> 598.4729 | H34: =IFERROR(365/H28,0) -> 579.39805 | I34: =IFERROR(365/I28,0) -> 581.9772 | J34: =IFERROR(365/J28,0) -> 586.54987 | ... M34: =IFERROR(365/M28,0) -> 418.75189 | O34: =IFERROR(AVERAGE(C34:M34),0) -> 667.97655 | P34: =IFERROR(MEDIAN(C34:M34),0) -> 598.4729
B35: Inventory Days | C35: =IFERROR(365/C29,0) -> 522.32124 | D35: =IFERROR(365/D29,0) -> 462.62106 | E35: =IFERROR(365/E29,0) -> 410.43821 | F35: =IFERROR(365/F29,0) -> 370.12191 | G35: =IFERROR(365/G29,0) -> 347.27912 | H35: =IFERROR(365/H29,0) -> 305.99619 | I35: =IFERROR(365/I29,0) -> 253.62476 | J35: =IFERROR(365/J29,0) -> 206.24195 | ... M35: =IFERROR(365/M29,0) -> 137.03829 | O35: =IFERROR(AVERAGE(C35:M35),0) -> 312.17057 | P35: =IFERROR(MEDIAN(C35:M35),0) -> 305.99619
B36: Cash Conversion Cycle | C36: =IFERROR((C33+C35-C34),0) -> -361.57183 | D36: =IFERROR((D33+D35-D34),0) -> -295.08978 | E36: =IFERROR((E33+E35-E34),0) -> -232.43692 | F36: =IFERROR((F33+F35-F34),0) -> -123.66528 | G36: =IFERROR((G33+G35-G34),0) -> -49.566783 | H36: =IFERROR((H33+H35-H34),0) -> -138.59222 | I36: =IFERROR((I33+I35-I34),0) -> -251.93096 | J36: =IFERROR((J33+J35-J34),0) -> -316.86602 | ... M36: =IFERROR((M33+M35-M34),0) -> -255.29319 | O36: =IFERROR(AVERAGE(C36:M36),0) -> -256.33817 | P36: =IFERROR(MEDIAN(C36:M36),0) -> -255.29319
B38: CFO / Sales | C38: =IFERROR('Historical FS'!C72/'Historical FS'!C6,0) -> 0 | D38: =IFERROR('Historical FS'!D72/'Historical FS'!D6,0) -> -0.022534919 | E38: =IFERROR('Historical FS'!E72/'Historical FS'!E6,0) -> -0.040367737 | F38: =IFERROR('Historical FS'!F72/'Historical FS'!F6,0) -> -0.38486006 | G38: =IFERROR('Historical FS'!G72/'Historical FS'!G6,0) -> 0.071223064 | H38: =IFERROR('Historical FS'!H72/'Historical FS'!H6,0) -> 0.66064105 | I38: =IFERROR('Historical FS'!I72/'Historical FS'!I6,0) -> 0.41320559 | J38: =IFERROR('Historical FS'!J72/'Historical FS'!J6,0) -> 0.32790765 | ... M38: =IFERROR('Historical FS'!M72/'Historical FS'!M6,0) -> 0 | O38: =IFERROR(AVERAGE(C38:M38),0) -> 0.15784117 | P38: =IFERROR(MEDIAN(C38:M38),0) -> 0.071223064
B39: CFO / Total Assets | C39: =IFERROR('Historical FS'!C72/'Historical FS'!C68,0) -> 0 | D39: =IFERROR('Historical FS'!D72/'Historical FS'!D68,0) -> -0.0078173768 | E39: =IFERROR('Historical FS'!E72/'Historical FS'!E68,0) -> -0.015426326 | F39: =IFERROR('Historical FS'!F72/'Historical FS'!F68,0) -> -0.14953066 | G39: =IFERROR('Historical FS'!G72/'Historical FS'!G68,0) -> 0.028179244 | H39: =IFERROR('Historical FS'!H72/'Historical FS'!H68,0) -> 0.28470846 | I39: =IFERROR('Historical FS'!I72/'Historical FS'!I68,0) -> 0.16883647 | J39: =IFERROR('Historical FS'!J72/'Historical FS'!J68,0) -> 0.12745713 | ... M39: =IFERROR('Historical FS'!M72/'Historical FS'!M68,0) -> 0 | O39: =IFERROR(AVERAGE(C39:M39),0) -> 0.060322881 | P39: =IFERROR(MEDIAN(C39:M39),0) -> 0.028179244
B40: CFO / Total Debt | C40: =IFERROR('Historical FS'!C72/'Historical FS'!C53,0) -> 0 | D40: =IFERROR('Historical FS'!D72/'Historical FS'!D53,0) -> -0.39578095 | E40: =IFERROR('Historical FS'!E72/'Historical FS'!E53,0) -> -0.82651572 | F40: =IFERROR('Historical FS'!F72/'Historical FS'!F53,0) -> -1.8707254 | G40: =IFERROR('Historical FS'!G72/'Historical FS'!G53,0) -> 0.25770166 | H40: =IFERROR('Historical FS'!H72/'Historical FS'!H53,0) -> 283.72748 | I40: =IFERROR('Historical FS'!I72/'Historical FS'!I53,0) -> 206.47717 | J40: =IFERROR('Historical FS'!J72/'Historical FS'!J53,0) -> 170.82066 | ... M40: =IFERROR('Historical FS'!M72/'Historical FS'!M53,0) -> 0 | O40: =IFERROR(AVERAGE(C40:M40),0) -> 98.862109 | P40: =IFERROR(MEDIAN(C40:M40),0) -> 0.25770166

Sheet Reg Forcast
B1: ='Data Sheet'!$B$1&" - "&" Linear Regression Forecasting" -> HINDUSTAN AERONAUTICS LTD - Linear Regression Forecasting
B2: Year | C2: ='Data Sheet'!B16 -> 42460 | D2: =C2+365 -> 42825 | E2: =D2+365 -> 43190 | F2: =E2+365 -> 43555 | G2: =F2+365 -> 43920 | H2: =G2+365 -> 44285 | I2: =H2+365 -> 44650 | J2: =I2+365 -> 45015 | K2: =J2+365 -> 45380 | ... Q2: =P2+365 -> 47570
B3: Weightage | C3: =1 -> 1 | D3: =C3+1 -> 2 | E3: =D3+1 -> 3 | F3: =E3+1 -> 4 | G3: =F3+1 -> 5 | H3: =G3+1 -> 6 | I3: =H3+1 -> 7 | J3: =I3+1 -> 8 | K3: =J3+1 -> 9 | ... Q3: =P3+1 -> 15
B5: ='Data Sheet'!A17 -> Sales | C5: =IFERROR('Historical FS'!C6,0) -> 16758.5 | D5: =IFERROR('Historical FS'!D6,0) -> 17949.92 | E5: =IFERROR('Historical FS'!E6,0) -> 18519.74 | F5: =IFERROR('Historical FS'!F6,0) -> 20008 | G5: =IFERROR('Historical FS'!G6,0) -> 21445.16 | H5: =IFERROR('Historical FS'!H6,0) -> 22882.32 | I5: =IFERROR('Historical FS'!I6,0) -> 24620.02 | J5: =IFERROR('Historical FS'!J6,0) -> 26927.46 | ... L5: =IFERROR('Historical FS'!L6,0) -> 30980.95 | M5: =_xlfn.FORECAST.LINEAR($M$3,$C$5:$L$5,$C$3:$L$3) -> 32125.048 | N5: =_xlfn.FORECAST.LINEAR(N3,$C$5:$L$5,$C$3:$L$3) -> 33775.545 | O5: =_xlfn.FORECAST.LINEAR(O3,$C$5:$L$5,$C$3:$L$3) -> 35426.042 | P5: =_xlfn.FORECAST.LINEAR(P3,$C$5:$L$5,$C$3:$L$3) -> 37076.539 | Q5: =_xlfn.FORECAST.LINEAR(Q3,$C$5:$L$5,$C$3:$L$3) -> 38727.036
B6: Sales Growth | C6: =IFERROR(C5/C5-1,0) -> 0 | D6: =IFERROR(D5/C5-1,0) -> 0.071093475 | E6: =IFERROR(E5/D5-1,0) -> 0.031744988 | F6: =IFERROR(F5/E5-1,0) -> 0.080360739 | G6: =IFERROR(G5/F5-1,0) -> 0.071829268 | H6: =IFERROR(H5/G5-1,0) -> 0.067015588 | I6: =IFERROR(I5/H5-1,0) -> 0.075940726 | J6: =IFERROR(J5/I5-1,0) -> 0.093722101 | K6: =IFERROR(K5/J5-1,0) -> 0.12825643 | ... Q6: =IFERROR(Q5/P5-1,0) -> 0.044515938
B8: COGS | C8: =IFERROR('Historical FS'!C9,0) -> 12512.9 | D8: =IFERROR('Historical FS'!D9,0) -> 13838.91 | E8: =IFERROR('Historical FS'!E9,0) -> 14219.92 | F8: =IFERROR('Historical FS'!F9,0) -> 14087.52 | G8: =IFERROR('Historical FS'!G9,0) -> 14937.2 | H8: =IFERROR('Historical FS'!H9,0) -> 16337.81 | I8: =IFERROR('Historical FS'!I9,0) -> 15494.02 | J8: =IFERROR('Historical FS'!J9,0) -> 16160.85 | ... L8: =IFERROR('Historical FS'!L9,0) -> 19124.16 | M8: =_xlfn.FORECAST.LINEAR(M3,$C$8:$L$8,$C$3:$L$3) -> 18759.55 | N8: =_xlfn.FORECAST.LINEAR(N3,$C$8:$L$8,$C$3:$L$3) -> 19367.058 | O8: =_xlfn.FORECAST.LINEAR(O3,$C$8:$L$8,$C$3:$L$3) -> 19974.565 | P8: =_xlfn.FORECAST.LINEAR(P3,$C$8:$L$8,$C$3:$L$3) -> 20582.073 | Q8: =_xlfn.FORECAST.LINEAR(Q3,$C$8:$L$8,$C$3:$L$3) -> 21189.581
B9: COGS Growth | C9: =IFERROR(C8/C8-1,0) -> 0 | D9: =IFERROR(D8/C8-1,0) -> 0.10597144 | E9: =IFERROR(E8/D8-1,0) -> 0.027531793 | F9: =IFERROR(F8/E8-1,0) -> -0.0093108822 | G9: =IFERROR(G8/F8-1,0) -> 0.060314378 | H9: =IFERROR(H8/G8-1,0) -> 0.093766569 | I9: =IFERROR(I8/H8-1,0) -> -0.051646457 | J9: =IFERROR(J8/I8-1,0) -> 0.043037895 | K9: =IFERROR(K8/J8-1,0) -> 0.080963563 | ... Q9: =IFERROR(Q8/P8-1,0) -> 0.029516348
B11: Gross Profit | C11: =IFERROR('Historical FS'!C12,0) -> 4245.6 | D11: =IFERROR('Historical FS'!D12,0) -> 4111.01 | E11: =IFERROR('Historical FS'!E12,0) -> 4299.82 | F11: =IFERROR('Historical FS'!F12,0) -> 5920.48 | G11: =IFERROR('Historical FS'!G12,0) -> 6507.96 | H11: =IFERROR('Historical FS'!H12,0) -> 6544.51 | I11: =IFERROR('Historical FS'!I12,0) -> 9126 | J11: =IFERROR('Historical FS'!J12,0) -> 10766.61 | ... L11: =IFERROR('Historical FS'!L12,0) -> 11856.79 | M11: =_xlfn.FORECAST.LINEAR(M3,$C$11:$L$11,$C$3:$L$3) -> 13365.498 | N11: =_xlfn.FORECAST.LINEAR(N3,$C$11:$L$11,$C$3:$L$3) -> 14408.487 | O11: =_xlfn.FORECAST.LINEAR(O3,$C$11:$L$11,$C$3:$L$3) -> 15451.477 | P11: =_xlfn.FORECAST.LINEAR(P3,$C$11:$L$11,$C$3:$L$3) -> 16494.466 | Q11: =_xlfn.FORECAST.LINEAR(Q3,$C$11:$L$11,$C$3:$L$3) -> 17537.455
B12: Gross Profit Growth | C12: =IFERROR(C11/C11-1,0) -> 0 | D12: =IFERROR(D11/C11-1,0) -> -0.031701055 | E12: =IFERROR(E11/D11-1,0) -> 0.045927886 | F12: =IFERROR(F11/E11-1,0) -> 0.37691345 | G12: =IFERROR(G11/F11-1,0) -> 0.099228441 | H12: =IFERROR(H11/G11-1,0) -> 0.0056161992 | I12: =IFERROR(I11/H11-1,0) -> 0.39445123 | J12: =IFERROR(J11/I11-1,0) -> 0.17977318 | K12: =IFERROR(K11/J11-1,0) -> 0.19924377 | ... Q12: =IFERROR(Q11/P11-1,0) -> 0.06323268
B14: Selling & General Expenses | C14: =IFERROR('Historical FS'!C15,0) -> 1771.7 | D14: =IFERROR('Historical FS'!D15,0) -> 880.32 | E14: =IFERROR('Historical FS'!E15,0) -> 851.13 | F14: =IFERROR('Historical FS'!F15,0) -> 1369.45 | G14: =IFERROR('Historical FS'!G15,0) -> 1593.72 | H14: =IFERROR('Historical FS'!H15,0) -> 1200.53 | I14: =IFERROR('Historical FS'!I15,0) -> 3710.63 | J14: =IFERROR('Historical FS'!J15,0) -> 4080.95 | ... L14: =IFERROR('Historical FS'!L15,0) -> 2235.77 | M14: =_xlfn.FORECAST.LINEAR(M3,$C$14:$L$14,$C$3:$L$3) -> 3515.9513 | N14: =_xlfn.FORECAST.LINEAR(N3,$C$14:$L$14,$C$3:$L$3) -> 3776.0441 | O14: =_xlfn.FORECAST.LINEAR(O3,$C$14:$L$14,$C$3:$L$3) -> 4036.1369 | P14: =_xlfn.FORECAST.LINEAR(P3,$C$14:$L$14,$C$3:$L$3) -> 4296.2297 | Q14: =_xlfn.FORECAST.LINEAR(Q3,$C$14:$L$14,$C$3:$L$3) -> 4556.3225
B15: S&G Growth | C15: =IFERROR(C14/C14-1,0) -> 0 | D15: =IFERROR(D14/C14-1,0) -> -0.5031213 | E15: =IFERROR(E14/D14-1,0) -> -0.033158397 | F15: =IFERROR(F14/E14-1,0) -> 0.60897865 | G15: =IFERROR(G14/F14-1,0) -> 0.16376648 | H15: =IFERROR(H14/G14-1,0) -> -0.24671209 | I15: =IFERROR(I14/H14-1,0) -> 2.0908266 | J15: =IFERROR(J14/I14-1,0) -> 0.099799764 | K15: =IFERROR(K14/J14-1,0) -> -0.22561903 | ... Q15: =IFERROR(Q14/P14-1,0) -> 0.060539777
B17: EBITDA | C17: =IFERROR('Historical FS'!C18,0) -> 2473.9 | D17: =IFERROR('Historical FS'!D18,0) -> 3230.69 | E17: =IFERROR('Historical FS'!E18,0) -> 3448.69 | F17: =IFERROR('Historical FS'!F18,0) -> 4551.03 | G17: =IFERROR('Historical FS'!G18,0) -> 4914.24 | H17: =IFERROR('Historical FS'!H18,0) -> 5343.98 | I17: =IFERROR('Historical FS'!I18,0) -> 5415.37 | J17: =IFERROR('Historical FS'!J18,0) -> 6685.66 | ... L17: =IFERROR('Historical FS'!L18,0) -> 9621.02 | M17: =_xlfn.FORECAST.LINEAR(M3,$C$17:$L$17,$C$3:$L$3) -> 9849.5467 | N17: =_xlfn.FORECAST.LINEAR(N3,$C$17:$L$17,$C$3:$L$3) -> 10632.443 | O17: =_xlfn.FORECAST.LINEAR(O3,$C$17:$L$17,$C$3:$L$3) -> 11415.34 | P17: =_xlfn.FORECAST.LINEAR(P3,$C$17:$L$17,$C$3:$L$3) -> 12198.236 | Q17: =_xlfn.FORECAST.LINEAR(Q3,$C$17:$L$17,$C$3:$L$3) -> 12981.133
B18: EBITDA Growth | C18: =IFERROR(C17/C17-1,0) -> 0 | D18: =IFERROR(D17/C17-1,0) -> 0.3059097 | E18: =IFERROR(E17/D17-1,0) -> 0.067477845 | F18: =IFERROR(F17/E17-1,0) -> 0.31964021 | G18: =IFERROR(G17/F17-1,0) -> 0.079808307 | H18: =IFERROR(H17/G17-1,0) -> 0.087447906 | I18: =IFERROR(I17/H17-1,0) -> 0.013358957 | J18: =IFERROR(J17/I17-1,0) -> 0.23457123 | K18: =IFERROR(K17/J17-1,0) -> 0.4585815 | ... Q18: =IFERROR(Q17/P17-1,0) -> 0.064181122
B20: Interest | C20: =IFERROR('Historical FS'!C24,0) -> 5.9 | D20: =IFERROR('Historical FS'!D24,0) -> 16.45 | E20: =IFERROR('Historical FS'!E24,0) -> 34.62 | F20: =IFERROR('Historical FS'!F24,0) -> 177.6 | G20: =IFERROR('Historical FS'!G24,0) -> 359.59 | H20: =IFERROR('Historical FS'!H24,0) -> 266.89 | I20: =IFERROR('Historical FS'!I24,0) -> 65.24 | J20: =IFERROR('Historical FS'!J24,0) -> 64.41 | ... L20: =IFERROR('Historical FS'!L24,0) -> 21.62 | M20: =_xlfn.FORECAST.LINEAR(M3,$C$20:$L$20,$C$3:$L$3) -> 106.95867 | N20: =_xlfn.FORECAST.LINEAR(N3,$C$20:$L$20,$C$3:$L$3) -> 107.22479 | O20: =_xlfn.FORECAST.LINEAR(O3,$C$20:$L$20,$C$3:$L$3) -> 107.49091 | P20: =_xlfn.FORECAST.LINEAR(P3,$C$20:$L$20,$C$3:$L$3) -> 107.75703 | Q20: =_xlfn.FORECAST.LINEAR(Q3,$C$20:$L$20,$C$3:$L$3) -> 108.02315
B21: Interest Growth | C21: =IFERROR(C20/C20-1,0) -> 0 | D21: =IFERROR(D20/C20-1,0) -> 1.7881356 | E21: =IFERROR(E20/D20-1,0) -> 1.1045593 | F21: =IFERROR(F20/E20-1,0) -> 4.1299827 | G21: =IFERROR(G20/F20-1,0) -> 1.0247185 | H21: =IFERROR(H20/G20-1,0) -> -0.2577936 | I21: =IFERROR(I20/H20-1,0) -> -0.75555472 | J21: =IFERROR(J20/I20-1,0) -> -0.012722256 | K21: =IFERROR(K20/J20-1,0) -> -0.33814625 | ... Q21: =IFERROR(Q20/P20-1,0) -> 0.0024696413
B23: Depreciation | C23: =IFERROR('Historical FS'!C27,0) -> 862.8 | D23: =IFERROR('Historical FS'!D27,0) -> 680.68 | E23: =IFERROR('Historical FS'!E27,0) -> 947.09 | F23: =IFERROR('Historical FS'!F27,0) -> 1025.26 | G23: =IFERROR('Historical FS'!G27,0) -> 998.52 | H23: =IFERROR('Historical FS'!H27,0) -> 1157.89 | I23: =IFERROR('Historical FS'!I27,0) -> 1110.53 | J23: =IFERROR('Historical FS'!J27,0) -> 1784.67 | ... L23: =IFERROR('Historical FS'!L27,0) -> 1340.37 | M23: =_xlfn.FORECAST.LINEAR(M3,$C$23:$L$23,$C$3:$L$3) -> 1597.7193 | N23: =_xlfn.FORECAST.LINEAR(N3,$C$23:$L$23,$C$3:$L$3) -> 1682.4868 | O23: =_xlfn.FORECAST.LINEAR(O3,$C$23:$L$23,$C$3:$L$3) -> 1767.2544 | P23: =_xlfn.FORECAST.LINEAR(P3,$C$23:$L$23,$C$3:$L$3) -> 1852.0219 | Q23: =_xlfn.FORECAST.LINEAR(Q3,$C$23:$L$23,$C$3:$L$3) -> 1936.7894
B24: Depreciation Growth | C24: =IFERROR(C23/C23-1,0) -> 0 | D24: =IFERROR(D23/C23-1,0) -> -0.2110802 | E24: =IFERROR(E23/D23-1,0) -> 0.39138802 | F24: =IFERROR(F23/E23-1,0) -> 0.082537034 | G24: =IFERROR(G23/F23-1,0) -> -0.026081189 | H24: =IFERROR(H23/G23-1,0) -> 0.15960622 | I24: =IFERROR(I23/H23-1,0) -> -0.040901986 | J24: =IFERROR(J23/I23-1,0) -> 0.60704348 | K24: =IFERROR(K23/J23-1,0) -> -0.2115237 | ... Q24: =IFERROR(Q23/P23-1,0) -> 0.045770256
B26: Profit Before Tax | C26: =IFERROR('Historical FS'!C30,0) -> 3213.3 | D26: =IFERROR('Historical FS'!D30,0) -> 3591.76 | E26: =IFERROR('Historical FS'!E30,0) -> 3242.68 | F26: =IFERROR('Historical FS'!F30,0) -> 3724.43 | G26: =IFERROR('Historical FS'!G30,0) -> 3978.64 | H26: =IFERROR('Historical FS'!H30,0) -> 4283.48 | I26: =IFERROR('Historical FS'!I30,0) -> 5224.53 | J26: =IFERROR('Historical FS'!J30,0) -> 6509.5 | ... L26: =IFERROR('Historical FS'!L30,0) -> 10867.26 | M26: =_xlfn.FORECAST.LINEAR(M3,$C$26:$L$26,$C$3:$L$3) -> 10034.603 | N26: =_xlfn.FORECAST.LINEAR(N3,$C$26:$L$26,$C$3:$L$3) -> 10861.614 | O26: =_xlfn.FORECAST.LINEAR(O3,$C$26:$L$26,$C$3:$L$3) -> 11688.624 | P26: =_xlfn.FORECAST.LINEAR(P3,$C$26:$L$26,$C$3:$L$3) -> 12515.635 | Q26: =_xlfn.FORECAST.LINEAR(Q3,$C$26:$L$26,$C$3:$L$3) -> 13342.645
B27: PBT Growth | C27: =IFERROR(C26/C26-1,0) -> 0 | D27: =IFERROR(D26/C26-1,0) -> 0.11777923 | E27: =IFERROR(E26/D26-1,0) -> -0.097189122 | F27: =IFERROR(F26/E26-1,0) -> 0.14856538 | G27: =IFERROR(G26/F26-1,0) -> 0.06825474 | H27: =IFERROR(H26/G26-1,0) -> 0.076619146 | I27: =IFERROR(I26/H26-1,0) -> 0.21969287 | J27: =IFERROR(J26/I26-1,0) -> 0.2459494 | K27: =IFERROR(K26/J26-1,0) -> 0.57076273 | ... Q27: =IFERROR(Q26/P26-1,0) -> 0.066078185
B29: Tax | C29: =IFERROR('Historical FS'!C33,0) -> 1209 | D29: =IFERROR('Historical FS'!D33,0) -> 966.95 | E29: =IFERROR('Historical FS'!E33,0) -> 1252.43 | F29: =IFERROR('Historical FS'!F33,0) -> 1396.28 | G29: =IFERROR('Historical FS'!G33,0) -> 1095.99 | H29: =IFERROR('Historical FS'!H33,0) -> 1037.93 | I29: =IFERROR('Historical FS'!I33,0) -> 144.65 | J29: =IFERROR('Historical FS'!J33,0) -> 681.77 | ... L29: =IFERROR('Historical FS'!L33,0) -> 2503.21 | M29: =_xlfn.FORECAST.LINEAR(M3,$C$29:$L$29,$C$3:$L$3) -> 1837.2307 | N29: =_xlfn.FORECAST.LINEAR(N3,$C$29:$L$29,$C$3:$L$3) -> 1936.8701 | O29: =_xlfn.FORECAST.LINEAR(O3,$C$29:$L$29,$C$3:$L$3) -> 2036.5095 | P29: =_xlfn.FORECAST.LINEAR(P3,$C$29:$L$29,$C$3:$L$3) -> 2136.1488 | Q29: =_xlfn.FORECAST.LINEAR(Q3,$C$29:$L$29,$C$3:$L$3) -> 2235.7882
B30: Effective Tax Rate | C30: =IFERROR(C29/C29-1,0) -> 0 | D30: =IFERROR(D29/C29-1,0) -> -0.20020678 | E30: =IFERROR(E29/D29-1,0) -> 0.2952376 | F30: =IFERROR(F29/E29-1,0) -> 0.11485672 | G30: =IFERROR(G29/F29-1,0) -> -0.21506431 | H30: =IFERROR(H29/G29-1,0) -> -0.052974936 | I30: =IFERROR(I29/H29-1,0) -> -0.86063607 | J30: =IFERROR(J29/I29-1,0) -> 3.7132389 | K30: =IFERROR(K29/J29-1,0) -> 2.8193672 | ... Q30: =IFERROR(Q29/P29-1,0) -> 0.046644406
B32: Net Profit | C32: =IFERROR('Historical FS'!C36,0) -> 2004.3 | D32: =IFERROR('Historical FS'!D36,0) -> 2624.81 | E32: =IFERROR('Historical FS'!E36,0) -> 1990.25 | F32: =IFERROR('Historical FS'!F36,0) -> 2328.15 | G32: =IFERROR('Historical FS'!G36,0) -> 2882.65 | H32: =IFERROR('Historical FS'!H36,0) -> 3245.55 | I32: =IFERROR('Historical FS'!I36,0) -> 5079.88 | J32: =IFERROR('Historical FS'!J36,0) -> 5827.73 | ... L32: =IFERROR('Historical FS'!L36,0) -> 8364.05 | M32: =_xlfn.FORECAST.LINEAR(M3,$C$32:$L$32,$C$3:$L$3) -> 8197.3727 | N32: =_xlfn.FORECAST.LINEAR(N3,$C$32:$L$32,$C$3:$L$3) -> 8924.7437 | O32: =_xlfn.FORECAST.LINEAR(O3,$C$32:$L$32,$C$3:$L$3) -> 9652.1147 | P32: =_xlfn.FORECAST.LINEAR(P3,$C$32:$L$32,$C$3:$L$3) -> 10379.486 | Q32: =_xlfn.FORECAST.LINEAR(Q3,$C$32:$L$32,$C$3:$L$3) -> 11106.857
B33: Net Margins | C33: =IFERROR(C32/C32-1,0) -> 0 | D33: =IFERROR(D32/C32-1,0) -> 0.30958938 | E33: =IFERROR(E32/D32-1,0) -> -0.24175464 | F33: =IFERROR(F32/E32-1,0) -> 0.16977767 | G33: =IFERROR(G32/F32-1,0) -> 0.23817194 | H33: =IFERROR(H32/G32-1,0) -> 0.12589111 | I33: =IFERROR(I32/H32-1,0) -> 0.5651831 | J33: =IFERROR(J32/I32-1,0) -> 0.14721804 | K33: =IFERROR(K32/J32-1,0) -> 0.30770472 | ... Q33: =IFERROR(Q32/P32-1,0) -> 0.070077752
B35: ='Historical FS'!B39 -> No. of Equity Shares | C35: ='Historical FS'!C39 -> 72.3 | D35: ='Historical FS'!D39 -> 72.3 | E35: ='Historical FS'!E39 -> 66.88 | F35: ='Historical FS'!F39 -> 66.88 | G35: ='Historical FS'!G39 -> 66.88 | H35: ='Historical FS'!H39 -> 66.88 | I35: ='Historical FS'!I39 -> 66.88 | ... L35: ='Historical FS'!L39 -> 66.88 | M35: =L35 -> 66.88 | N35: =M35 -> 66.88 | O35: =N35 -> 66.88 | P35: =O35 -> 66.88 | Q35: =P35 -> 66.88
B37: ='Historical FS'!B41 -> Earnings Per Share | C37: =IFERROR(C32/C35,0) -> 27.721992 | D37: =IFERROR(D32/D35,0) -> 36.304426 | E37: =IFERROR(E32/E35,0) -> 29.758523 | F37: =IFERROR(F32/F35,0) -> 34.810855 | G37: =IFERROR(G32/G35,0) -> 43.101824 | H37: =IFERROR(H32/H35,0) -> 48.527961 | I37: =IFERROR(I32/I35,0) -> 75.955144 | J37: =IFERROR(J32/J35,0) -> 87.137111 | ... Q37: =IFERROR(Q32/Q35,0) -> 166.07142
B38: ='Historical FS'!B42 -> EPS growth | C38: =C37/C37-1 -> 0 | D38: =IFERROR(D37/C37-1,0) -> 0.30958938 | E38: =IFERROR(E37/D37-1,0) -> -0.18030593 | F38: =IFERROR(F37/E37-1,0) -> 0.16977767 | G38: =IFERROR(G37/F37-1,0) -> 0.23817194 | H38: =IFERROR(H37/G37-1,0) -> 0.12589111 | I38: =IFERROR(I37/H37-1,0) -> 0.5651831 | J38: =IFERROR(J37/I37-1,0) -> 0.14721804 | K38: =IFERROR(K37/J37-1,0) -> 0.30770472 | ... Q38: =IFERROR(Q37/P37-1,0) -> 0.070077752

Sheet Wacc
B2: Weighted Average Cost of Capital
B4: All figures are in INR unless stated otherwise
B5: Peer Comps
H6: Debt / | I6: Debt / | J6: Levered | K6: Unlevered
B7: Name of the Comp | D7: Country | E7: Total Debt | F7: Total Equity | G7: Tax Rate 1 | H7: Equity | I7: Capital | J7: Beta 2 | K7: Beta 3
B10: ='Peer data'!C3 -> Hind.Aeronautics | D10: India | E10: ='Peer data'!F3 -> 11.4 | F10: ='Peer data'!J3 -> 334.39 | G10: 0.3 | H10: =E10/F10 -> 0.034091929 | I10: =E10/(E10+F10) -> 0.032967986 | J10: =Beta!M8 -> 1.6170793 | K10: =J10/(1+(1-G10)*H10) -> 1.5793882
B11: ='Peer data'!C4 -> Bharat Electron | D11: India | E11: ='Peer data'!F4 -> 58.89 | F11: ='Peer data'!J4 -> 730.98 | G11: 0.3 | H11: =E11/F11 -> 0.08056308 | I11: =E11/(E11+F11) -> 0.074556573 | J11: =Beta!AI8 -> 1.2462382 | K11: =J11/(1+(1-G11)*H11) -> 1.1797095
B12: ='Peer data'!C5 -> Bharat Dynamics | D12: India | E12: ='Peer data'!F5 -> 1.24 | F12: ='Peer data'!J5 -> 182.38 | G12: 0.3 | H12: =E12/F12 -> 0.0067989911 | I12: =E12/(E12+F12) -> 0.006753077 | J12: =Beta!BD8 -> 1.466286 | K12: =J12/(1+(1-G12)*H12) -> 1.4593405
B13: ='Peer data'!C6 -> Data Pattern | D13: India | E13: ='Peer data'!F6 -> 5.81 | F13: ='Peer data'!J6 -> 11.2 | G13: 0.3 | H13: =E13/F13 -> 0.51875 | I13: =E13/(E13+F13) -> 0.34156379 | J13: =Beta!BX8 -> 1.8927246 | K13: =J13/(1+(1-G13)*H13) -> 1.3885187
B14: ='Peer data'!C7 -> Zen Technologies | D14: India | E14: ='Peer data'!F7 -> 17.95 | F14: ='Peer data'!J7 -> 9.03 | G14: 0.3 | H14: =E14/F14 -> 1.9878184 | I14: =E14/(E14+F14) -> 0.66530764 | J14: =Beta!CR8 -> 0.97933055 | K14: =J14/(1+(1-G14)*H14) -> 0.40950937
F16: Average | G16: =AVERAGE(G10:G14) -> 0.3 | H16: =AVERAGE(H10:H14) -> 0.52560448 | I16: =AVERAGE(I10:I14) -> 0.22422981 | J16: =AVERAGE(J10:J14) -> 1.4403317 | K16: =AVERAGE(K10:K14) -> 1.2032933
F17: Median | G17: =MEDIAN(G10:G14) -> 0.3 | H17: =MEDIAN(H10:H14) -> 0.08056308 | I17: =MEDIAN(I10:I14) -> 0.074556573 | J17: =MEDIAN(J10:J14) -> 1.466286 | K17: =MEDIAN(K10:K14) -> 1.3885187
B20: Cost Of Debt | G20: Cost Of Equity
B22: Pre Tax Cost Of Debt | E22: =IFERROR('Data Sheet'!K27/'Data Sheet'!K59,0) -> 0.42029549 | G22: Risk Free Rate | K22: 0.0653
B23: Tax Rate | E23: =30% -> 0.3 | G23: Equity Risk Premium | K23: 0.088
B24: Post Tax Cost of Debt | E24: =E22*(1-E23) -> 0.29420684 | G24: Levered Beta 4 | K24: =K33 -> 1.6694564
G25: Cost Of Equity | K25: =K22+(K23*K24) -> 0.21221217
B28: Capital Structure | G28: Levered Beta
D30: Current | E30: Target | G30: Comps Median Unlevered Beta | K30: =K17 -> 1.3885187
B31: Total Debt | C31: =E10 -> 11.4 | D31: =C31/$C$33 -> 0.032967986 | E31: =I16 -> 0.22422981 | G31: Target Debt / Equity | K31: =E35 -> 0.28904154
B32: Market Capitalization | C32: =F10 -> 334.39 | D32: =C32/$C$33 -> 0.96703201 | E32: =E33-E31 -> 0.77577019 | G32: Tax Rate | K32: =E23 -> 0.3
B33: Total Capital | C33: =SUM(C31:C32) -> 345.79 | D33: =C33/$C$33 -> 1 | E33: =D33 -> 1 | G33: Levered Beta | K33: =K30*(1+(1-K32)*K31) -> 1.6694564
B35: Debt / Equity | D35: =D31/D32 -> 0.034091929 | E35: =E31/E32 -> 0.28904154 | G35: Weighted Average Cost of Capital
B37: Notes : | G37: Cost of Equity | K37: =K25 -> 0.21221217
B38: 1) Tax Rate considered as Marginal Tax Rate for the country | G38: Equity Weight | K38: =E32 -> 0.77577019
B39: 2) Levered Beta is based on 5-year monthly data
B40: 3) Unlevereed Beta = Levered Beta / (1+(1-Tax rate)*Debt/Equity) | G40: Cost of Debt | K40: =E24 -> 0.29420684
B41: 4) Levereed Beta = Unlevered Beta *(1+(1-Tax rate)*Debt/Equity) | G41: Debt Weight | K41: =E31 -> 0.22422981
G43: WACC | K43: =(K37*K38)+(K40*K41) -> 0.23059782

Sheet Intrinsic Growth
B2: Calculation Of ROIC | E2: 44256 | F2: 44621 | G2: 44986 | H2: 45352 | I2: 45717
B4: Current Assets
B5: ='Raw FS'!B31 -> Inventories | E5: =VLOOKUP($B5,'Raw FS'!$B$2:$G$36,2,0) -> 18005 | F5: =VLOOKUP($B5,'Raw FS'!$B$2:$G$36,3,0) -> 16210 | G5: =VLOOKUP($B5,'Raw FS'!$B$2:$G$36,4,0) -> 14221 | H5: =VLOOKUP($B5,'Raw FS'!$B$2:$G$36,5,0) -> 16033 | I5: =VLOOKUP($B5,'Raw FS'!$B$2:$G$36,6,0) -> 24107
B6: ='Raw FS'!B32 -> Trade receivables | E6: =VLOOKUP($B6,'Raw FS'!$B$2:$G$36,2,0) -> 5668 | F6: =VLOOKUP($B6,'Raw FS'!$B$2:$G$36,3,0) -> 4642 | G6: =VLOOKUP($B6,'Raw FS'!$B$2:$G$36,4,0) -> 4719 | H6: =VLOOKUP($B6,'Raw FS'!$B$2:$G$36,5,0) -> 4617 | I6: =VLOOKUP($B6,'Raw FS'!$B$2:$G$36,6,0) -> 4648
B7: ='Raw FS'!B34 -> Loans n Advances | E7: =VLOOKUP($B7,'Raw FS'!$B$2:$G$36,2,0) -> 951 | F7: =VLOOKUP($B7,'Raw FS'!$B$2:$G$36,3,0) -> -962 | G7: =VLOOKUP($B7,'Raw FS'!$B$2:$G$36,4,0) -> -1093 | H7: =VLOOKUP($B7,'Raw FS'!$B$2:$G$36,5,0) -> -41 | I7: =VLOOKUP($B7,'Raw FS'!$B$2:$G$36,6,0) -> -186
B8: ='Raw FS'!B35 -> Other asset items | E8: =VLOOKUP($B8,'Raw FS'!$B$2:$G$36,2,0) -> 11058 | F8: =VLOOKUP($B8,'Raw FS'!$B$2:$G$36,3,0) -> 15416 | G8: =VLOOKUP($B8,'Raw FS'!$B$2:$G$36,4,0) -> 20935 | H8: =VLOOKUP($B8,'Raw FS'!$B$2:$G$36,5,0) -> 23049 | I8: =VLOOKUP($B8,'Raw FS'!$B$2:$G$36,6,0) -> 30424
B9: Total Current Assets | E9: =SUM(E5:E8) -> 35682 | F9: =SUM(F5:F8) -> 35306 | G9: =SUM(G5:G8) -> 38782 | H9: =SUM(H5:H8) -> 43658 | I9: =SUM(I5:I8) -> 58993
B11: Current Liabilities
B12: Trade Payables | E12: =VLOOKUP($B12,'Raw FS'!$B$2:$G$36,2,0) -> 2256 | F12: =VLOOKUP($B12,'Raw FS'!$B$2:$G$36,3,0) -> 2558 | G12: =VLOOKUP($B12,'Raw FS'!$B$2:$G$36,4,0) -> 3135 | H12: =VLOOKUP($B12,'Raw FS'!$B$2:$G$36,5,0) -> 3413 | I12: =VLOOKUP($B12,'Raw FS'!$B$2:$G$36,6,0) -> 5106
B13: Advance from Customers | E13: =VLOOKUP($B13,'Raw FS'!$B$2:$G$36,2,0) -> 16553 | F13: =VLOOKUP($B13,'Raw FS'!$B$2:$G$36,3,0) -> 4352 | G13: =VLOOKUP($B13,'Raw FS'!$B$2:$G$36,4,0) -> 5540 | H13: =VLOOKUP($B13,'Raw FS'!$B$2:$G$36,5,0) -> 7363 | I13: =VLOOKUP($B13,'Raw FS'!$B$2:$G$36,6,0) -> 9789
B14: Other liability items | E14: =VLOOKUP($B14,'Raw FS'!$B$2:$G$36,2,0) -> 18806 | F14: =VLOOKUP($B14,'Raw FS'!$B$2:$G$36,3,0) -> 33979 | G14: =VLOOKUP($B14,'Raw FS'!$B$2:$G$36,4,0) -> 36974 | H14: =VLOOKUP($B14,'Raw FS'!$B$2:$G$36,5,0) -> 40943 | I14: =VLOOKUP($B14,'Raw FS'!$B$2:$G$36,6,0) -> 58767
B15: Total Current Liabilities | E15: =SUM(E12:E14) -> 37615 | F15: =SUM(F12:F14) -> 40889 | G15: =SUM(G12:G14) -> 45649 | H15: =SUM(H12:H14) -> 51719 | I15: =SUM(I12:I14) -> 73662
A17: # | B17: Net Working Capital | E17: =E9-E15 -> -1933 | F17: =F9-F15 -> -5583 | G17: =G9-G15 -> -6867 | H17: =H9-H15 -> -8061 | I17: =I9-I15 -> -14669
B19: Non Current Assets
B20: ='Raw FS'!B17 -> Land | E20: =VLOOKUP($B20,'Raw FS'!$B$2:$G$36,2,0) -> 33 | F20: =VLOOKUP($B20,'Raw FS'!$B$2:$G$36,3,0) -> 28 | G20: =VLOOKUP($B20,'Raw FS'!$B$2:$G$36,4,0) -> 28 | H20: =VLOOKUP($B20,'Raw FS'!$B$2:$G$36,5,0) -> 28 | I20: =VLOOKUP($B20,'Raw FS'!$B$2:$G$36,6,0) -> 28
B21: ='Raw FS'!B18 -> Building | E21: =VLOOKUP($B21,'Raw FS'!$B$2:$G$36,2,0) -> 1432 | F21: =VLOOKUP($B21,'Raw FS'!$B$2:$G$36,3,0) -> 1456 | G21: =VLOOKUP($B21,'Raw FS'!$B$2:$G$36,4,0) -> 1866 | H21: =VLOOKUP($B21,'Raw FS'!$B$2:$G$36,5,0) -> 1892 | I21: =VLOOKUP($B21,'Raw FS'!$B$2:$G$36,6,0) -> 1979
B22: ='Raw FS'!B19 -> Plant Machinery | E22: =VLOOKUP($B22,'Raw FS'!$B$2:$G$36,2,0) -> 2275 | F22: =VLOOKUP($B22,'Raw FS'!$B$2:$G$36,3,0) -> 2364 | G22: =VLOOKUP($B22,'Raw FS'!$B$2:$G$36,4,0) -> 2496 | H22: =VLOOKUP($B22,'Raw FS'!$B$2:$G$36,5,0) -> 2711 | I22: =VLOOKUP($B22,'Raw FS'!$B$2:$G$36,6,0) -> 2951
B23: ='Raw FS'!B20 -> Equipments | E23: =VLOOKUP($B23,'Raw FS'!$B$2:$G$36,2,0) -> 5915 | F23: =VLOOKUP($B23,'Raw FS'!$B$2:$G$36,3,0) -> 6212 | G23: =VLOOKUP($B23,'Raw FS'!$B$2:$G$36,4,0) -> 6752 | H23: =VLOOKUP($B23,'Raw FS'!$B$2:$G$36,5,0) -> 7254 | I23: =VLOOKUP($B23,'Raw FS'!$B$2:$G$36,6,0) -> 7815
B24: ='Raw FS'!B21 -> Furniture n fittings | E24: =VLOOKUP($B24,'Raw FS'!$B$2:$G$36,2,0) -> 85 | F24: =VLOOKUP($B24,'Raw FS'!$B$2:$G$36,3,0) -> 90 | G24: =VLOOKUP($B24,'Raw FS'!$B$2:$G$36,4,0) -> 103 | H24: =VLOOKUP($B24,'Raw FS'!$B$2:$G$36,5,0) -> 112 | I24: =VLOOKUP($B24,'Raw FS'!$B$2:$G$36,6,0) -> 130
B25: ='Raw FS'!B22 -> Railway sidings | E25: =VLOOKUP($B25,'Raw FS'!$B$2:$G$36,2,0) -> 0 | F25: =VLOOKUP($B25,'Raw FS'!$B$2:$G$36,3,0) -> 0 | G25: =VLOOKUP($B25,'Raw FS'!$B$2:$G$36,4,0) -> 0 | H25: =VLOOKUP($B25,'Raw FS'!$B$2:$G$36,5,0) -> 0 | I25: =VLOOKUP($B25,'Raw FS'!$B$2:$G$36,6,0) -> 0
B26: ='Raw FS'!B23 -> Vehicles | E26: =VLOOKUP($B26,'Raw FS'!$B$2:$G$36,2,0) -> 412 | F26: =VLOOKUP($B26,'Raw FS'!$B$2:$G$36,3,0) -> 415 | G26: =VLOOKUP($B26,'Raw FS'!$B$2:$G$36,4,0) -> 483 | H26: =VLOOKUP($B26,'Raw FS'!$B$2:$G$36,5,0) -> 490 | I26: =VLOOKUP($B26,'Raw FS'!$B$2:$G$36,6,0) -> 497
B27: ='Raw FS'!B24 -> Intangible Assets | E27: =VLOOKUP($B27,'Raw FS'!$B$2:$G$36,2,0) -> 2507 | F27: =VLOOKUP($B27,'Raw FS'!$B$2:$G$36,3,0) -> 2919 | G27: =VLOOKUP($B27,'Raw FS'!$B$2:$G$36,4,0) -> 3287 | H27: =VLOOKUP($B27,'Raw FS'!$B$2:$G$36,5,0) -> 3788 | I27: =VLOOKUP($B27,'Raw FS'!$B$2:$G$36,6,0) -> 4089
B28: ='Raw FS'!B25 -> Other fixed assets | E28: =VLOOKUP($B28,'Raw FS'!$B$2:$G$36,2,0) -> 513 | F28: =VLOOKUP($B28,'Raw FS'!$B$2:$G$36,3,0) -> 519 | G28: =VLOOKUP($B28,'Raw FS'!$B$2:$G$36,4,0) -> 842 | H28: =VLOOKUP($B28,'Raw FS'!$B$2:$G$36,5,0) -> 892 | I28: =VLOOKUP($B28,'Raw FS'!$B$2:$G$36,6,0) -> 954
B29: Gross Block | E29: =SUM(E20:E28) -> 13172 | F29: =SUM(F20:F28) -> 14003 | G29: =SUM(G20:G28) -> 15857 | H29: =SUM(H20:H28) -> 17167 | I29: =SUM(I20:I28) -> 18443
B30: ='Raw FS'!B27 -> Accumulated Depreciation | E30: =-VLOOKUP($B30,'Raw FS'!$B$2:$G$36,2,0) -> -6006 | F30: =-VLOOKUP($B30,'Raw FS'!$B$2:$G$36,3,0) -> -7237 | G30: =-VLOOKUP($B30,'Raw FS'!$B$2:$G$36,4,0) -> -9023 | H30: =-VLOOKUP($B30,'Raw FS'!$B$2:$G$36,5,0) -> -10431 | I30: =-VLOOKUP($B30,'Raw FS'!$B$2:$G$36,6,0) -> -11774
A31: # | B31: Net Non Current Assets | E31: =E29+E30 -> 7166 | F31: =F29+F30 -> 6766 | G31: =G29+G30 -> 6834 | H31: =H29+H30 -> 6736 | I31: =I29+I30 -> 6669
A33: # | B33: Invested Capital | E33: =E31+E17 -> 5233 | F33: =F31+F17 -> 1183 | G33: =G31+G17 -> -33 | H33: =H31+H17 -> -1325 | I33: =I31+I17 -> -8000
B34: EBIT | E34: ='Historical FS'!H30+'Historical FS'!I24 -> 4348.72 | F34: ='Historical FS'!I30+'Historical FS'!J24 -> 5288.94 | G34: ='Historical FS'!J30+'Historical FS'!K24 -> 6552.13 | H34: ='Historical FS'!K30+'Historical FS'!L24 -> 10246.5 | I34: ='Historical FS'!L30+'Historical FS'!M24 -> 10876.44
A36: # | B36: Return on Invested Capital | E36: =E34/E33 -> 0.83101854 | F36: =F34/F33 -> 4.4707861 | G36: =G34/G33 -> -198.54939 | H36: =H34/H33 -> -7.7332075 | I36: =I34/I33 -> -1.359555
B39: Calculation Of Reinvestment Rate | E39: 44256 | F39: 44621 | G39: 44986 | H39: 45352 | I39: 45717
B41: Net Capex | E41: =-SUM('Raw FS'!L12:L13) -> 1208 | F41: =-SUM('Raw FS'!M12:M13) -> 1498 | G41: =-SUM('Raw FS'!N12:N13) -> 1776 | H41: =-SUM('Raw FS'!O12:O13) -> 1747 | I41: =-SUM('Raw FS'!P12:P13) -> 1754
B42: Change in Working Capital | F42: =F17-E17 -> -3650 | G42: =G17-F17 -> -1284 | H42: =H17-G17 -> -1194 | I42: =I17-H17 -> -6608
B44: EBIT | E44: =E34 -> 4348.72 | F44: =F34 -> 5288.94 | G44: =G34 -> 6552.13 | H44: =H34 -> 10246.5 | I44: =I34 -> 10876.44
B45: Marginal Tax Rate | E45: 0.25 | F45: 0.25 | G45: 0.25 | H45: 0.25 | I45: 0.25
B46: EBIT (1-T) | E46: =E44*(1-E45) -> 3261.54 | F46: =F44*(1-F45) -> 3966.705 | G46: =G44*(1-G45) -> 4914.0975 | H46: =H44*(1-H45) -> 7684.875 | I46: =I44*(1-I45) -> 8157.33
B48: Reinvestment | F48: =SUM(F41:F42) -> -2152 | G48: =SUM(G41:G42) -> 492 | H48: =SUM(H41:H42) -> 553 | I48: =SUM(I41:I42) -> -4854
B49: Reinvestment Rate | F49: =F48/F46 -> -0.54251577 | G49: =G48/G46 -> 0.10012011 | H49: =H48/H46 -> 0.071959531 | I49: =I48/I46 -> -0.59504764
H51: 4 year Average | I51: =AVERAGE(F49:I49) -> -0.24137094
H52: 4 year Median | I52: =MEDIAN(F49:I49) -> -0.23527812
B54: Calculation of Growth Rate | E54: 44256 | F54: 44621 | G54: 44986 | H54: 45352 | I54: 45717
B56: =B49 -> Reinvestment Rate | F56: =F49 -> -0.54251577 | G56: =G49 -> 0.10012011 | H56: =H49 -> 0.071959531 | I56: =I49 -> -0.59504764
B57: =B36 -> Return on Invested Capital | F57: =F36 -> 4.4707861 | G57: =G36 -> -198.54939 | H57: =H36 -> -7.7332075 | I57: =I36 -> -1.359555
B59: Intrinsic Growth | F59: =F56*F57 -> -2.425472 | G59: =G56*G57 -> -19.878788 | H59: =H56*H57 -> -0.55647799 | I59: =I56*I57 -> 0.809
H61: 4 year Average | I61: =AVERAGE(F59:I59) -> -5.5129345
H62: 4 year Median | I62: =MEDIAN(F59:I59) -> -1.490975

Sheet DCF
B3: Calculation of PV of FCFF | D3: ='Reg Forcast'!L2 -> 45745 | E3: ='Reg Forcast'!M2 -> 46110 | F3: ='Reg Forcast'!N2 -> 46475 | G3: ='Reg Forcast'!O2 -> 46840 | H3: ='Reg Forcast'!P2 -> 47205 | I3: ='Reg Forcast'!Q2 -> 47570
B5: EBIT | D5: ='Intrinsic Growth'!I44 -> 10876.44 | E5: =D5*(1+$C$14) -> 11246.239 | F5: =E5*(1+$C$14) -> 11628.611 | G5: =F5*(1+$C$14) -> 12023.984 | H5: =G5*(1+$C$14) -> 12432.799 | I5: =H5*(1+$C$14) -> 12855.514
B6: Tax Rate | D6: 0.25 | E6: 0.25 | F6: 0.25 | G6: 0.25 | H6: 0.25 | I6: 0.25
B7: EBIT(1-T) | D7: =D5*(1-D6) -> 8157.33 | E7: =E5*(1-E6) -> 8434.6792 | F7: =F5*(1-F6) -> 8721.4583 | G7: =G5*(1-G6) -> 9017.9879 | H7: =H5*(1-H6) -> 9324.5995 | I7: =I5*(1-I6) -> 9641.6359
B8: Less : Reinvestment Rate | D8: ='Intrinsic Growth'!I52 -> -0.23527812 | E8: =D8+(($I$8-$D$8)/4) -> -0.17345859 | F8: =E8+(($I$8-$D$8)/4) -> -0.11163906 | G8: =F8+(($I$8-$D$8)/4) -> -0.049819529 | H8: =G8+(($I$8-$D$8)/4) -> 0.012 | I8: 0.012
B9: Free Cash Flow to Firm | D9: =D7*(1-D8) -> 10076.571 | E9: =E7*(1-E8) -> 9897.7468 | F9: =F7*(1-F8) -> 9695.1137 | G9: =G7*(1-G8) -> 9467.2598 | H9: =H7*(1-H8) -> 9212.7043 | I9: =I7*(1-I8) -> 9525.9362
B10: Mid Year Convention | E10: 0.5 | F10: =E10+1 -> 1.5 | G10: =F10+1 -> 2.5 | H10: =G10+1 -> 3.5 | I10: =H10+1 -> 4.5
B11: Discounting Factor | E11: =1/(1+$C$16)^E10 -> 0.90145059 | F11: =1/(1+$C$16)^F10 -> 0.73253063 | G11: =1/(1+$C$16)^G10 -> 0.59526404 | H11: =1/(1+$C$16)^H10 -> 0.4837194 | I11: =1/(1+$C$16)^I10 -> 0.39307676
B12: PV of FCFF | E12: =E9*E11 -> 8922.3297 | F12: =F9*F11 -> 7101.9678 | G12: =G9*G11 -> 5635.5193 | H12: =H9*H11 -> 4456.3638 | I12: =I9*I11 -> 3744.4241
B14: Expected Growth | C14: 0.034
B15: Terminal Growth | C15: 0.055
B16: WACC | C16: =Wacc!K43 -> 0.23059782
B18: Calculation of Terminal Value | E18: Sensitivity Analysis
B20: FCFF (n+1) | C20: =I9*(1+C14) -> 9849.8181 | E20: =C30 -> 51909.481 | F20: =C16-2% -> 0.21059782 | G20: =F20+2% -> 0.23059782 | H20: =G20+2% -> 0.25059782 | I20: =H20+2% -> 0.27059782
B21: WACC | C21: =C16 -> 0.23059782 | E21: =C15-2% -> 0.035 | F21: 51909.481 | G21: 49654.97 | H21: 47818.739 | I21: 46294.265
B22: Terminal Growth Rate | C22: 0.055 | E22: =E21+2% -> 0.055 | F22: 54743.567 | G22: 51909.481 | H22: 49654.97 | I22: 47818.739
E23: =E22+2% -> 0.075 | F23: 58413.679 | G23: 54743.567 | H23: 51909.481 | I23: 49654.97
B24: Terminal Value | C24: =C20/(C21-C22) -> 56093.055 | E24: =E23+2% -> 0.095 | F24: 63353.751 | G24: 58413.679 | H24: 54743.567 | I24: 51909.481
B26: Calculation of Equity Value
B28: =B12 -> PV of FCFF | C28: =SUM(E12:I12) -> 29860.605
B29: PV of Termial Value | C29: =C24*I11 -> 22048.876
B30: Value of Operating Assets | C30: =SUM(C28:C29) -> 51909.481
B32: Add : Cash | C32: ='Data Sheet'!K69 -> 38182.25
B33: Less : Debt | C33: ='Data Sheet'!K59 -> 51.44
B34: Value of Equity | C34: =(C30+C32)-C33 -> 90040.291
B36: No. of Shares | C36: ='Data Sheet'!B6 -> 66.890714
B37: Equity Value per Share | C37: =C34/C36 -> 1346.0806
B39: Share Price | C39: ='Data Sheet'!B8 -> 4321.6
B40: Discount / Premium | C40: =C39/C37-1 -> 2.2105062

Sheet VaR
B2: Calculation of Value at Risk
A4: # | B4: =Beta!B6 -> Date | C4: =Beta!C6 -> Closing Price | D4: =Beta!D6 -> Returns | E4: Sorted Returns | F4: Replication | G4: Simulated Returns | I4: Historical Approach
B5: =Beta!B54 -> 45660 | C5: =Beta!C54 -> 4177.45 | D5: =(C5-C6)/C6 -> 0.7553786 | E5: 0.35271355 | F5: 1 | G5: =_xlfn.NORM.INV(RAND(),$M$5,$M$6) -> 0.13216361 | I5: Mean | M5: =AVERAGE(E5:E60) -> 0.045623386
B6: =Beta!B38 -> 44937 | C6: =Beta!C38 -> 2379.8 | D6: =(C6-C7)/C7 -> -0.52153764 | E6: 0.30539481 | F6: 2 | G6: =_xlfn.NORM.INV(RAND(),$M$5,$M$6) -> 0.096906363 | I6: Standard Deviation | M6: =_xlfn.STDEV.S(E5:E60) -> 0.10662606
B7: =Beta!B44 -> 45296 | C7: =Beta!C44 -> 4973.85 | D7: =(C7-C8)/C8 -> 6.2304841 | E7: 0.26260678 | F7: 3 | G7: =_xlfn.NORM.INV(RAND(),$M$5,$M$6) -> 0.007075086 | I7: Min | M7: =MIN(E5:E60) -> -0.21555578
B8: =Beta!B11 -> 44204 | C8: =Beta!C11 -> 687.9 | D8: =(C8-C9)/C9 -> -0.63723138 | E8: 0.23242023 | F8: 4 | G8: =_xlfn.NORM.INV(RAND(),$M$5,$M$6) -> -0.15993448 | I8: Max | M8: =MAX(E5:E60) -> 0.35271355
B9: =Beta!B33 -> 44932 | C9: =Beta!C33 -> 1896.25 | D9: =(C9-C10)/C10 -> 1.6269308 | E9: 0.21669137 | F9: 5 | G9: =_xlfn.NORM.INV(RAND(),$M$5,$M$6) -> -0.11405907 | I9: CMP | M9: =DCF!C39 -> 4321.6
B10: =Beta!B16 -> 44562 | C10: =Beta!C16 -> 721.85 | D10: =(C10-C11)/C11 -> -0.81675911 | E10: 0.19249005 | F10: 6 | G10: =_xlfn.NORM.INV(RAND(),$M$5,$M$6) -> 0.066494237
B11: =Beta!B43 -> 45295 | C11: =Beta!C43 -> 3939.35 | D11: =(C11-C12)/C12 -> 0.40490371 | E11: 0.1840547 | F11: 7 | G11: =_xlfn.NORM.INV(RAND(),$M$5,$M$6) -> -0.057970166 | I11: Percentile | J11: Confidence Level | K11: VaR % | L11: Stock Price | M11: Var INR
B12: =Beta!B39 -> 44938 | C12: =Beta!C39 -> 2804 | D12: =(C12-C13)/C13 -> 2.0506446 | E12: 0.17825027 | F12: 8 | G12: =_xlfn.NORM.INV(RAND(),$M$5,$M$6) -> -0.0023956615 | I12: 0.05 | J12: =1-I12 -> 0.95 | K12: =_xlfn.PERCENTILE.INC($E$5:E60,I12) -> -0.067251294 | L12: =$M$9*(1-K12) -> 4612.2332 | M12: =$M$9-L12 -> -290.63319
B13: =Beta!B20 -> 44566 | C13: =Beta!C20 -> 919.15 | D13: =(C13-C14)/C14 -> -0.092197531 | E13: 0.15246693 | F13: 9 | G13: =_xlfn.NORM.INV(RAND(),$M$5,$M$6) -> 0.064583249 | I13: 0.02 | J13: =1-I13 -> 0.98 | K13: =_xlfn.PERCENTILE.INC($E$6:E61,I13) -> -0.079944937 | L13: =$M$9*(1-K13) -> 4667.09 | M13: =$M$9-L13 -> -345.49004
B14: =Beta!B22 -> 44568 | C14: =Beta!C22 -> 1012.5 | D14: =(C14-C15)/C15 -> -0.11772395 | E14: 0.14419708 | F14: 10 | G14: =_xlfn.NORM.INV(RAND(),$M$5,$M$6) -> 0.17862279 | I14: 0.01 | J14: =1-I14 -> 0.99 | K14: =_xlfn.PERCENTILE.INC($E$7:E62,I14) -> -0.14418755 | L14: =$M$9*(1-K14) -> 4944.7209 | M14: =$M$9-L14 -> -623.12093
B15: =Beta!B23 -> 44569 | C15: =Beta!C23 -> 1147.6 | D15: =(C15-C16)/C16 -> -0.7692849 | E15: 0.1334321 | F15: 11 | G15: =_xlfn.NORM.INV(RAND(),$M$5,$M$6) -> 0.057873934 | I15: 0.005 | J15: =1-I15 -> 0.995 | K15: =_xlfn.PERCENTILE.INC($E$8:E63,I15) -> -0.18054495 | L15: =$M$9*(1-K15) -> 5101.8431 | M15: =$M$9-L15 -> -780.24307
B16: =Beta!B56 -> 45662 | C16: =Beta!C56 -> 4974.1 | D16: =(C16-C17)/C17 -> 0.047951122 | E16: 0.10833575 | F16: 12 | G16: =_xlfn.NORM.INV(RAND(),$M$5,$M$6) -> -0.027490075
B17: =Beta!B60 -> 45666 | C17: =Beta!C60 -> 4746.5 | D17: =(C17-C18)/C18 -> 7.5036817 | E17: 0.095531551 | F17: 13 | G17: =_xlfn.NORM.INV(RAND(),$M$5,$M$6) -> -0.016372946
B18: =Beta!B10 -> 44203 | C18: =Beta!C10 -> 558.17 | D18: =(C18-C19)/C19 -> -0.59465662 | E18: 0.092522999 | F18: 14 | G18: =_xlfn.NORM.INV(RAND(),$M$5,$M$6) -> 0.023158044 | I18: Monta Carlo Simulation
B19: =Beta!B26 -> 44572 | C19: =Beta!C26 -> 1377.03 | D19: =(C19-C20)/C20 -> 0.08853545 | E19: 0.08853545 | F19: 15 | G19: =_xlfn.NORM.INV(RAND(),$M$5,$M$6) -> 0.062262175 | I19: Mean | M19: =AVERAGE(G5:G10004) -> 0.046278391
B20: =Beta!B25 -> 44571 | C20: =Beta!C25 -> 1265.03 | D20: =(C20-C21)/C21 -> -0.61976856 | E20: 0.078981261 | F20: 16 | G20: =_xlfn.NORM.INV(RAND(),$M$5,$M$6) -> 0.13135311 | I20: Standard Deviation | M20: =_xlfn.STDEV.S(G5:G10004) -> 0.10618245
B21: =Beta!B42 -> 45294 | C21: =Beta!C42 -> 3327 | D21: =(C21-C22)/C22 -> -0.25867332 | E21: 0.078776284 | F21: 17 | G21: =_xlfn.NORM.INV(RAND(),$M$5,$M$6) -> 0.066144933 | I21: Min | M21: =MIN(G5:G10004) -> -0.34829734
B22: =Beta!B55 -> 45661 | C22: =Beta!C55 -> 4487.9 | D22: =(C22-C23)/C23 -> 4.627108 | E22: 0.074315671 | F22: 18 | G22: =_xlfn.NORM.INV(RAND(),$M$5,$M$6) -> -0.061856745 | I22: Max | M22: =MAX(G5:G10004) -> 0.45594011
B23: =Beta!B19 -> 44565 | C23: =Beta!C19 -> 797.55 | D23: =(C23-C24)/C24 -> 0.074213752 | E23: 0.074213752 | F23: 19 | G23: =_xlfn.NORM.INV(RAND(),$M$5,$M$6) -> 0.16120733 | I23: CMP | M23: =M9 -> 4321.6
B24: =Beta!B18 -> 44564 | C24: =Beta!C18 -> 742.45 | D24: =(C24-C25)/C25 -> -0.75246716 | E24: 0.069997694 | F24: 20 | G24: =_xlfn.NORM.INV(RAND(),$M$5,$M$6) -> -0.020803826
B25: =Beta!B40 -> 45292 | C25: =Beta!C40 -> 2999.4 | D25: =(C25-C26)/C26 -> 1.0542429 | E25: 0.069686163 | F25: 21 | G25: =_xlfn.NORM.INV(RAND(),$M$5,$M$6) -> -0.050132242 | I25: Percentile | J25: Confidence Level | K25: VaR % | L25: Stock Price | M25: Var INR
B26: =Beta!B31 -> 44930 | C26: =Beta!C31 -> 1460.1 | D26: =(C26-C27)/C27 -> -0.063155666 | E26: 0.069239501 | F26: 22 | G26: =_xlfn.NORM.INV(RAND(),$M$5,$M$6) -> 0.20600193 | I26: 0.05 | J26: =1-I26 -> 0.95 | K26: =_xlfn.PERCENTILE.INC($G$5:$G$10004,I26) -> -0.1280117 | L26: =$M$23*(1-K26) -> 4874.8154 | M26: =$M$23-L26 -> -553.21535
B27: =Beta!B32 -> 44931 | C27: =Beta!C32 -> 1558.53 | D27: =(C27-C28)/C28 -> 2.0543242 | E27: 0.067413191 | F27: 23 | G27: =_xlfn.NORM.INV(RAND(),$M$5,$M$6) -> -0.055826577 | I27: 0.02 | J27: =1-I27 -> 0.98 | K27: =_xlfn.PERCENTILE.INC($G$5:$G$10004,I27) -> -0.17059205 | L27: =$M$23*(1-K27) -> 5058.8306 | M27: =$M$23-L27 -> -737.23062
B28: =Beta!B8 -> 44201 | C28: =Beta!C8 -> 510.27 | D28: =(C28-C29)/C29 -> -0.62632639 | E28: 0.066105342 | F28: 24 | G28: =_xlfn.NORM.INV(RAND(),$M$5,$M$6) -> -0.00080228593 | I28: 0.01 | J28: =1-I28 -> 0.99 | K28: =_xlfn.PERCENTILE.INC($G$5:$G$10004,I28) -> -0.2038395 | L28: =$M$23*(1-K28) -> 5202.5128 | M28: =$M$23-L28 -> -880.91279
B29: =Beta!B30 -> 44929 | C29: =Beta!C30 -> 1365.55 | D29: =(C29-C30)/C30 -> -0.74059933 | E29: 0.060909762 | F29: 25 | G29: =_xlfn.NORM.INV(RAND(),$M$5,$M$6) -> 0.08692689 | I29: 0.005 | J29: =1-I29 -> 0.995 | K29: =_xlfn.PERCENTILE.INC($G$5:$G$10004,I29) -> -0.22987165 | L29: =$M$23*(1-K29) -> 5315.0133 | M29: =$M$23-L29 -> -993.41331
B30: =Beta!B45 -> 45297 | C30: =Beta!C45 -> 5264.25 | D30: =(C30-C31)/C31 -> 0.1758826 | E30: 0.058385355 | F30: 26 | G30: =_xlfn.NORM.INV(RAND(),$M$5,$M$6) -> -0.20584833
B31: =Beta!B50 -> 45302 | C31: =Beta!C50 -> 4476.85 | D31: =(C31-C32)/C32 -> 1.2601792 | E31: 0.054195022 | F31: 27 | G31: =_xlfn.NORM.INV(RAND(),$M$5,$M$6) -> -0.11573266
B32: =Beta!B34 -> 44933 | C32: =Beta!C34 -> 1980.75 | D32: =(C32-C33)/C33 -> -0.35774388 | E32: 0.044561635 | F32: 28 | G32: =_xlfn.NORM.INV(RAND(),$M$5,$M$6) -> 0.10310693
B33: =Beta!B41 -> 45293 | C33: =Beta!C41 -> 3084.05 | D33: =(C33-C34)/C34 -> 1.6304769 | E33: 0.028222311 | F33: 29 | G33: =_xlfn.NORM.INV(RAND(),$M$5,$M$6) -> 0.0967159
B34: =Beta!B24 -> 44570 | C34: =Beta!C24 -> 1172.43 | D34: =(C34-C35)/C35 -> -0.081477245 | E34: 0.021636459 | F34: 30 | G34: =_xlfn.NORM.INV(RAND(),$M$5,$M$6) -> 0.15948507
B35: =Beta!B28 -> 44927 | C35: =Beta!C28 -> 1276.43 | D35: =(C35-C36)/C36 -> -0.0083284776 | E35: 0.0085332996 | F35: 31 | G35: =_xlfn.NORM.INV(RAND(),$M$5,$M$6) -> 0.2369012
B36: =Beta!B29 -> 44928 | C36: =Beta!C29 -> 1287.15 | D36: =(C36-C37)/C37 -> 1.5193776 | E36: 0.0083984237 | F36: 32 | G36: =_xlfn.NORM.INV(RAND(),$M$5,$M$6) -> 0.15629286
B37: =Beta!B9 -> 44202 | C37: =Beta!C9 -> 510.9 | D37: =(C37-C38)/C38 -> -0.73503099 | E37: 0.0012346405 | F37: 33 | G37: =_xlfn.NORM.INV(RAND(),$M$5,$M$6) -> 0.11997444
B38: =Beta!B36 -> 44935 | C38: =Beta!C36 -> 1928.15 | D38: =(C38-C39)/C39 -> -0.58798453 | E38: -0.011281183 | F38: 34 | G38: =_xlfn.NORM.INV(RAND(),$M$5,$M$6) -> 0.09761158
B39: =Beta!B61 -> 45667 | C39: =Beta!C61 -> 4679.8 | D39: =(C39-C40)/C40 -> 1.3997128 | E39: -0.01405246 | F39: 35 | G39: =_xlfn.NORM.INV(RAND(),$M$5,$M$6) -> 0.030468893
B40: =Beta!B35 -> 44934 | C40: =Beta!C35 -> 1950.15 | D40: =(C40-C41)/C41 -> 1.8796403 | E40: -0.015448694 | F40: 36 | G40: =_xlfn.NORM.INV(RAND(),$M$5,$M$6) -> 0.16559163
B41: =Beta!B12 -> 44205 | C41: =Beta!C12 -> 677.22 | D41: =(C41-C42)/C42 -> -0.86093474 | E41: -0.015525512 | F41: 37 | G41: =_xlfn.NORM.INV(RAND(),$M$5,$M$6) -> 0.15879086
B42: =Beta!B57 -> 45663 | C42: =Beta!C57 -> 4869.8 | D42: =(C42-C43)/C43 -> 6.6275354 | E42: -0.020968617 | F42: 38 | G42: =_xlfn.NORM.INV(RAND(),$M$5,$M$6) -> 0.39657081
B43: =Beta!B14 -> 44207 | C43: =Beta!C14 -> 638.45 | D43: =(C43-C44)/C44 -> -0.85522019 | E43: -0.022730752 | F43: 39 | G43: =_xlfn.NORM.INV(RAND(),$M$5,$M$6) -> 0.14171888
B44: =Beta!B63 -> 45669 | C44: =Beta!C63 -> 4409.8 | D44: =(C44-C45)/C45 -> -0.029191617 | E44: -0.029191617 | F44: 40 | G44: =_xlfn.NORM.INV(RAND(),$M$5,$M$6) -> 0.075356866
B45: =Beta!B62 -> 45668 | C45: =Beta!C62 -> 4542.4 | D45: =(C45-C46)/C46 -> 5.9530078 | E45: -0.029360229 | F45: 41 | G45: =_xlfn.NORM.INV(RAND(),$M$5,$M$6) -> 0.1457597
B46: =Beta!B13 -> 44206 | C46: =Beta!C13 -> 653.3 | D46: =(C46-C47)/C47 -> -0.26172449 | E46: -0.035320871 | F46: 42 | G46: =_xlfn.NORM.INV(RAND(),$M$5,$M$6) -> 0.28317191
B47: =Beta!B21 -> 44567 | C47: =Beta!C21 -> 884.9 | D47: =(C47-C48)/C48 -> 0.27529256 | E47: -0.037262688 | F47: 43 | G47: =_xlfn.NORM.INV(RAND(),$M$5,$M$6) -> -0.14390721
B48: =Beta!B17 -> 44563 | C48: =Beta!C17 -> 693.88 | D48: =(C48-C49)/C49 -> -0.83660725 | E48: -0.038747662 | F48: 44 | G48: =_xlfn.NORM.INV(RAND(),$M$5,$M$6) -> 0.01452794
B49: =Beta!B49 -> 45301 | C49: =Beta!C49 -> 4246.7 | D49: =(C49-C50)/C50 -> -0.019826432 | E49: -0.039349417 | F49: 45 | G49: =_xlfn.NORM.INV(RAND(),$M$5,$M$6) -> -0.016554097
B50: =Beta!B59 -> 45665 | C50: =Beta!C59 -> 4332.6 | D50: =(C50-C51)/C51 -> -0.074220878 | E50: -0.044398862 | F50: 46 | G50: =_xlfn.NORM.INV(RAND(),$M$5,$M$6) -> 0.11399556
B51: =Beta!B47 -> 45299 | C51: =Beta!C47 -> 4679.95 | D51: =(C51-C52)/C52 -> 6.7312375 | E51: -0.049341337 | F51: 47 | G51: =_xlfn.NORM.INV(RAND(),$M$5,$M$6) -> -0.085098852
B52: =Beta!B15 -> 44208 | C52: =Beta!C15 -> 605.33 | D52: =(C52-C53)/C53 -> -0.66795754 | E52: -0.051875636 | F52: 48 | G52: =_xlfn.NORM.INV(RAND(),$M$5,$M$6) -> -0.027576937
B53: =Beta!B37 -> 44936 | C53: =Beta!C37 -> 1823.05 | D53: =(C53-C54)/C54 -> -0.5876059 | E53: -0.054508207 | F53: 49 | G53: =_xlfn.NORM.INV(RAND(),$M$5,$M$6) -> -0.1495006
B54: =Beta!B48 -> 45300 | C54: =Beta!C48 -> 4420.65 | D54: =(C54-C55)/C55 -> 0.12290439 | E54: -0.055406575 | F54: 50 | G54: =_xlfn.NORM.INV(RAND(),$M$5,$M$6) -> 0.15831026
B55: =Beta!B52 -> 45658 | C55: =Beta!C52 -> 3936.8 | D55: =(C55-C56)/C56 -> -0.20030064 | E55: -0.057809901 | F55: 51 | G55: =_xlfn.NORM.INV(RAND(),$M$5,$M$6) -> -0.048277319
B56: =Beta!B46 -> 45298 | C56: =Beta!C46 -> 4922.85 | D56: =(C56-C57)/C57 -> 0.17818038 | E56: -0.064852543 | F56: 52 | G56: =_xlfn.NORM.INV(RAND(),$M$5,$M$6) -> -0.0046148822
B57: =Beta!B51 -> 45303 | C57: =Beta!C51 -> 4178.35 | D57: =(C57-C58)/C58 -> -0.078420345 | E57: -0.066676346 | F57: 53 | G57: =_xlfn.NORM.INV(RAND(),$M$5,$M$6) -> 0.046524998
B58: =Beta!B58 -> 45664 | C58: =Beta!C58 -> 4533.9 | D58: =(C58-C59)/C59 -> 2.5823266 | E58: -0.068976139 | F58: 54 | G58: =_xlfn.NORM.INV(RAND(),$M$5,$M$6) -> 0.008286332
B59: =Beta!B27 -> 44573 | C59: =Beta!C27 -> 1265.63 | D59: =(C59-C60)/C60 -> -0.59017227 | E59: -0.080898746 | F59: 55 | G59: =_xlfn.NORM.INV(RAND(),$M$5,$M$6) -> 0.10037821
B60: =Beta!B53 -> 45659 | C60: =Beta!C53 -> 3088.2 | D60: =(C60-C61)/C61 -> #DIV/0! | E60: -0.21555578 | F60: 56 | G60: =_xlfn.NORM.INV(RAND(),$M$5,$M$6) -> 0.013155387
F61: 57 | G61: =_xlfn.NORM.INV(RAND(),$M$5,$M$6) -> 0.010210057
F62: 58 | G62: =_xlfn.NORM.INV(RAND(),$M$5,$M$6) -> 0.122066
F63: 59 | G63: =_xlfn.NORM.INV(RAND(),$M$5,$M$6) -> -0.005705292
F64: 60 | G64: =_xlfn.NORM.INV(RAND(),$M$5,$M$6) -> 0.23650934
F65: 61 | G65: =_xlfn.NORM.INV(RAND(),$M$5,$M$6) -> 0.029461805
F66: 62 | G66: =_xlfn.NORM.INV(RAND(),$M$5,$M$6) -> 0.050758106
F67: 63 | G67: =_xlfn.NORM.INV(RAND(),$M$5,$M$6) -> 0.14840756
F68: 64 | G68: =_xlfn.NORM.INV(RAND(),$M$5,$M$6) -> 0.014465328
F69: 65 | G69: =_xlfn.NORM.INV(RAND(),$M$5,$M$6) -> -0.049174951
F70: 66 | G70: =_xlfn.NORM.INV(RAND(),$M$5,$M$6) -> 0.1232307
F71: 67 | G71: =_xlfn.NORM.INV(RAND(),$M$5,$M$6) -> 0.00022953804
F72: 68 | G72: =_xlfn.NORM.INV(RAND(),$M$5,$M$6) -> -0.066302673
... F10004: 10000 | G10004: =_xlfn.NORM.INV(RAND(),$M$5,$M$6) -> -0.064734626

Sheet Peer Comparison
B2: Relative Valuation
B3: Amount in Crores
B4: Comparable Company Valuation
C6: Market Data | I6: Financials | M6: Valuation
B7: Company | C7: Share Price | D7: Shares Outstanding | E7: Equity Value | F7: Net Debt | G7: Enterprise Value | I7: Revenue | J7: EBITDA | K7: Net Income | M7: EV/Revenue | N7: EV/EBITDA | O7: P/E
B9: ='Peer data'!C3 -> Hind.Aeronautics | C9: ='Peer data'!D3 -> 4421.3 | D9: ='Peer data'!G3 -> 66.88 | E9: =D9*C9 -> 295696.54 | F9: ='Peer data'!F3-'Peer data'!H3 -> -38170.85 | G9: =E9+F9 -> 257525.69 | I9: ='Peer data'!K3 -> 32104.78 | J9: ='Peer data'!L3+'Peer data'!M3 -> 12775.6 | K9: ='Peer data'!N3 -> 8469.24 | M9: =G9/I9 -> 8.0214128 | N9: =G9/J9 -> 20.15762 | O9: =E9/K9 -> 34.914177
B10: ='Peer data'!C4 -> Bharat Electron | C10: ='Peer data'!D4 -> 400 | D10: ='Peer data'!G4 -> 730.98 | E10: =D10*C10 -> 292392 | F10: ='Peer data'!F4-'Peer data'!H4 -> -9486.21 | G10: =E10+F10 -> 282905.79 | I10: ='Peer data'!K4 -> 25152.11 | J10: ='Peer data'!L4+'Peer data'!M4 -> 8124.25 | K10: ='Peer data'!N4 -> 5694.83 | M10: =G10/I10 -> 11.247796 | N10: =G10/J10 -> 34.822389 | O10: =E10/K10 -> 51.343411
B11: ='Peer data'!C5 -> Bharat Dynamics | C11: ='Peer data'!D5 -> 1481.2 | D11: ='Peer data'!G5 -> 36.66 | E11: =D11*C11 -> 54300.792 | F11: ='Peer data'!F5-'Peer data'!H5 -> -4189.13 | G11: =E11+F11 -> 50111.662 | I11: ='Peer data'!K5 -> 4004.08 | J11: ='Peer data'!L5+'Peer data'!M5 -> 959.4 | K11: ='Peer data'!N5 -> 654.13 | M11: =G11/I11 -> 12.51515 | N11: =G11/J11 -> 52.232293 | O11: =E11/K11 -> 83.012233
B12: ='Peer data'!C6 -> Data Pattern | C12: ='Peer data'!D6 -> 2672.3 | D12: ='Peer data'!G6 -> 5.6 | E12: =D12*C12 -> 14964.88 | F12: ='Peer data'!F6-'Peer data'!H6 -> -120.59 | G12: =E12+F12 -> 14844.29 | I12: ='Peer data'!K6 -> 920.04 | J12: ='Peer data'!L6+'Peer data'!M6 -> 342.56 | K12: ='Peer data'!N6 -> 233.43 | M12: =G12/I12 -> 16.134396 | N12: =G12/J12 -> 43.333401 | O12: =E12/K12 -> 64.108641
B13: ='Peer data'!C7 -> Zen Technologies | C13: ='Peer data'!D7 -> 1391.6 | D13: ='Peer data'!G7 -> 9.03 | E13: =D13*C13 -> 12566.148 | F13: ='Peer data'!F7-'Peer data'!H7 -> -947.83 | G13: =E13+F13 -> 11618.318 | I13: ='Peer data'!K7 -> 808.97 | J13: ='Peer data'!L7+'Peer data'!M7 -> 404.89 | K13: ='Peer data'!N7 -> 271.4 | M13: =G13/I13 -> 14.361865 | N13: =G13/J13 -> 28.694999 | O13: =E13/K13 -> 46.301209
B14: ='Peer data'!C8 -> Apollo Micro Sys | C14: ='Peer data'!D8 -> 263 | D14: ='Peer data'!G8 -> 35.73 | E14: =D14*C14 -> 9396.99 | F14: ='Peer data'!F8-'Peer data'!H8 -> 288.61 | G14: =E14+F14 -> 9685.6 | I14: ='Peer data'!K8 -> 669 | J14: ='Peer data'!L8+'Peer data'!M8 -> 181.09 | K14: ='Peer data'!N8 -> 85.24 | M14: =G14/I14 -> 14.477728 | N14: =G14/J14 -> 53.485007 | O14: =E14/K14 -> 110.24155
B16: High | M16: =MAX(M9:M14) -> 16.134396 | N16: =MAX(N9:N14) -> 53.485007 | O16: =MAX(O9:O14) -> 110.24155
B17: 75th Percentile | M17: =QUARTILE(M9:M14,) -> 8.0214128 | N17: =QUARTILE(N9:N14,) -> 20.15762 | O17: =QUARTILE(O9:O14,) -> 34.914177
B18: Average | M18: =AVERAGE(M9:M14) -> 12.793058 | N18: =AVERAGE(N9:N14) -> 38.787618 | O18: =AVERAGE(O9:O14) -> 64.986871
B19: Median | M19: =MEDIAN(M9:M14) -> 13.438508 | N19: =MEDIAN(N9:N14) -> 39.077895 | O19: =MEDIAN(O9:O14) -> 57.726026
B20: 25th Percentile | M20: =QUARTILE(M9:M14,1) -> 11.564634 | N20: =QUARTILE(N9:N14,1) -> 30.226846 | O20: =QUARTILE(O9:O14,1) -> 47.561759
B21: Low | M21: =MIN(M9:M14) -> 8.0214128 | N21: =MIN(N9:N14) -> 20.15762 | O21: =MIN(O9:O14) -> 34.914177
B23: ='Data Sheet'!B1 & " " & "Comparable Valuation" -> HINDUSTAN AERONAUTICS LTD Comparable Valuation
B25: Implied Enterprise Value | M25: =M$19*I9 -> 431440.33 | N25: =N$19*J9 -> 499243.56 | O25: =O27+O26 -> 450724.72
B26: Net Debt | M26: =$F$9 -> -38170.85 | N26: =$F$9 -> -38170.85 | O26: =$F$9 -> -38170.85
B27: Implied Market Value | M27: =M25-M26 -> 469611.18 | N27: =N25-N26 -> 537414.41 | O27: =O19*K9 -> 488895.57
B28: Shares Outstanding | M28: =D9 -> 66.88 | N28: =M28 -> 66.88 | O28: =N28 -> 66.88
B30: Implied Value Per Share | M30: =M27/M28 -> 7021.6983 | N30: =N27/N28 -> 8035.5025 | O30: =O27/O28 -> 7310.0414
B32: Source : Screener.in
M33: =IF(M30>$C$9,"Undervalued","Overvalued") -> Undervalued | N33: =IF(N30>$C$9,"Undervalued","Overvalued") -> Undervalued | O33: =IF(O30>$C$9,"Undervalued","Overvalued") -> Undervalued

Sheet DuPont Analysis
B2: ='Data Sheet'!B1 -> HINDUSTAN AERONAUTICS LTD
B3: =CONCATENATE(" ","(",VLOOKUP(B2,'List of Stocks'!A2:D5442,3,0)," | ","BSE CODE :"," ",VLOOKUP(B2,'List of Stocks'!A2:D5442,2,TRUE),")") -> (HAL | BSE CODE : 541154)
B4: =CONCATENATE(" ","INR "&'Data Sheet'!B8) -> INR 4321.6
B5: 52 Week (High- INR 5165 & Low- INR 3046)
B7: About the Company
B8: Hindustan Aeronautics Limited (HAL) is an Indian public sector aerospace and defence company. Headquartered in Bengaluru, it is an Indian government owned company, that is involved in the designing, manufacturing and overhaul of combat aircraft, helicopters, unmanned aerial vehicles, jet and turbine engines, avionics, and other hardware.
B13: Financial Summary
B39: Return on Equity (ROE)
C40: ='Data Sheet'!E16 -> 43555 | D40: ='Data Sheet'!F16 -> 43921 | E40: ='Data Sheet'!G16 -> 44286 | F40: ='Data Sheet'!H16 -> 44651 | G40: ='Data Sheet'!I16 -> 45016 | H40: ='Data Sheet'!J16 -> 45382 | I40: ='Data Sheet'!K16 -> 45747
B41: Net Profit | C41: ='Data Sheet'!E30 -> 2328.63 | D41: ='Data Sheet'!F30 -> 2882.82 | E41: ='Data Sheet'!G30 -> 3245.95 | F41: ='Data Sheet'!H30 -> 5080.04 | G41: ='Data Sheet'!I30 -> 5827.74 | H41: ='Data Sheet'!J30 -> 7621.05 | I41: ='Data Sheet'!K30 -> 8364.13
B42: Average Shareholder Equity | C42: =(('Data Sheet'!E57+'Data Sheet'!E58)+('Data Sheet'!D57+'Data Sheet'!D58)/2) -> 16837.745 | D42: =(('Data Sheet'!F57+'Data Sheet'!F58)+('Data Sheet'!E57+'Data Sheet'!E58)/2) -> 19289.57 | E42: =(('Data Sheet'!G57+'Data Sheet'!G58)+('Data Sheet'!F57+'Data Sheet'!F58)/2) -> 22048.155 | F42: =(('Data Sheet'!H57+'Data Sheet'!H58)+('Data Sheet'!G57+'Data Sheet'!G58)/2) -> 27025.08 | G42: =(('Data Sheet'!I57+'Data Sheet'!I58)+('Data Sheet'!H57+'Data Sheet'!H58)/2) -> 33228.715 | H42: =(('Data Sheet'!J57+'Data Sheet'!J58)+('Data Sheet'!I57+'Data Sheet'!I58)/2) -> 40924.245 | I42: =(('Data Sheet'!K57+'Data Sheet'!K58)+('Data Sheet'!J57+'Data Sheet'!J58)/2) -> 49550.695
B43: Return On Equity | C43: =C41/C42 -> 0.13829821 | D43: =D41/D42 -> 0.14944968 | E43: =E41/E42 -> 0.14722094 | F43: =F41/F42 -> 0.18797502 | G43: =G41/G42 -> 0.17538265 | H43: =H41/H42 -> 0.18622335 | I43: =I41/I42 -> 0.16879945
B45: ROE - Dupont Equation
C46: 43555 | D46: 43921 | E46: 44286 | F46: 44651 | G46: 45016 | H46: 45382 | I46: 45747
B47: Net Profit | C47: 2328.63 | D47: 2882.82 | E47: 3245.95 | F47: 5080.04 | G47: 5827.74 | H47: 7621.05 | I47: 8364.13
B48: Revenue | C48: ='Data Sheet'!C17 -> 17949.92 | D48: ='Data Sheet'!F17 -> 21445.16 | E48: ='Data Sheet'!G17 -> 22882.32 | F48: ='Data Sheet'!H17 -> 24620.02 | G48: ='Data Sheet'!I17 -> 26927.46 | H48: ='Data Sheet'!J17 -> 30381.08 | I48: ='Data Sheet'!K17 -> 30980.95
B49: Net Profit Margin (A) | C49: =C47/C48 -> 0.12972927 | D49: =D47/D48 -> 0.13442754 | E49: =E47/E48 -> 0.14185406 | F49: =F47/F48 -> 0.20633777 | G49: =G47/G48 -> 0.21642368 | H49: =H47/H48 -> 0.25084855 | I49: =I47/I48 -> 0.26997655
B51: Revenue | C51: =C48 -> 17949.92 | D51: =D48 -> 21445.16 | E51: =E48 -> 22882.32 | F51: =F48 -> 24620.02 | G51: =G48 -> 26927.46 | H51: =H48 -> 30381.08 | I51: =I48 -> 30980.95
B52: Average Total Assets | C52: =(('Data Sheet'!E66+'Data Sheet'!D66)/2) -> 49979.47 | D52: =(('Data Sheet'!F66+'Data Sheet'!E66)/2) -> 52849.495 | E52: =(('Data Sheet'!G66+'Data Sheet'!F66)/2) -> 53649.54 | F52: =(('Data Sheet'!H66+'Data Sheet'!G66)/2) -> 56675.38 | G52: =(('Data Sheet'!I66+'Data Sheet'!H66)/2) -> 64765.17 | H52: =(('Data Sheet'!J66+'Data Sheet'!I66)/2) -> 75093.42 | I52: =(('Data Sheet'!K66+'Data Sheet'!J66)/2) -> 94804.65
B53: Asset TurnOver Ratio (B) | C53: =C51/C52 -> 0.35914587 | D53: =D51/D52 -> 0.40577795 | E53: =E51/E52 -> 0.42651475 | F53: =F51/F52 -> 0.43440415 | G53: =G51/G52 -> 0.4157707 | H53: =H51/H52 -> 0.40457713 | I53: =I51/I52 -> 0.32678724
B55: Average Total Assets | C55: =C52 -> 49979.47 | D55: =D52 -> 52849.495 | E55: =E52 -> 53649.54 | F55: =F52 -> 56675.38 | G55: =G52 -> 64765.17 | H55: =H52 -> 75093.42 | I55: =I52 -> 94804.65
B56: =B42 -> Average Shareholder Equity | C56: =C42 -> 16837.745 | D56: =D42 -> 19289.57 | E56: =E42 -> 22048.155 | F56: =F42 -> 27025.08 | G56: =G42 -> 33228.715 | H56: =H42 -> 40924.245 | I56: =I42 -> 49550.695
B57: Equity Multiplier (C) | C57: =C55/C56 -> 2.9682995 | D57: =D55/D56 -> 2.7397964 | E57: =E55/E56 -> 2.4332893 | F57: =F55/F56 -> 2.0971401 | G57: =G55/G56 -> 1.9490724 | H57: =H55/H56 -> 1.8349372 | I57: =I55/I56 -> 1.913286
B59: Return on Equity (A*B*C) | C59: =C49*C53*C57 -> 0.13829821 | D59: =D49*D53*D57 -> 0.14944968 | E59: =E49*E53*E57 -> 0.14722094 | F59: =F49*F53*F57 -> 0.18797502 | G59: =G49*G53*G57 -> 0.17538265 | H59: =H49*H53*H57 -> 0.18622335 | I59: =I49*I53*I57 -> 0.16879945
B61: Return on Assets (ROA)
C62: =C40 -> 43555 | D62: =D40 -> 43921 | E62: =E40 -> 44286 | F62: =F40 -> 44651 | G62: =G40 -> 45016 | H62: =H40 -> 45382 | I62: =I40 -> 45747
B63: Net Profit | C63: =C47 -> 2328.63 | D63: =D47 -> 2882.82 | E63: =E47 -> 3245.95 | F63: =F47 -> 5080.04 | G63: =G47 -> 5827.74 | H63: =H47 -> 7621.05 | I63: =I47 -> 8364.13
B64: =B52 -> Average Total Assets | C64: =C52 -> 49979.47 | D64: =D52 -> 52849.495 | E64: =E52 -> 53649.54 | F64: =F52 -> 56675.38 | G64: =G52 -> 64765.17 | H64: =H52 -> 75093.42 | I64: =I52 -> 94804.65
B65: Return On Equity | C65: =C63/C64 -> 0.046591731 | D65: =D63/D64 -> 0.05454773 | E65: =E63/E64 -> 0.060502849 | F65: =F63/F64 -> 0.089633982 | G65: =G63/G64 -> 0.089982625 | H65: =H63/H64 -> 0.10148759 | I65: =I63/I64 -> 0.088224892
B67: ROA - Dupont Equation
C68: 43555 | D68: 43921 | E68: 44286 | F68: 44651 | G68: 45016 | H68: 45382 | I68: 45747
B69: Net Profit | C69: 2328.63 | D69: 2882.82 | E69: 3245.95 | F69: 5080.04 | G69: 5827.74 | H69: 7621.05 | I69: 8364.13
B70: Revenue | C70: =C48 -> 17949.92 | D70: =D48 -> 21445.16 | E70: =E48 -> 22882.32 | F70: =F48 -> 24620.02 | G70: =G48 -> 26927.46 | H70: =H48 -> 30381.08 | I70: =I48 -> 30980.95
B71: Net Profit Margin (A) | C71: =C69/C70 -> 0.12972927 | D71: =D69/D70 -> 0.13442754 | E71: =E69/E70 -> 0.14185406 | F71: =F69/F70 -> 0.20633777 | G71: =G69/G70 -> 0.21642368 | H71: =H69/H70 -> 0.25084855 | I71: =I69/I70 -> 0.26997655
B73: Revenue | C73: =C70 -> 17949.92 | D73: =D70 -> 21445.16 | E73: =E70 -> 22882.32 | F73: =F70 -> 24620.02 | G73: =G70 -> 26927.46 | H73: =H70 -> 30381.08 | I73: =I70 -> 30980.95
B74: Average Total Assets | C74: =C64 -> 49979.47 | D74: =D64 -> 52849.495 | E74: =E64 -> 53649.54 | F74: =F64 -> 56675.38 | G74: =G64 -> 64765.17 | H74: =H64 -> 75093.42 | I74: =I64 -> 94804.65
B75: Asset TurnOver Ratio (B) | C75: =C73/C74 -> 0.35914587 | D75: =D73/D74 -> 0.40577795 | E75: =E73/E74 -> 0.42651475 | F75: =F73/F74 -> 0.43440415 | G75: =G73/G74 -> 0.4157707 | H75: =H73/H74 -> 0.40457713 | I75: =I73/I74 -> 0.32678724
B77: Return on Asset (A*B) | C77: =C71*C75 -> 0.046591731 | D77: =D71*D75 -> 0.05454773 | E77: =E71*E75 -> 0.060502849 | F77: =F71*F75 -> 0.089633982 | G77: =G71*G75 -> 0.089982625 | H77: =H71*H75 -> 0.10148759 | I77: =I71*I75 -> 0.088224892

Sheet Beta
B2: ="BETA CALCULATION - "&'Data Sheet'!B1 -> BETA CALCULATION - HINDUSTAN AERONAUTICS LTD | X2: ="BETA CALCULATION - "&Wacc!B11 -> BETA CALCULATION - Bharat Electron | AS2: ="BETA CALCULATION - "&Wacc!B12 -> BETA CALCULATION - Bharat Dynamics | BM2: ="BETA CALCULATION - "&Wacc!B13 -> BETA CALCULATION - Data Pattern | CG2: ="BETA CALCULATION - "&Wacc!B14 -> BETA CALCULATION - Zen Technologies
A4: # | B4: Regression Beta - 5 years Monthly | X4: Regression Beta - 5 years Monthly | AS4: Regression Beta - 5 years Monthly | BM4: Regression Beta - 5 years Monthly | CG4: Regression Beta - 5 years Monthly
B5: ='Data Sheet'!B1&"-Monthly Returns" -> HINDUSTAN AERONAUTICS LTD-Monthly Returns | F5: Nifty 50 Monthly Returns | I5: Beta Drifting | L5: Beta 1 | M5: =SLOPE(D8:D63, G8:G63) -> 1.6170793 | X5: =Wacc!B11&"-Monthly Returns" -> Bharat Electron-Monthly Returns | AB5: Nifty 50 Monthly Returns | AE5: Beta Drifting | AH5: Beta 1 | AI5: =SLOPE(Z8:Z63, AC8:AC63) -> 1.2462382 | AS5: =Wacc!B12&"-Monthly Returns" -> Bharat Dynamics-Monthly Returns | AW5: Nifty 50 Monthly Returns | AZ5: Beta Drifting | BC5: Beta 1 | BD5: =SLOPE(AU8:AU63, AX8:AX63) -> 1.466286 | BM5: =Wacc!V23&"-Monthly Returns" -> -Monthly Returns | BQ5: Nifty 50 Monthly Returns | BT5: Beta Drifting | BW5: Beta 1 | BX5: =SLOPE(BO17:BO63, BR8:BR63) -> #N/A | CG5: =Wacc!AP23&"-Monthly Returns" -> -Monthly Returns | CK5: Nifty 50 Monthly Returns | CN5: Beta Drifting | CQ5: Beta 1 | CR5: =SLOPE(CI8:CI63, CL8:CL63) -> 0.9957513
B6: Date | C6: Closing Price | D6: Returns | F6: Closing Price | G6: Returns | L6: Beta 2 | M6: =_xlfn.COVARIANCE.S(D7:D63,G7:G63)/_xlfn.VAR.S(G7:G63) -> 1.6212855 | X6: Date | Y6: Closing Price | Z6: Returns | AB6: Closing Price | AC6: Returns | AH6: Beta 2 | AI6: =_xlfn.COVARIANCE.S(Z7:Z63,AC7:AC63)/_xlfn.VAR.S(AC7:AC63) -> 1.2507834 | AS6: Date | AT6: Closing Price | AU6: Returns | AW6: Closing Price | AX6: Returns | BC6: Beta 2 | BD6: =_xlfn.COVARIANCE.S(AU7:AU63,AX7:AX63)/_xlfn.VAR.S(AX7:AX63) -> 1.4712976 | BM6: Date | BN6: Closing Price | BO6: Returns | BQ6: Closing Price | BR6: Returns | BW6: Beta 2 | BX6: =_xlfn.COVARIANCE.S(BO16:BO63,BR7:BR63)/_xlfn.VAR.S(BR7:BR63) -> #N/A | CG6: Date | CH6: Closing Price | CI6: Returns | CK6: Closing Price | CL6: Returns | CQ6: Beta 2 | CR6: =_xlfn.COVARIANCE.S(CI7:CI63,CL7:CL63)/_xlfn.VAR.S(CL7:CL63) -> 0.99783515
B7: =IFERROR('Data for Beta >2'!B3,0) -> 44200 | C7: =IFERROR('Data for Beta >2'!C3,0) -> 478.63 | D7: =IFERROR(C7/C7-1,0) -> 0 | F7: =IFERROR('Data for Beta >2'!L3,0) -> 14631.1 | G7: =IFERROR(F7/F7-1,0) -> 0 | I7: Levered Raw Beta | J7: =M5 -> 1.6170793 | X7: =B7 -> 44200 | Y7: =IFERROR('Data for Beta >2'!T3,0) -> 43.92 | Z7: =IFERROR(Y7/Y7-1,0) -> 0 | AB7: =F7 -> 14631.1 | AC7: =IFERROR(AB7/AB7-1,0) -> 0 | AE7: Levered Raw Beta | AF7: =AI5 -> 1.2462382 | AS7: =X7 -> 44200 | AT7: =IFERROR('Data for Beta >2'!AB3,0) -> 168.43 | AU7: =IFERROR(AT7/AT7-1,0) -> 0 | AW7: =AB7 -> 14631.1 | AX7: =IFERROR(AW7/AW7-1,0) -> 0 | AZ7: Levered Raw Beta | BA7: =BD5 -> 1.466286 | BM7: 44200 | BN7: =IFERROR('Data for Beta >2'!AJ3,0) -> 0 | BO7: =IFERROR(BN7/BN6-1,0) -> 0 | BQ7: =AW7 -> 14631.1 | BR7: =IFERROR(BQ7/BQ7-1,0) -> 0 | BT7: Levered Raw Beta | BU7: =BX5 -> #N/A | CG7: =IFERROR('Data for Beta >2'!AQ3,0) -> 44200 | CH7: =IFERROR('Data for Beta >2'!AR3,0) -> 264.3 | CI7: =IFERROR(CH7/CH7-1,0) -> 0 | CK7: =IFERROR('Data for Beta >2'!L3,0) -> 14631.1 | CL7: =IFERROR(CK7/CK7-1,0) -> 0 | CN7: Levered Raw Beta | CO7: =CR5 -> 0.9957513
B8: =IFERROR('Data for Beta >2'!B4,0) -> 44201 | C8: =IFERROR('Data for Beta >2'!C4,0) -> 510.27 | D8: =IFERROR(C8/C7-1,0) -> 0.066105342 | F8: =IFERROR('Data for Beta >2'!L4,0) -> 15582.8 | G8: =IFERROR(F8/F7-1,0) -> 0.065046374 | I8: Beta Weight | J8: 0.75 | L8: Beta 3 | M8: =M27 -> 1.6170793 | X8: =B8 -> 44201 | Y8: =IFERROR('Data for Beta >2'!T4,0) -> 48.47 | Z8: =IFERROR(Y8/Y7-1,0) -> 0.10359745 | AB8: =F8 -> 15582.8 | AC8: =IFERROR(AB8/AB7-1,0) -> 0.065046374 | AE8: Beta Weight | AF8: 0.75 | AH8: Beta 3 | AI8: =AI27 -> 1.2462382 | AS8: =X8 -> 44201 | AT8: =IFERROR('Data for Beta >2'!AB4,0) -> 180.85 | AU8: =IFERROR(AT8/AT7-1,0) -> 0.073739833 | AW8: =AB8 -> 15582.8 | AX8: =IFERROR(AW8/AW7-1,0) -> 0.065046374 | AZ8: Beta Weight | BA8: 0.75 | BC8: Beta 3 | BD8: =BD27 -> 1.466286 | BM8: 44201 | BN8: =IFERROR('Data for Beta >2'!AJ4,0) -> 0 | BO8: =IFERROR(BN8/BN7-1,0) -> 0 | BQ8: =AW8 -> 15582.8 | BR8: =IFERROR(BQ8/BQ7-1,0) -> 0.065046374 | BT8: Beta Weight | BU8: 0.75 | BW8: Beta 3 | BX8: =BX27 -> 1.8927246 | CG8: =IFERROR('Data for Beta >2'!AQ4,0) -> 44201 | CH8: =IFERROR('Data for Beta >2'!AR4,0) -> 285.8 | CI8: =IFERROR(CH8/CH7-1,0) -> 0.081346954 | CK8: =IFERROR('Data for Beta >2'!L4,0) -> 15582.8 | CL8: =IFERROR(CK8/CK7-1,0) -> 0.065046374 | CN8: Beta Weight | CO8: 0.75 | CQ8: Beta 3 | CR8: =CR27 -> 0.97933055
B9: =IFERROR('Data for Beta >2'!B5,0) -> 44202 | C9: =IFERROR('Data for Beta >2'!C5,0) -> 510.9 | D9: =IFERROR(C9/C8-1,0) -> 0.0012346405 | F9: =IFERROR('Data for Beta >2'!L5,0) -> 15721.5 | G9: =IFERROR(F9/F8-1,0) -> 0.0089008394 | X9: =B9 -> 44202 | Y9: =IFERROR('Data for Beta >2'!T5,0) -> 59.33 | Z9: =IFERROR(Y9/Y8-1,0) -> 0.22405612 | AB9: =F9 -> 15721.5 | AC9: =IFERROR(AB9/AB8-1,0) -> 0.0089008394 | AS9: =X9 -> 44202 | AT9: =IFERROR('Data for Beta >2'!AB5,0) -> 178.98 | AU9: =IFERROR(AT9/AT8-1,0) -> -0.010340061 | AW9: =AB9 -> 15721.5 | AX9: =IFERROR(AW9/AW8-1,0) -> 0.0089008394 | BM9: 44202 | BN9: =IFERROR('Data for Beta >2'!AJ5,0) -> 0 | BO9: =IFERROR(BN9/BN8-1,0) -> 0 | BQ9: =AW9 -> 15721.5 | BR9: =IFERROR(BQ9/BQ8-1,0) -> 0.0089008394 | CG9: =IFERROR('Data for Beta >2'!AQ5,0) -> 44202 | CH9: =IFERROR('Data for Beta >2'!AR5,0) -> 311.35 | CI9: =IFERROR(CH9/CH8-1,0) -> 0.089398181 | CK9: =IFERROR('Data for Beta >2'!L5,0) -> 15721.5 | CL9: =IFERROR(CK9/CK8-1,0) -> 0.0089008394
B10: =IFERROR('Data for Beta >2'!B6,0) -> 44203 | C10: =IFERROR('Data for Beta >2'!C6,0) -> 558.17 | D10: =IFERROR(C10/C9-1,0) -> 0.092522999 | F10: =IFERROR('Data for Beta >2'!L6,0) -> 15763.05 | G10: =IFERROR(F10/F9-1,0) -> 0.0026428776 | I10: Market Beta | J10: 1 | L10: SUMMARY OUTPUT | X10: =B10 -> 44203 | Y10: =IFERROR('Data for Beta >2'!T6,0) -> 61.55 | Z10: =IFERROR(Y10/Y9-1,0) -> 0.037417832 | AB10: =F10 -> 15763.05 | AC10: =IFERROR(AB10/AB9-1,0) -> 0.0026428776 | AE10: Market Beta | AF10: 1 | AH10: SUMMARY OUTPUT | AS10: =X10 -> 44203 | AT10: =IFERROR('Data for Beta >2'!AB6,0) -> 210.02 | AU10: =IFERROR(AT10/AT9-1,0) -> 0.1734272 | AW10: =AB10 -> 15763.05 | AX10: =IFERROR(AW10/AW9-1,0) -> 0.0026428776 | AZ10: Market Beta | BA10: 1 | BC10: SUMMARY OUTPUT | BM10: 44203 | BN10: =IFERROR('Data for Beta >2'!AJ6,0) -> 0 | BO10: =IFERROR(BN10/BN9-1,0) -> 0 | BQ10: =AW10 -> 15763.05 | BR10: =IFERROR(BQ10/BQ9-1,0) -> 0.0026428776 | BT10: Market Beta | BU10: 1 | BW10: SUMMARY OUTPUT | CG10: =IFERROR('Data for Beta >2'!AQ6,0) -> 44203 | CH10: =IFERROR('Data for Beta >2'!AR6,0) -> 415.9 | CI10: =IFERROR(CH10/CH9-1,0) -> 0.33579573 | CK10: =IFERROR('Data for Beta >2'!L6,0) -> 15763.05 | CL10: =IFERROR(CK10/CK9-1,0) -> 0.0026428776 | CN10: Market Beta | CO10: 1 | CQ10: SUMMARY OUTPUT
B11: =IFERROR('Data for Beta >2'!B7,0) -> 44204 | C11: =IFERROR('Data for Beta >2'!C7,0) -> 687.9 | D11: =IFERROR(C11/C10-1,0) -> 0.23242023 | F11: =IFERROR('Data for Beta >2'!L7,0) -> 17132.2 | G11: =IFERROR(F11/F10-1,0) -> 0.086858191 | I11: Market Beta Weight | J11: 0.25 | X11: =B11 -> 44204 | Y11: =IFERROR('Data for Beta >2'!T7,0) -> 62.22 | Z11: =IFERROR(Y11/Y10-1,0) -> 0.010885459 | AB11: =F11 -> 17132.2 | AC11: =IFERROR(AB11/AB10-1,0) -> 0.086858191 | AE11: Market Beta Weight | AF11: 0.25 | AS11: =X11 -> 44204 | AT11: =IFERROR('Data for Beta >2'!AB7,0) -> 196.55 | AU11: =IFERROR(AT11/AT10-1,0) -> -0.064136749 | AW11: =AB11 -> 17132.2 | AX11: =IFERROR(AW11/AW10-1,0) -> 0.086858191 | AZ11: Market Beta Weight | BA11: 0.25 | BM11: 44204 | BN11: =IFERROR('Data for Beta >2'!AJ7,0) -> 0 | BO11: =IFERROR(BN11/BN10-1,0) -> 0 | BQ11: =AW11 -> 17132.2 | BR11: =IFERROR(BQ11/BQ10-1,0) -> 0.086858191 | BT11: Market Beta Weight | BU11: 0.25 | CG11: =IFERROR('Data for Beta >2'!AQ7,0) -> 44204 | CH11: =IFERROR('Data for Beta >2'!AR7,0) -> 450.3 | CI11: =IFERROR(CH11/CH10-1,0) -> 0.08271219 | CK11: =IFERROR('Data for Beta >2'!L7,0) -> 17132.2 | CL11: =IFERROR(CK11/CK10-1,0) -> 0.086858191 | CN11: Market Beta Weight | CO11: 0.25
B12: =IFERROR('Data for Beta >2'!B8,0) -> 44205 | C12: =IFERROR('Data for Beta >2'!C8,0) -> 677.22 | D12: =IFERROR(C12/C11-1,0) -> -0.015525512 | F12: =IFERROR('Data for Beta >2'!L8,0) -> 17618.15 | G12: =IFERROR(F12/F11-1,0) -> 0.028364717 | L12: Regression Statistics | X12: =B12 -> 44205 | Y12: =IFERROR('Data for Beta >2'!T8,0) -> 67.65 | Z12: =IFERROR(Y12/Y11-1,0) -> 0.087270974 | AB12: =F12 -> 17618.15 | AC12: =IFERROR(AB12/AB11-1,0) -> 0.028364717 | AH12: Regression Statistics | AS12: =X12 -> 44205 | AT12: =IFERROR('Data for Beta >2'!AB8,0) -> 191.48 | AU12: =IFERROR(AT12/AT11-1,0) -> -0.025794963 | AW12: =AB12 -> 17618.15 | AX12: =IFERROR(AW12/AW11-1,0) -> 0.028364717 | BC12: Regression Statistics | BM12: 44205 | BN12: =IFERROR('Data for Beta >2'!AJ8,0) -> 0 | BO12: =IFERROR(BN12/BN11-1,0) -> 0 | BQ12: =AW12 -> 17618.15 | BR12: =IFERROR(BQ12/BQ11-1,0) -> 0.028364717 | BW12: Regression Statistics | CG12: =IFERROR('Data for Beta >2'!AQ8,0) -> 44205 | CH12: =IFERROR('Data for Beta >2'!AR8,0) -> 477.8 | CI12: =IFERROR(CH12/CH11-1,0) -> 0.061070398 | CK12: =IFERROR('Data for Beta >2'!L8,0) -> 17618.15 | CL12: =IFERROR(CK12/CK11-1,0) -> 0.028364717 | CQ12: Regression Statistics
B13: =IFERROR('Data for Beta >2'!B9,0) -> 44206 | C13: =IFERROR('Data for Beta >2'!C9,0) -> 653.3 | D13: =IFERROR(C13/C12-1,0) -> -0.035320871 | F13: =IFERROR('Data for Beta >2'!L9,0) -> 17671.65 | G13: =IFERROR(F13/F12-1,0) -> 0.0030366412 | I13: Ajusted Beta | J13: =(J7*J8)+(J10*J11) -> 1.4628095 | L13: Multiple R | M13: 0.54707594 | X13: =B13 -> 44206 | Y13: =IFERROR('Data for Beta >2'!T9,0) -> 68.95 | Z13: =IFERROR(Y13/Y12-1,0) -> 0.019216556 | AB13: =F13 -> 17671.65 | AC13: =IFERROR(AB13/AB12-1,0) -> 0.0030366412 | AE13: Ajusted Beta | AF13: =(AF7*AF8)+(AF10*AF11) -> 1.1846787 | AH13: Multiple R | AI13: 0.51007389 | AS13: =X13 -> 44206 | AT13: =IFERROR('Data for Beta >2'!AB9,0) -> 202.73 | AU13: =IFERROR(AT13/AT12-1,0) -> 0.058752872 | AW13: =AB13 -> 17671.65 | AX13: =IFERROR(AW13/AW12-1,0) -> 0.0030366412 | AZ13: Ajusted Beta | BA13: =(BA7*BA8)+(BA10*BA11) -> 1.3497145 | BC13: Multiple R | BD13: 0.34162556 | BM13: 44206 | BN13: =IFERROR('Data for Beta >2'!AJ9,0) -> 0 | BO13: =IFERROR(BN13/BN12-1,0) -> 0 | BQ13: =AW13 -> 17671.65 | BR13: =IFERROR(BQ13/BQ12-1,0) -> 0.0030366412 | BT13: Ajusted Beta | BU13: =(BU7*BU8)+(BU10*BU11) -> #N/A | BW13: Multiple R | BX13: 0.43498236 | CG13: =IFERROR('Data for Beta >2'!AQ9,0) -> 44206 | CH13: =IFERROR('Data for Beta >2'!AR9,0) -> 461.65 | CI13: =IFERROR(CH13/CH12-1,0) -> -0.033800753 | CK13: =IFERROR('Data for Beta >2'!L9,0) -> 17671.65 | CL13: =IFERROR(CK13/CK12-1,0) -> 0.0030366412 | CN13: Ajusted Beta | CO13: =(CO7*CO8)+(CO10*CO11) -> 0.99681347 | CQ13: Multiple R | CR13: 0.3019838
B14: =IFERROR('Data for Beta >2'!B10,0) -> 44207 | C14: =IFERROR('Data for Beta >2'!C10,0) -> 638.45 | D14: =IFERROR(C14/C13-1,0) -> -0.022730752 | F14: =IFERROR('Data for Beta >2'!L10,0) -> 16983.2 | G14: =IFERROR(F14/F13-1,0) -> -0.038957879 | L14: R Square | M14: 0.29929208 | X14: =B14 -> 44207 | Y14: =IFERROR('Data for Beta >2'!T10,0) -> 67.92 | Z14: =IFERROR(Y14/Y13-1,0) -> -0.014938361 | AB14: =F14 -> 16983.2 | AC14: =IFERROR(AB14/AB13-1,0) -> -0.038957879 | AH14: R Square | AI14: 0.26017537 | AS14: =X14 -> 44207 | AT14: =IFERROR('Data for Beta >2'!AB10,0) -> 207.23 | AU14: =IFERROR(AT14/AT13-1,0) -> 0.022197011 | AW14: =AB14 -> 16983.2 | AX14: =IFERROR(AW14/AW13-1,0) -> -0.038957879 | BC14: R Square | BD14: 0.11670802 | BM14: 44207 | BN14: =IFERROR('Data for Beta >2'!AJ10,0) -> 0 | BO14: =IFERROR(BN14/BN13-1,0) -> 0 | BQ14: =AW14 -> 16983.2 | BR14: =IFERROR(BQ14/BQ13-1,0) -> -0.038957879 | BW14: R Square | BX14: 0.18920966 | CG14: =IFERROR('Data for Beta >2'!AQ10,0) -> 44207 | CH14: =IFERROR('Data for Beta >2'!AR10,0) -> 446.55 | CI14: =IFERROR(CH14/CH13-1,0) -> -0.032708762 | CK14: =IFERROR('Data for Beta >2'!L10,0) -> 16983.2 | CL14: =IFERROR(CK14/CK13-1,0) -> -0.038957879 | CQ14: R Square | CR14: 0.091194217
B15: =IFERROR('Data for Beta >2'!B11,0) -> 44208 | C15: =IFERROR('Data for Beta >2'!C11,0) -> 605.33 | D15: =IFERROR(C15/C14-1,0) -> -0.051875636 | F15: =IFERROR('Data for Beta >2'!L11,0) -> 17354.05 | G15: =IFERROR(F15/F14-1,0) -> 0.021836285 | L15: Adjusted R Square | M15: 0.28631601 | X15: =B15 -> 44208 | Y15: =IFERROR('Data for Beta >2'!T11,0) -> 69.98 | Z15: =IFERROR(Y15/Y14-1,0) -> 0.0303298 | AB15: =F15 -> 17354.05 | AC15: =IFERROR(AB15/AB14-1,0) -> 0.021836285 | AH15: Adjusted R Square | AI15: 0.24647492 | AS15: =X15 -> 44208 | AT15: =IFERROR('Data for Beta >2'!AB11,0) -> 194.77 | AU15: =IFERROR(AT15/AT14-1,0) -> -0.06012643 | AW15: =AB15 -> 17354.05 | AX15: =IFERROR(AW15/AW14-1,0) -> 0.021836285 | BC15: Adjusted R Square | BD15: 0.10035076 | BM15: 44208 | BN15: =IFERROR('Data for Beta >2'!AJ11,0) -> 0 | BO15: =IFERROR(BN15/BN14-1,0) -> 0 | BQ15: =AW15 -> 17354.05 | BR15: =IFERROR(BQ15/BQ14-1,0) -> 0.021836285 | BW15: Adjusted R Square | BX15: 0.17119209 | CG15: =IFERROR('Data for Beta >2'!AQ11,0) -> 44208 | CH15: =IFERROR('Data for Beta >2'!AR11,0) -> 521.55 | CI15: =IFERROR(CH15/CH14-1,0) -> 0.16795432 | CK15: =IFERROR('Data for Beta >2'!L11,0) -> 17354.05 | CL15: =IFERROR(CK15/CK14-1,0) -> 0.021836285 | CQ15: Adjusted R Square | CR15: 0.070998533
B16: =IFERROR('Data for Beta >2'!B12,0) -> 44562 | C16: =IFERROR('Data for Beta >2'!C12,0) -> 721.85 | D16: =IFERROR(C16/C15-1,0) -> 0.19249005 | F16: =IFERROR('Data for Beta >2'!L12,0) -> 17339.85 | G16: =IFERROR(F16/F15-1,0) -> -0.0008182528 | L16: Standard Error | M16: 0.090077499 | X16: =B16 -> 44562 | Y16: =IFERROR('Data for Beta >2'!T12,0) -> 69.9 | Z16: =IFERROR(Y16/Y15-1,0) -> -0.0011431838 | AB16: =F16 -> 17339.85 | AC16: =IFERROR(AB16/AB15-1,0) -> -0.0008182528 | AH16: Standard Error | AI16: 0.07650617 | AS16: =X16 -> 44562 | AT16: =IFERROR('Data for Beta >2'!AB12,0) -> 248.95 | AU16: =IFERROR(AT16/AT15-1,0) -> 0.27817426 | AW16: =AB16 -> 17339.85 | AX16: =IFERROR(AW16/AW15-1,0) -> -0.0008182528 | BC16: Standard Error | BD16: 0.14685359 | BM16: 44562 | BN16: =IFERROR('Data for Beta >2'!AJ12,0) -> 721.8 | BO16: =IFERROR(BN16/BN15-1,0) -> 0 | BQ16: =AW16 -> 17339.85 | BR16: =IFERROR(BQ16/BQ15-1,0) -> -0.0008182528 | BW16: Standard Error | BX16: 0.14257185 | CG16: =IFERROR('Data for Beta >2'!AQ12,0) -> 44562 | CH16: =IFERROR('Data for Beta >2'!AR12,0) -> 415.5 | CI16: =IFERROR(CH16/CH15-1,0) -> -0.20333621 | CK16: =IFERROR('Data for Beta >2'!L12,0) -> 17339.85 | CL16: =IFERROR(CK16/CK15-1,0) -> -0.0008182528 | CQ16: Standard Error | CR16: 0.11924816
B17: =IFERROR('Data for Beta >2'!B13,0) -> 44563 | C17: =IFERROR('Data for Beta >2'!C13,0) -> 693.88 | D17: =IFERROR(C17/C16-1,0) -> -0.038747662 | F17: =IFERROR('Data for Beta >2'!L13,0) -> 16793.9 | G17: =IFERROR(F17/F16-1,0) -> -0.031485278 | L17: Observations | M17: 56 | X17: =B17 -> 44563 | Y17: =IFERROR('Data for Beta >2'!T13,0) -> 70.15 | Z17: =IFERROR(Y17/Y16-1,0) -> 0.0035765379 | AB17: =F17 -> 16793.9 | AC17: =IFERROR(AB17/AB16-1,0) -> -0.031485278 | AH17: Observations | AI17: 56 | AS17: =X17 -> 44563 | AT17: =IFERROR('Data for Beta >2'!AB13,0) -> 224.07 | AU17: =IFERROR(AT17/AT16-1,0) -> -0.099939747 | AW17: =AB17 -> 16793.9 | AX17: =IFERROR(AW17/AW16-1,0) -> -0.031485278 | BC17: Observations | BD17: 56 | BM17: 44563 | BN17: =IFERROR('Data for Beta >2'!AJ13,0) -> 613.55 | BO17: =IFERROR(BN17/BN16-1,0) -> -0.14997229 | BQ17: =AW17 -> 16793.9 | BR17: =IFERROR(BQ17/BQ16-1,0) -> -0.031485278 | BW17: Observations | BX17: 47 | CG17: =IFERROR('Data for Beta >2'!AQ13,0) -> 44563 | CH17: =IFERROR('Data for Beta >2'!AR13,0) -> 346.35 | CI17: =IFERROR(CH17/CH16-1,0) -> -0.16642599 | CK17: =IFERROR('Data for Beta >2'!L13,0) -> 16793.9 | CL17: =IFERROR(CK17/CK16-1,0) -> -0.031485278 | CQ17: Observations | CR17: 47
B18: =IFERROR('Data for Beta >2'!B14,0) -> 44564 | C18: =IFERROR('Data for Beta >2'!C14,0) -> 742.45 | D18: =IFERROR(C18/C17-1,0) -> 0.069997694 | F18: =IFERROR('Data for Beta >2'!L14,0) -> 17464.75 | G18: =IFERROR(F18/F17-1,0) -> 0.039946052 | X18: =B18 -> 44564 | Y18: =IFERROR('Data for Beta >2'!T14,0) -> 70.27 | Z18: =IFERROR(Y18/Y17-1,0) -> 0.0017106201 | AB18: =F18 -> 17464.75 | AC18: =IFERROR(AB18/AB17-1,0) -> 0.039946052 | AS18: =X18 -> 44564 | AT18: =IFERROR('Data for Beta >2'!AB14,0) -> 274.65 | AU18: =IFERROR(AT18/AT17-1,0) -> 0.22573303 | AW18: =AB18 -> 17464.75 | AX18: =IFERROR(AW18/AW17-1,0) -> 0.039946052 | BM18: 44564 | BN18: =IFERROR('Data for Beta >2'!AJ14,0) -> 702.9 | BO18: =IFERROR(BN18/BN17-1,0) -> 0.1456279 | BQ18: =AW18 -> 17464.75 | BR18: =IFERROR(BQ18/BQ17-1,0) -> 0.039946052 | CG18: =IFERROR('Data for Beta >2'!AQ14,0) -> 44564 | CH18: =IFERROR('Data for Beta >2'!AR14,0) -> 366.95 | CI18: =IFERROR(CH18/CH17-1,0) -> 0.059477407 | CK18: =IFERROR('Data for Beta >2'!L14,0) -> 17464.75 | CL18: =IFERROR(CK18/CK17-1,0) -> 0.039946052
B19: =IFERROR('Data for Beta >2'!B15,0) -> 44565 | C19: =IFERROR('Data for Beta >2'!C15,0) -> 797.55 | D19: =IFERROR(C19/C18-1,0) -> 0.074213752 | F19: =IFERROR('Data for Beta >2'!L15,0) -> 17102.55 | G19: =IFERROR(F19/F18-1,0) -> -0.020738917 | L19: ANOVA | X19: =B19 -> 44565 | Y19: =IFERROR('Data for Beta >2'!T15,0) -> 79.52 | Z19: =IFERROR(Y19/Y18-1,0) -> 0.13163512 | AB19: =F19 -> 17102.55 | AC19: =IFERROR(AB19/AB18-1,0) -> -0.020738917 | AH19: ANOVA | AS19: =X19 -> 44565 | AT19: =IFERROR('Data for Beta >2'!AB15,0) -> 374.1 | AU19: =IFERROR(AT19/AT18-1,0) -> 0.36209721 | AW19: =AB19 -> 17102.55 | AX19: =IFERROR(AW19/AW18-1,0) -> -0.020738917 | BC19: ANOVA | BM19: 44565 | BN19: =IFERROR('Data for Beta >2'!AJ15,0) -> 797.9 | BO19: =IFERROR(BN19/BN18-1,0) -> 0.13515436 | BQ19: =AW19 -> 17102.55 | BR19: =IFERROR(BQ19/BQ18-1,0) -> -0.020738917 | BW19: ANOVA | CG19: =IFERROR('Data for Beta >2'!AQ15,0) -> 44565 | CH19: =IFERROR('Data for Beta >2'!AR15,0) -> 323.1 | CI19: =IFERROR(CH19/CH18-1,0) -> -0.11949857 | CK19: =IFERROR('Data for Beta >2'!L15,0) -> 17102.55 | CL19: =IFERROR(CK19/CK18-1,0) -> -0.020738917 | CQ19: ANOVA
B20: =IFERROR('Data for Beta >2'!B16,0) -> 44566 | C20: =IFERROR('Data for Beta >2'!C16,0) -> 919.15 | D20: =IFERROR(C20/C19-1,0) -> 0.15246693 | F20: =IFERROR('Data for Beta >2'!L16,0) -> 16584.55 | G20: =IFERROR(F20/F19-1,0) -> -0.030287881 | M20: df | N20: SS | O20: MS | P20: F | Q20: Significance F | X20: =B20 -> 44566 | Y20: =IFERROR('Data for Beta >2'!T16,0) -> 78.25 | Z20: =IFERROR(Y20/Y19-1,0) -> -0.015970825 | AB20: =F20 -> 16584.55 | AC20: =IFERROR(AB20/AB19-1,0) -> -0.030287881 | AI20: df | AJ20: SS | AK20: MS | AL20: F | AM20: Significance F | AS20: =X20 -> 44566 | AT20: =IFERROR('Data for Beta >2'!AB16,0) -> 391.83 | AU20: =IFERROR(AT20/AT19-1,0) -> 0.047393745 | AW20: =AB20 -> 16584.55 | AX20: =IFERROR(AW20/AW19-1,0) -> -0.030287881 | BD20: df | BE20: SS | BF20: MS | BG20: F | BH20: Significance F | BM20: 44566 | BN20: =IFERROR('Data for Beta >2'!AJ16,0) -> 764.65 | BO20: =IFERROR(BN20/BN19-1,0) -> -0.041671889 | BQ20: =AW20 -> 16584.55 | BR20: =IFERROR(BQ20/BQ19-1,0) -> -0.030287881 | BX20: df | BY20: SS | BZ20: MS | CA20: F | CB20: Significance F | CG20: =IFERROR('Data for Beta >2'!AQ16,0) -> 44566 | CH20: =IFERROR('Data for Beta >2'!AR16,0) -> 305.8 | CI20: =IFERROR(CH20/CH19-1,0) -> -0.053543794 | CK20: =IFERROR('Data for Beta >2'!L16,0) -> 16584.55 | CL20: =IFERROR(CK20/CK19-1,0) -> -0.030287881 | CR20: df | CS20: SS | CT20: MS | CU20: F | CV20: Significance F
B21: =IFERROR('Data for Beta >2'!B17,0) -> 44567 | C21: =IFERROR('Data for Beta >2'!C17,0) -> 884.9 | D21: =IFERROR(C21/C20-1,0) -> -0.037262688 | F21: =IFERROR('Data for Beta >2'!L17,0) -> 15780.25 | G21: =IFERROR(F21/F20-1,0) -> -0.048496944 | L21: Regression | M21: 1 | N21: 0.18714775 | O21: 0.18714775 | P21: 23.064921 | Q21: 1.2840152e-05 | X21: =B21 -> 44567 | Y21: =IFERROR('Data for Beta >2'!T17,0) -> 78.03 | Z21: =IFERROR(Y21/Y20-1,0) -> -0.0028115016 | AB21: =F21 -> 15780.25 | AC21: =IFERROR(AB21/AB20-1,0) -> -0.048496944 | AH21: Regression | AI21: 1 | AJ21: 0.11115374 | AK21: 0.11115374 | AL21: 18.990271 | AM21: 5.9255859e-05 | AS21: =X21 -> 44567 | AT21: =IFERROR('Data for Beta >2'!AB17,0) -> 340.63 | AU21: =IFERROR(AT21/AT20-1,0) -> -0.13066891 | AW21: =AB21 -> 15780.25 | AX21: =IFERROR(AW21/AW20-1,0) -> -0.048496944 | BC21: Regression | BD21: 1 | BE21: 0.1538719 | BF21: 0.1538719 | BG21: 7.1349378 | BH21: 0.0099699779 | BM21: 44567 | BN21: =IFERROR('Data for Beta >2'!AJ17,0) -> 640.5 | BO21: =IFERROR(BN21/BN20-1,0) -> -0.16236186 | BQ21: =AW21 -> 15780.25 | BR21: =IFERROR(BQ21/BQ20-1,0) -> -0.048496944 | BW21: Regression | BX21: 1 | BY21: 0.21345917 | BZ21: 0.21345917 | CA21: 10.501401 | CB21: 0.0022468227 | CG21: =IFERROR('Data for Beta >2'!AQ17,0) -> 44567 | CH21: =IFERROR('Data for Beta >2'!AR17,0) -> 272.1 | CI21: =IFERROR(CH21/CH20-1,0) -> -0.11020275 | CK21: =IFERROR('Data for Beta >2'!L17,0) -> 15780.25 | CL21: =IFERROR(CK21/CK20-1,0) -> -0.048496944 | CQ21: Regression | CR21: 1 | CS21: 0.064211394 | CT21: 0.064211394 | CU21: 4.51553 | CV21: 0.039113952
B22: =IFERROR('Data for Beta >2'!B18,0) -> 44568 | C22: =IFERROR('Data for Beta >2'!C18,0) -> 1012.5 | D22: =IFERROR(C22/C21-1,0) -> 0.14419708 | F22: =IFERROR('Data for Beta >2'!L18,0) -> 17158.25 | G22: =IFERROR(F22/F21-1,0) -> 0.087324345 | L22: Residual | M22: 54 | N22: 0.43815362 | O22: 0.0081139559 | X22: =B22 -> 44568 | Y22: =IFERROR('Data for Beta >2'!T18,0) -> 91.73 | Z22: =IFERROR(Y22/Y21-1,0) -> 0.1755735 | AB22: =F22 -> 17158.25 | AC22: =IFERROR(AB22/AB21-1,0) -> 0.087324345 | AH22: Residual | AI22: 54 | AJ22: 0.31607248 | AK22: 0.0058531941 | AS22: =X22 -> 44568 | AT22: =IFERROR('Data for Beta >2'!AB18,0) -> 405.88 | AU22: =IFERROR(AT22/AT21-1,0) -> 0.19155682 | AW22: =AB22 -> 17158.25 | AX22: =IFERROR(AW22/AW21-1,0) -> 0.087324345 | BC22: Residual | BD22: 54 | BE22: 1.1645628 | BF22: 0.021565977 | BM22: 44568 | BN22: =IFERROR('Data for Beta >2'!AJ18,0) -> 776.15 | BO22: =IFERROR(BN22/BN21-1,0) -> 0.21178767 | BQ22: =AW22 -> 17158.25 | BR22: =IFERROR(BQ22/BQ21-1,0) -> 0.087324345 | BW22: Residual | BX22: 45 | BY22: 0.91470298 | BZ22: 0.020326733 | CG22: =IFERROR('Data for Beta >2'!AQ18,0) -> 44568 | CH22: =IFERROR('Data for Beta >2'!AR18,0) -> 247.55 | CI22: =IFERROR(CH22/CH21-1,0) -> -0.090224182 | CK22: =IFERROR('Data for Beta >2'!L18,0) -> 17158.25 | CL22: =IFERROR(CK22/CK21-1,0) -> 0.087324345 | CQ22: Residual | CR22: 45 | CS22: 0.63990555 | CT22: 0.014220123
B23: =IFERROR('Data for Beta >2'!B19,0) -> 44569 | C23: =IFERROR('Data for Beta >2'!C19,0) -> 1147.6 | D23: =IFERROR(C23/C22-1,0) -> 0.1334321 | F23: =IFERROR('Data for Beta >2'!L19,0) -> 17759.3 | G23: =IFERROR(F23/F22-1,0) -> 0.035029796 | L23: Total | M23: 55 | N23: 0.62530137 | X23: =B23 -> 44569 | Y23: =IFERROR('Data for Beta >2'!T19,0) -> 102.17 | Z23: =IFERROR(Y23/Y22-1,0) -> 0.11381228 | AB23: =F23 -> 17759.3 | AC23: =IFERROR(AB23/AB22-1,0) -> 0.035029796 | AH23: Total | AI23: 55 | AJ23: 0.42722623 | AS23: =X23 -> 44569 | AT23: =IFERROR('Data for Beta >2'!AB19,0) -> 408.9 | AU23: =IFERROR(AT23/AT22-1,0) -> 0.0074406228 | AW23: =AB23 -> 17759.3 | AX23: =IFERROR(AW23/AW22-1,0) -> 0.035029796 | BC23: Total | BD23: 55 | BE23: 1.3184347 | BM23: 44569 | BN23: =IFERROR('Data for Beta >2'!AJ19,0) -> 1067.2 | BO23: =IFERROR(BN23/BN22-1,0) -> 0.37499195 | BQ23: =AW23 -> 17759.3 | BR23: =IFERROR(BQ23/BQ22-1,0) -> 0.035029796 | BW23: Total | BX23: 46 | BY23: 1.1281622 | CG23: =IFERROR('Data for Beta >2'!AQ19,0) -> 44569 | CH23: =IFERROR('Data for Beta >2'!AR19,0) -> 230.9 | CI23: =IFERROR(CH23/CH22-1,0) -> -0.06725914 | CK23: =IFERROR('Data for Beta >2'!L19,0) -> 17759.3 | CL23: =IFERROR(CK23/CK22-1,0) -> 0.035029796 | CQ23: Total | CR23: 46 | CS23: 0.70411695
B24: =IFERROR('Data for Beta >2'!B20,0) -> 44570 | C24: =IFERROR('Data for Beta >2'!C20,0) -> 1172.43 | D24: =IFERROR(C24/C23-1,0) -> 0.021636459 | F24: =IFERROR('Data for Beta >2'!L20,0) -> 17094.35 | G24: =IFERROR(F24/F23-1,0) -> -0.037442354 | X24: =B24 -> 44570 | Y24: =IFERROR('Data for Beta >2'!T20,0) -> 100.95 | Z24: =IFERROR(Y24/Y23-1,0) -> -0.011940883 | AB24: =F24 -> 17094.35 | AC24: =IFERROR(AB24/AB23-1,0) -> -0.037442354 | AS24: =X24 -> 44570 | AT24: =IFERROR('Data for Beta >2'!AB20,0) -> 437.38 | AU24: =IFERROR(AT24/AT23-1,0) -> 0.069650281 | AW24: =AB24 -> 17094.35 | AX24: =IFERROR(AW24/AW23-1,0) -> -0.037442354 | BM24: 44570 | BN24: =IFERROR('Data for Beta >2'!AJ20,0) -> 1129.6 | BO24: =IFERROR(BN24/BN23-1,0) -> 0.058470765 | BQ24: =AW24 -> 17094.35 | BR24: =IFERROR(BQ24/BQ23-1,0) -> -0.037442354 | CG24: =IFERROR('Data for Beta >2'!AQ20,0) -> 44570 | CH24: =IFERROR('Data for Beta >2'!AR20,0) -> 211.65 | CI24: =IFERROR(CH24/CH23-1,0) -> -0.083369424 | CK24: =IFERROR('Data for Beta >2'!L20,0) -> 17094.35 | CL24: =IFERROR(CK24/CK23-1,0) -> -0.037442354
B25: =IFERROR('Data for Beta >2'!B21,0) -> 44571 | C25: =IFERROR('Data for Beta >2'!C21,0) -> 1265.03 | D25: =IFERROR(C25/C24-1,0) -> 0.078981261 | F25: =IFERROR('Data for Beta >2'!L21,0) -> 18012.2 | G25: =IFERROR(F25/F24-1,0) -> 0.053693179 | M25: Coefficients | N25: Standard Error | O25: t Stat | P25: P-value | Q25: Lower 95% | R25: Upper 95% | S25: Lower 95.0% | T25: Upper 95.0% | X25: =B25 -> 44571 | Y25: =IFERROR('Data for Beta >2'!T21,0) -> 106.85 | Z25: =IFERROR(Y25/Y24-1,0) -> 0.058444775 | AB25: =F25 -> 18012.2 | AC25: =IFERROR(AB25/AB24-1,0) -> 0.053693179 | AI25: Coefficients | AJ25: Standard Error | AK25: t Stat | AL25: P-value | AM25: Lower 95% | AN25: Upper 95% | AO25: Lower 95.0% | AP25: Upper 95.0% | AS25: =X25 -> 44571 | AT25: =IFERROR('Data for Beta >2'!AB21,0) -> 479.1 | AU25: =IFERROR(AT25/AT24-1,0) -> 0.095386163 | AW25: =AB25 -> 18012.2 | AX25: =IFERROR(AW25/AW24-1,0) -> 0.053693179 | BD25: Coefficients | BE25: Standard Error | BF25: t Stat | BG25: P-value | BH25: Lower 95% | BI25: Upper 95% | BJ25: Lower 95.0% | BK25: Upper 95.0% | BM25: 44571 | BN25: =IFERROR('Data for Beta >2'!AJ21,0) -> 1334.95 | BO25: =IFERROR(BN25/BN24-1,0) -> 0.18179001 | BQ25: =AW25 -> 18012.2 | BR25: =IFERROR(BQ25/BQ24-1,0) -> 0.053693179 | BX25: Coefficients | BY25: Standard Error | BZ25: t Stat | CA25: P-value | CB25: Lower 95% | CC25: Upper 95% | CD25: Lower 95.0% | CE25: Upper 95.0% | CG25: =IFERROR('Data for Beta >2'!AQ21,0) -> 44571 | CH25: =IFERROR('Data for Beta >2'!AR21,0) -> 223.4 | CI25: =IFERROR(CH25/CH24-1,0) -> 0.055516182 | CK25: =IFERROR('Data for Beta >2'!L21,0) -> 18012.2 | CL25: =IFERROR(CK25/CK24-1,0) -> 0.053693179 | CR25: Coefficients | CS25: Standard Error | CT25: t Stat | CU25: P-value | CV25: Lower 95% | CW25: Upper 95% | CX25: Lower 95.0% | CY25: Upper 95.0%
B26: =IFERROR('Data for Beta >2'!B22,0) -> 44572 | C26: =IFERROR('Data for Beta >2'!C22,0) -> 1377.03 | D26: =IFERROR(C26/C25-1,0) -> 0.08853545 | F26: =IFERROR('Data for Beta >2'!L22,0) -> 18758.35 | G26: =IFERROR(F26/F25-1,0) -> 0.041424701 | L26: Intercept | M26: 0.027716447 | N26: 0.012601369 | O26: 2.1994791 | P26: 0.03214498 | Q26: 0.0024522237 | R26: 0.052980671 | S26: 0.0024522237 | T26: 0.052980671 | X26: =B26 -> 44572 | Y26: =IFERROR('Data for Beta >2'!T22,0) -> 105.1 | Z26: =IFERROR(Y26/Y25-1,0) -> -0.0163781 | AB26: =F26 -> 18758.35 | AC26: =IFERROR(AB26/AB25-1,0) -> 0.041424701 | AH26: Intercept | AI26: 0.029950495 | AJ26: 0.010702811 | AK26: 2.7983764 | AL26: 0.0071058498 | AM26: 0.0084926498 | AN26: 0.051408339 | AO26: 0.0084926498 | AP26: 0.051408339 | AS26: =X26 -> 44572 | AT26: =IFERROR('Data for Beta >2'!AB22,0) -> 484.5 | AU26: =IFERROR(AT26/AT25-1,0) -> 0.011271133 | AW26: =AB26 -> 18758.35 | AX26: =IFERROR(AW26/AW25-1,0) -> 0.041424701 | BC26: Intercept | BD26: 0.033024284 | BE26: 0.020544046 | BF26: 1.6074869 | BG26: 0.11377968 | BH26: -0.0081640479 | BI26: 0.074212616 | BJ26: -0.0081640479 | BK26: 0.074212616 | BM26: 44572 | BN26: =IFERROR('Data for Beta >2'!AJ22,0) -> 1345.15 | BO26: =IFERROR(BN26/BN25-1,0) -> 0.0076407356 | BQ26: =AW26 -> 18758.35 | BR26: =IFERROR(BQ26/BQ25-1,0) -> 0.041424701 | BW26: Intercept | BX26: 0.021820018 | BY26: 0.021513244 | BZ26: 1.0142598 | CA26: 0.31588138 | CB26: -0.021509879 | CC26: 0.065149914 | CD26: -0.021509879 | CE26: 0.065149914 | CG26: =IFERROR('Data for Beta >2'!AQ22,0) -> 44572 | CH26: =IFERROR('Data for Beta >2'!AR22,0) -> 222.9 | CI26: =IFERROR(CH26/CH25-1,0) -> -0.0022381379 | CK26: =IFERROR('Data for Beta >2'!L22,0) -> 18758.35 | CL26: =IFERROR(CK26/CK25-1,0) -> 0.041424701 | CQ26: Intercept | CR26: 0.017359916 | CS26: 0.01809911 | CT26: 0.95915855 | CU26: 0.34260423 | CV26: -0.019093562 | CW26: 0.053813394 | CX26: -0.019093562 | CY26: 0.053813394
B27: =IFERROR('Data for Beta >2'!B23,0) -> 44573 | C27: =IFERROR('Data for Beta >2'!C23,0) -> 1265.63 | D27: =IFERROR(C27/C26-1,0) -> -0.080898746 | F27: =IFERROR('Data for Beta >2'!L23,0) -> 18105.3 | G27: =IFERROR(F27/F26-1,0) -> -0.03481383 | L27: X Variable 1 | M27: 1.6170793 | N27: 0.33670947 | O27: 4.8025952 | P27: 1.2840152e-05 | Q27: 0.94201745 | R27: 2.2921411 | S27: 0.94201745 | T27: 2.2921411 | X27: =B27 -> 44573 | Y27: =IFERROR('Data for Beta >2'!T23,0) -> 99.9 | Z27: =IFERROR(Y27/Y26-1,0) -> -0.049476689 | AB27: =F27 -> 18105.3 | AC27: =IFERROR(AB27/AB26-1,0) -> -0.03481383 | AH27: X Variable 1 | AI27: 1.2462382 | AJ27: 0.28597988 | AK27: 4.3577828 | AL27: 5.9255859e-05 | AM27: 0.67288307 | AN27: 1.8195933 | AO27: 0.67288307 | AP27: 1.8195933 | AS27: =X27 -> 44573 | AT27: =IFERROR('Data for Beta >2'!AB23,0) -> 472.05 | AU27: =IFERROR(AT27/AT26-1,0) -> -0.025696594 | AW27: =AB27 -> 18105.3 | AX27: =IFERROR(AW27/AW26-1,0) -> -0.03481383 | BC27: X Variable 1 | BD27: 1.466286 | BE27: 0.54893836 | BF27: 2.6711304 | BG27: 0.0099699779 | BH27: 0.36573081 | BI27: 2.5668411 | BJ27: 0.36573081 | BK27: 2.5668411 | BM27: 44573 | BN27: =IFERROR('Data for Beta >2'!AJ23,0) -> 1095.55 | BO27: =IFERROR(BN27/BN26-1,0) -> -0.18555551 | BQ27: =AW27 -> 18105.3 | BR27: =IFERROR(BQ27/BQ26-1,0) -> -0.03481383 | BW27: X Variable 1 | BX27: 1.8927246 | BY27: 0.58406852 | BZ27: 3.2405865 | CA27: 0.0022468227 | CB27: 0.7163502 | CC27: 3.069099 | CD27: 0.7163502 | CE27: 3.069099 | CG27: =IFERROR('Data for Beta >2'!AQ23,0) -> 44573 | CH27: =IFERROR('Data for Beta >2'!AR23,0) -> 213 | CI27: =IFERROR(CH27/CH26-1,0) -> -0.044414536 | CK27: =IFERROR('Data for Beta >2'!L23,0) -> 18105.3 | CL27: =IFERROR(CK27/CK26-1,0) -> -0.03481383 | CQ27: X Variable 1 | CR27: 0.97933055 | CS27: 0.46086628 | CT27: 2.1249776 | CU27: 0.039113952 | CV27: 0.051098208 | CW27: 1.9075629 | CX27: 0.051098208 | CY27: 1.9075629
B28: =IFERROR('Data for Beta >2'!B24,0) -> 44927 | C28: =IFERROR('Data for Beta >2'!C24,0) -> 1276.43 | D28: =IFERROR(C28/C27-1,0) -> 0.0085332996 | F28: =IFERROR('Data for Beta >2'!L24,0) -> 17662.15 | G28: =IFERROR(F28/F27-1,0) -> -0.024476258 | X28: =B28 -> 44927 | Y28: =IFERROR('Data for Beta >2'!T24,0) -> 94.95 | Z28: =IFERROR(Y28/Y27-1,0) -> -0.04954955 | AB28: =F28 -> 17662.15 | AC28: =IFERROR(AB28/AB27-1,0) -> -0.024476258 | AS28: =X28 -> 44927 | AT28: =IFERROR('Data for Beta >2'!AB24,0) -> 472.67 | AU28: =IFERROR(AT28/AT27-1,0) -> 0.0013134202 | AW28: =AB28 -> 17662.15 | AX28: =IFERROR(AW28/AW27-1,0) -> -0.024476258 | BM28: 44927 | BN28: =IFERROR('Data for Beta >2'!AJ24,0) -> 1392.5 | BO28: =IFERROR(BN28/BN27-1,0) -> 0.27105107 | BQ28: =AW28 -> 17662.15 | BR28: =IFERROR(BQ28/BQ27-1,0) -> -0.024476258 | CG28: =IFERROR('Data for Beta >2'!AQ24,0) -> 44927 | CH28: =IFERROR('Data for Beta >2'!AR24,0) -> 230.3 | CI28: =IFERROR(CH28/CH27-1,0) -> 0.081220657 | CK28: =IFERROR('Data for Beta >2'!L24,0) -> 17662.15 | CL28: =IFERROR(CK28/CK27-1,0) -> -0.024476258
B29: =IFERROR('Data for Beta >2'!B25,0) -> 44928 | C29: =IFERROR('Data for Beta >2'!C25,0) -> 1287.15 | D29: =IFERROR(C29/C28-1,0) -> 0.0083984237 | F29: =IFERROR('Data for Beta >2'!L25,0) -> 17303.95 | G29: =IFERROR(F29/F28-1,0) -> -0.020280657 | X29: =B29 -> 44928 | Y29: =IFERROR('Data for Beta >2'!T25,0) -> 94.6 | Z29: =IFERROR(Y29/Y28-1,0) -> -0.0036861506 | AB29: =F29 -> 17303.95 | AC29: =IFERROR(AB29/AB28-1,0) -> -0.020280657 | AS29: =X29 -> 44928 | AT29: =IFERROR('Data for Beta >2'!AB25,0) -> 467.25 | AU29: =IFERROR(AT29/AT28-1,0) -> -0.011466774 | AW29: =AB29 -> 17303.95 | AX29: =IFERROR(AW29/AW28-1,0) -> -0.020280657 | BM29: 44928 | BN29: =IFERROR('Data for Beta >2'!AJ25,0) -> 1305.9 | BO29: =IFERROR(BN29/BN28-1,0) -> -0.062190305 | BQ29: =AW29 -> 17303.95 | BR29: =IFERROR(BQ29/BQ28-1,0) -> -0.020280657 | CG29: =IFERROR('Data for Beta >2'!AQ25,0) -> 44928 | CH29: =IFERROR('Data for Beta >2'!AR25,0) -> 290.3 | CI29: =IFERROR(CH29/CH28-1,0) -> 0.26052974 | CK29: =IFERROR('Data for Beta >2'!L25,0) -> 17303.95 | CL29: =IFERROR(CK29/CK28-1,0) -> -0.020280657
B30: =IFERROR('Data for Beta >2'!B26,0) -> 44929 | C30: =IFERROR('Data for Beta >2'!C26,0) -> 1365.55 | D30: =IFERROR(C30/C29-1,0) -> 0.060909762 | F30: =IFERROR('Data for Beta >2'!L26,0) -> 17359.75 | G30: =IFERROR(F30/F29-1,0) -> 0.0032246973 | X30: =B30 -> 44929 | Y30: =IFERROR('Data for Beta >2'!T26,0) -> 97.55 | Z30: =IFERROR(Y30/Y29-1,0) -> 0.031183932 | AB30: =F30 -> 17359.75 | AC30: =IFERROR(AB30/AB29-1,0) -> 0.0032246973 | AS30: =X30 -> 44929 | AT30: =IFERROR('Data for Beta >2'!AB26,0) -> 494.35 | AU30: =IFERROR(AT30/AT29-1,0) -> 0.05799893 | AW30: =AB30 -> 17359.75 | AX30: =IFERROR(AW30/AW29-1,0) -> 0.0032246973 | BM30: 44929 | BN30: =IFERROR('Data for Beta >2'!AJ26,0) -> 1375.7 | BO30: =IFERROR(BN30/BN29-1,0) -> 0.053449728 | BQ30: =AW30 -> 17359.75 | BR30: =IFERROR(BQ30/BQ29-1,0) -> 0.0032246973 | CG30: =IFERROR('Data for Beta >2'!AQ26,0) -> 44929 | CH30: =IFERROR('Data for Beta >2'!AR26,0) -> 274.35 | CI30: =IFERROR(CH30/CH29-1,0) -> -0.054943162 | CK30: =IFERROR('Data for Beta >2'!L26,0) -> 17359.75 | CL30: =IFERROR(CK30/CK29-1,0) -> 0.0032246973
B31: =IFERROR('Data for Beta >2'!B27,0) -> 44930 | C31: =IFERROR('Data for Beta >2'!C27,0) -> 1460.1 | D31: =IFERROR(C31/C30-1,0) -> 0.069239501 | F31: =IFERROR('Data for Beta >2'!L27,0) -> 18065 | G31: =IFERROR(F31/F30-1,0) -> 0.040625585 | X31: =B31 -> 44930 | Y31: =IFERROR('Data for Beta >2'!T27,0) -> 103.3 | Z31: =IFERROR(Y31/Y30-1,0) -> 0.058944131 | AB31: =F31 -> 18065 | AC31: =IFERROR(AB31/AB30-1,0) -> 0.040625585 | AS31: =X31 -> 44930 | AT31: =IFERROR('Data for Beta >2'!AB27,0) -> 502.65 | AU31: =IFERROR(AT31/AT30-1,0) -> 0.016789724 | AW31: =AB31 -> 18065 | AX31: =IFERROR(AW31/AW30-1,0) -> 0.040625585 | BM31: 44930 | BN31: =IFERROR('Data for Beta >2'!AJ27,0) -> 1662.95 | BO31: =IFERROR(BN31/BN30-1,0) -> 0.20880279 | BQ31: =AW31 -> 18065 | BR31: =IFERROR(BQ31/BQ30-1,0) -> 0.040625585 | CG31: =IFERROR('Data for Beta >2'!AQ27,0) -> 44930 | CH31: =IFERROR('Data for Beta >2'!AR27,0) -> 278.25 | CI31: =IFERROR(CH31/CH30-1,0) -> 0.014215418 | CK31: =IFERROR('Data for Beta >2'!L27,0) -> 18065 | CL31: =IFERROR(CK31/CK30-1,0) -> 0.040625585
B32: =IFERROR('Data for Beta >2'!B28,0) -> 44931 | C32: =IFERROR('Data for Beta >2'!C28,0) -> 1558.53 | D32: =IFERROR(C32/C31-1,0) -> 0.067413191 | F32: =IFERROR('Data for Beta >2'!L28,0) -> 18534.4 | G32: =IFERROR(F32/F31-1,0) -> 0.025983947 | X32: =B32 -> 44931 | Y32: =IFERROR('Data for Beta >2'!T28,0) -> 112.15 | Z32: =IFERROR(Y32/Y31-1,0) -> 0.085672798 | AB32: =F32 -> 18534.4 | AC32: =IFERROR(AB32/AB31-1,0) -> 0.025983947 | AS32: =X32 -> 44931 | AT32: =IFERROR('Data for Beta >2'!AB28,0) -> 550.88 | AU32: =IFERROR(AT32/AT31-1,0) -> 0.095951457 | AW32: =AB32 -> 18534.4 | AX32: =IFERROR(AW32/AW31-1,0) -> 0.025983947 | BM32: 44931 | BN32: =IFERROR('Data for Beta >2'!AJ28,0) -> 1689.1 | BO32: =IFERROR(BN32/BN31-1,0) -> 0.015725067 | BQ32: =AW32 -> 18534.4 | BR32: =IFERROR(BQ32/BQ31-1,0) -> 0.025983947 | CG32: =IFERROR('Data for Beta >2'!AQ28,0) -> 44931 | CH32: =IFERROR('Data for Beta >2'!AR28,0) -> 369.65 | CI32: =IFERROR(CH32/CH31-1,0) -> 0.32848158 | CK32: =IFERROR('Data for Beta >2'!L28,0) -> 18534.4 | CL32: =IFERROR(CK32/CK31-1,0) -> 0.025983947
B33: =IFERROR('Data for Beta >2'!B29,0) -> 44932 | C33: =IFERROR('Data for Beta >2'!C29,0) -> 1896.25 | D33: =IFERROR(C33/C32-1,0) -> 0.21669137 | F33: =IFERROR('Data for Beta >2'!L29,0) -> 19189.05 | G33: =IFERROR(F33/F32-1,0) -> 0.035320809 | X33: =B33 -> 44932 | Y33: =IFERROR('Data for Beta >2'!T29,0) -> 125.75 | Z33: =IFERROR(Y33/Y32-1,0) -> 0.12126616 | AB33: =F33 -> 19189.05 | AC33: =IFERROR(AB33/AB32-1,0) -> 0.035320809 | AS33: =X33 -> 44932 | AT33: =IFERROR('Data for Beta >2'!AB29,0) -> 560.13 | AU33: =IFERROR(AT33/AT32-1,0) -> 0.016791316 | AW33: =AB33 -> 19189.05 | AX33: =IFERROR(AW33/AW32-1,0) -> 0.035320809 | BM33: 44932 | BN33: =IFERROR('Data for Beta >2'!AJ29,0) -> 1868.2 | BO33: =IFERROR(BN33/BN32-1,0) -> 0.1060328 | BQ33: =AW33 -> 19189.05 | BR33: =IFERROR(BQ33/BQ32-1,0) -> 0.035320809 | CG33: =IFERROR('Data for Beta >2'!AQ29,0) -> 44932 | CH33: =IFERROR('Data for Beta >2'!AR29,0) -> 386.95 | CI33: =IFERROR(CH33/CH32-1,0) -> 0.046801028 | CK33: =IFERROR('Data for Beta >2'!L29,0) -> 19189.05 | CL33: =IFERROR(CK33/CK32-1,0) -> 0.035320809
B34: =IFERROR('Data for Beta >2'!B30,0) -> 44933 | C34: =IFERROR('Data for Beta >2'!C30,0) -> 1980.75 | D34: =IFERROR(C34/C33-1,0) -> 0.044561635 | F34: =IFERROR('Data for Beta >2'!L30,0) -> 19753.8 | G34: =IFERROR(F34/F33-1,0) -> 0.029430847 | X34: =B34 -> 44933 | Y34: =IFERROR('Data for Beta >2'!T30,0) -> 130.7 | Z34: =IFERROR(Y34/Y33-1,0) -> 0.039363817 | AB34: =F34 -> 19753.8 | AC34: =IFERROR(AB34/AB33-1,0) -> 0.029430847 | AS34: =X34 -> 44933 | AT34: =IFERROR('Data for Beta >2'!AB30,0) -> 613.78 | AU34: =IFERROR(AT34/AT33-1,0) -> 0.095781336 | AW34: =AB34 -> 19753.8 | AX34: =IFERROR(AW34/AW33-1,0) -> 0.029430847 | BM34: 44933 | BN34: =IFERROR('Data for Beta >2'!AJ30,0) -> 2037.7 | BO34: =IFERROR(BN34/BN33-1,0) -> 0.090729044 | BQ34: =AW34 -> 19753.8 | BR34: =IFERROR(BQ34/BQ33-1,0) -> 0.029430847 | CG34: =IFERROR('Data for Beta >2'!AQ30,0) -> 44933 | CH34: =IFERROR('Data for Beta >2'!AR30,0) -> 497.4 | CI34: =IFERROR(CH34/CH33-1,0) -> 0.2854374 | CK34: =IFERROR('Data for Beta >2'!L30,0) -> 19753.8 | CL34: =IFERROR(CK34/CK33-1,0) -> 0.029430847
B35: =IFERROR('Data for Beta >2'!B31,0) -> 44934 | C35: =IFERROR('Data for Beta >2'!C31,0) -> 1950.15 | D35: =IFERROR(C35/C34-1,0) -> -0.015448694 | F35: =IFERROR('Data for Beta >2'!L31,0) -> 19253.8 | G35: =IFERROR(F35/F34-1,0) -> -0.025311586 | X35: =B35 -> 44934 | Y35: =IFERROR('Data for Beta >2'!T31,0) -> 133.2 | Z35: =IFERROR(Y35/Y34-1,0) -> 0.019127774 | AB35: =F35 -> 19253.8 | AC35: =IFERROR(AB35/AB34-1,0) -> -0.025311586 | AS35: =X35 -> 44934 | AT35: =IFERROR('Data for Beta >2'!AB31,0) -> 563.2 | AU35: =IFERROR(AT35/AT34-1,0) -> -0.082407377 | AW35: =AB35 -> 19253.8 | AX35: =IFERROR(AW35/AW34-1,0) -> -0.025311586 | BM35: 44934 | BN35: =IFERROR('Data for Beta >2'!AJ31,0) -> 2372.2 | BO35: =IFERROR(BN35/BN34-1,0) -> 0.16415567 | BQ35: =AW35 -> 19253.8 | BR35: =IFERROR(BQ35/BQ34-1,0) -> -0.025311586 | CG35: =IFERROR('Data for Beta >2'!AQ31,0) -> 44934 | CH35: =IFERROR('Data for Beta >2'!AR31,0) -> 526.95 | CI35: =IFERROR(CH35/CH34-1,0) -> 0.059408926 | CK35: =IFERROR('Data for Beta >2'!L31,0) -> 19253.8 | CL35: =IFERROR(CK35/CK34-1,0) -> -0.025311586
B36: =IFERROR('Data for Beta >2'!B32,0) -> 44935 | C36: =IFERROR('Data for Beta >2'!C32,0) -> 1928.15 | D36: =IFERROR(C36/C35-1,0) -> -0.011281183 | F36: =IFERROR('Data for Beta >2'!L32,0) -> 19638.3 | G36: =IFERROR(F36/F35-1,0) -> 0.019970084 | X36: =B36 -> 44935 | Y36: =IFERROR('Data for Beta >2'!T32,0) -> 138.3 | Z36: =IFERROR(Y36/Y35-1,0) -> 0.038288288 | AB36: =F36 -> 19638.3 | AC36: =IFERROR(AB36/AB35-1,0) -> 0.019970084 | AS36: =X36 -> 44935 | AT36: =IFERROR('Data for Beta >2'!AB32,0) -> 515.65 | AU36: =IFERROR(AT36/AT35-1,0) -> -0.084428267 | AW36: =AB36 -> 19638.3 | AX36: =IFERROR(AW36/AW35-1,0) -> 0.019970084 | BM36: 44935 | BN36: =IFERROR('Data for Beta >2'!AJ32,0) -> 2101.2 | BO36: =IFERROR(BN36/BN35-1,0) -> -0.11423995 | BQ36: =AW36 -> 19638.3 | BR36: =IFERROR(BQ36/BQ35-1,0) -> 0.019970084 | CG36: =IFERROR('Data for Beta >2'!AQ32,0) -> 44935 | CH36: =IFERROR('Data for Beta >2'!AR32,0) -> 517.4 | CI36: =IFERROR(CH36/CH35-1,0) -> -0.018123162 | CK36: =IFERROR('Data for Beta >2'!L32,0) -> 19638.3 | CL36: =IFERROR(CK36/CK35-1,0) -> 0.019970084
B37: =IFERROR('Data for Beta >2'!B33,0) -> 44936 | C37: =IFERROR('Data for Beta >2'!C33,0) -> 1823.05 | D37: =IFERROR(C37/C36-1,0) -> -0.054508207 | F37: =IFERROR('Data for Beta >2'!L33,0) -> 19079.6 | G37: =IFERROR(F37/F36-1,0) -> -0.028449509 | X37: =B37 -> 44936 | Y37: =IFERROR('Data for Beta >2'!T33,0) -> 133.25 | Z37: =IFERROR(Y37/Y36-1,0) -> -0.036514823 | AB37: =F37 -> 19079.6 | AC37: =IFERROR(AB37/AB36-1,0) -> -0.028449509 | AS37: =X37 -> 44936 | AT37: =IFERROR('Data for Beta >2'!AB33,0) -> 487.08 | AU37: =IFERROR(AT37/AT36-1,0) -> -0.055405799 | AW37: =AB37 -> 19079.6 | AX37: =IFERROR(AW37/AW36-1,0) -> -0.028449509 | BM37: 44936 | BN37: =IFERROR('Data for Beta >2'!AJ33,0) -> 1867.4 | BO37: =IFERROR(BN37/BN36-1,0) -> -0.11126975 | BQ37: =AW37 -> 19079.6 | BR37: =IFERROR(BQ37/BQ36-1,0) -> -0.028449509 | CG37: =IFERROR('Data for Beta >2'!AQ33,0) -> 44936 | CH37: =IFERROR('Data for Beta >2'!AR33,0) -> 490.05 | CI37: =IFERROR(CH37/CH36-1,0) -> -0.052860456 | CK37: =IFERROR('Data for Beta >2'!L33,0) -> 19079.6 | CL37: =IFERROR(CK37/CK36-1,0) -> -0.028449509
B38: =IFERROR('Data for Beta >2'!B34,0) -> 44937 | C38: =IFERROR('Data for Beta >2'!C34,0) -> 2379.8 | D38: =IFERROR(C38/C37-1,0) -> 0.30539481 | F38: =IFERROR('Data for Beta >2'!L34,0) -> 20133.15 | G38: =IFERROR(F38/F37-1,0) -> 0.055218663 | X38: =B38 -> 44937 | Y38: =IFERROR('Data for Beta >2'!T34,0) -> 145.9 | Z38: =IFERROR(Y38/Y37-1,0) -> 0.094934334 | AB38: =F38 -> 20133.15 | AC38: =IFERROR(AB38/AB37-1,0) -> 0.055218663 | AS38: =X38 -> 44937 | AT38: =IFERROR('Data for Beta >2'!AB34,0) -> 581.38 | AU38: =IFERROR(AT38/AT37-1,0) -> 0.19360269 | AW38: =AB38 -> 20133.15 | AX38: =IFERROR(AW38/AW37-1,0) -> 0.055218663 | BM38: 44937 | BN38: =IFERROR('Data for Beta >2'!AJ34,0) -> 2012.7 | BO38: =IFERROR(BN38/BN37-1,0) -> 0.077808718 | BQ38: =AW38 -> 20133.15 | BR38: =IFERROR(BQ38/BQ37-1,0) -> 0.055218663 | CG38: =IFERROR('Data for Beta >2'!AQ34,0) -> 44937 | CH38: =IFERROR('Data for Beta >2'!AR34,0) -> 538.45 | CI38: =IFERROR(CH38/CH37-1,0) -> 0.098765432 | CK38: =IFERROR('Data for Beta >2'!L34,0) -> 20133.15 | CL38: =IFERROR(CK38/CK37-1,0) -> 0.055218663
B39: =IFERROR('Data for Beta >2'!B35,0) -> 44938 | C39: =IFERROR('Data for Beta >2'!C35,0) -> 2804 | D39: =IFERROR(C39/C38-1,0) -> 0.17825027 | F39: =IFERROR('Data for Beta >2'!L35,0) -> 21731.4 | G39: =IFERROR(F39/F38-1,0) -> 0.079384001 | X39: =B39 -> 44938 | Y39: =IFERROR('Data for Beta >2'!T35,0) -> 184.2 | Z39: =IFERROR(Y39/Y38-1,0) -> 0.26250857 | AB39: =F39 -> 21731.4 | AC39: =IFERROR(AB39/AB38-1,0) -> 0.079384001 | AS39: =X39 -> 44938 | AT39: =IFERROR('Data for Beta >2'!AB35,0) -> 856.17 | AU39: =IFERROR(AT39/AT38-1,0) -> 0.47265128 | AW39: =AB39 -> 21731.4 | AX39: =IFERROR(AW39/AW38-1,0) -> 0.079384001 | BM39: 44938 | BN39: =IFERROR('Data for Beta >2'!AJ35,0) -> 1861.2 | BO39: =IFERROR(BN39/BN38-1,0) -> -0.075272023 | BQ39: =AW39 -> 21731.4 | BR39: =IFERROR(BQ39/BQ38-1,0) -> 0.079384001 | CG39: =IFERROR('Data for Beta >2'!AQ35,0) -> 44938 | CH39: =IFERROR('Data for Beta >2'!AR35,0) -> 610.65 | CI39: =IFERROR(CH39/CH38-1,0) -> 0.13408859 | CK39: =IFERROR('Data for Beta >2'!L35,0) -> 21731.4 | CL39: =IFERROR(CK39/CK38-1,0) -> 0.079384001
... B63: =IFERROR('Data for Beta >2'!B59,0) -> 45669 | C63: =IFERROR('Data for Beta >2'!C59,0) -> 4409.8 | D63: =IFERROR(C63/C62-1,0) -> -0.029191617 | F63: =IFERROR('Data for Beta >2'!L59,0) -> 26177.15 | G63: =IFERROR(F63/F62-1,0) -> -0.00098462196 | X63: =B63 -> 45669 | Y63: =IFERROR('Data for Beta >2'!T59,0) -> 399.4 | Z63: =IFERROR(Y63/Y62-1,0) -> -0.029993928 | AB63: =F63 -> 26177.15 | AC63: =IFERROR(AB63/AB62-1,0) -> -0.00098462196 | AS63: =X63 -> 45669 | AT63: =IFERROR('Data for Beta >2'!AB59,0) -> 1431.4 | AU63: =IFERROR(AT63/AT62-1,0) -> -0.054307611 | AW63: =AB63 -> 26177.15 | AX63: =IFERROR(AW63/AW62-1,0) -> -0.00098462196 | BM63: 45669 | BN63: =IFERROR('Data for Beta >2'!AJ59,0) -> 2657.8 | BO63: =IFERROR(BN63/BN62-1,0) -> -0.10535883 | BQ63: =AW63 -> 26177.15 | BR63: =IFERROR(BQ63/BQ62-1,0) -> -0.00098462196 | CG63: =IFERROR('Data for Beta >2'!AQ59,0) -> 45669 | CH63: =IFERROR('Data for Beta >2'!AR59,0) -> 739.85 | CI63: =IFERROR(CH63/CH62-1,0) -> -0.013072767 | CK63: =IFERROR('Data for Beta >2'!L59,0) -> 26177.15 | CL63: =IFERROR(CK63/CK62-1,0) -> -0.00098462196

Sheet Rm
B2: Return on Market
B4: Year | C4: Annual
B5: 2000 | C5: -0.1465 | E5: Average Returns | F5: =AVERAGE(C5:C29) -> 0.153348
B6: 2001 | C6: -0.1618 | E6: Dividend Yield | F6: 1.35%1
B7: 2002 | C7: 0.0325 | E7: Total Market Return | F7: =SUM(F5:F6) -> 0.153348
B8: 2003 | C8: 0.719
B9: 2004 | C9: 0.1068
B10: 2005 | C10: 0.3634
B11: 2006 | C11: 0.3983
B12: 2007 | C12: 0.5477
B13: 2008 | C13: -0.5179
B14: 2009 | C14: 0.7576
B15: 2010 | C15: 0.1795
B16: 2011 | C16: -0.2462
B17: 2012 | C17: 0.277
B18: 2013 | C18: 0.0676
B19: 2014 | C19: 0.3139
... B29: 2024 | C29: 0.0875

Sheet Data Sheet
A1: COMPANY NAME | B1: HINDUSTAN AERONAUTICS LTD
A2: LATEST VERSION | B2: 2.1 | E2: PLEASE DO NOT MAKE ANY CHANGES TO THIS SHEET
A3: CURRENT VERSION | B3: 2.1
A5: META
A6: Number of shares | B6: =IF(B9>0, B9/B8, 0) -> 66.890714
A7: Face Value | B7: 5
A8: Current Price | B8: 4321.6
A9: Market Capitalization | B9: 289074.91
A15: PROFIT & LOSS
A16: Report Date | B16: 42460 | C16: 42825 | D16: 43190 | E16: 43555 | F16: 43921 | G16: 44286 | H16: 44651 | I16: 45016 | J16: 45382 | K16: 45747
A17: Sales | B17: 16758.5 | C17: 17949.92 | D17: 18519.74 | E17: 20008 | F17: 21445.16 | G17: 22882.32 | H17: 24620.02 | I17: 26927.46 | J17: 30381.08 | K17: 30980.95
A18: Raw Material Cost | B18: 9175.6 | C18: 8425.61 | D18: 7712.8 | E18: 7301.75 | F18: 8483.24 | G18: 8467.86 | H18: 9151.74 | I18: 10536.96 | J18: 12718.89 | K18: 19589.16
A19: Change in Inventory | B19: 562.4 | C19: -510.92 | D19: -728.64 | E19: -1172.15 | F19: -635.68 | G19: -2458.14 | H19: -592.3 | I19: 690.72 | J19: 1958.64 | K19: 7625.79
A20: Power and Fuel | B20: 233.8 | C20: 171.87 | D20: 175.78 | E20: 182.21 | F20: 151.37 | G20: 183.39 | H20: 200.47 | I20: 202.55 | J20: 210.48 | K20: 211.98
A21: Other Mfr. Exp | B21: 391.4 | C21: 1160.02 | D21: 1292.02 | E21: 1120.38 | F21: 889.29 | G21: 923.25 | H21: 945.09 | I21: 1201.69 | J21: 1207.87 | K21: 1218.44
A22: Employee Cost | B22: 3274.5 | C22: 3570.49 | D22: 4310.68 | E22: 4311.03 | F22: 4777.62 | G22: 4305.17 | H22: 4604.42 | I22: 4910.37 | J22: 5290.69 | K22: 5730.37
A23: Selling and admin | B23: 226.58 | C23: 222.3 | D23: 209.9 | E23: 352.05 | F23: 155.55 | G23: 138.35 | H23: 179.9 | I23: 215.6 | J23: 241.69 | K23: 310.09
A24: Other Expenses | B24: 1545.12 | C24: 658.02 | D24: 641.23 | E24: 1017.4 | F24: 1438.17 | G24: 1062.18 | H24: 3530.73 | I24: 3865.35 | J24: 2918.52 | K24: 1925.68
A25: Other Income | B25: 1608.1 | C25: 1058.2 | D25: 775.7 | E25: 376.26 | F25: 422.51 | G25: 364.28 | H25: 984.93 | I25: 1672.92 | J25: 1923.1 | K25: 2608.23
A26: Depreciation | B26: 862.8 | C26: 680.68 | D26: 947.09 | E26: 1025.26 | F26: 998.52 | G26: 1157.89 | H26: 1110.53 | I26: 1784.67 | J26: 1407.17 | K26: 1340.37
A27: Interest | B27: 5.9 | C27: 16.45 | D27: 34.62 | E27: 177.6 | F27: 359.59 | G27: 266.89 | H27: 65.24 | I27: 64.41 | J27: 42.63 | K27: 21.62
... A31: Dividend Amount | B31: 629.01 | C31: 800 | D31: 1075.73 | E31: 662.09 | F31: 1111.85 | G31: 1003.17 | H31: 1337.56 | I31: 1839.14 | J31: 2340.73 | K31: 2675.12
A40: Quarters
A41: Report Date | B41: 45107 | C41: 45199 | D41: 45291 | E41: 45382 | F41: 45473 | G41: 45565 | H41: 45657 | I41: 45747 | J41: 45838 | K41: 45930
A42: Sales | B42: 3915.35 | C42: 5635.7 | D42: 6061.28 | E42: 14768.75 | F42: 4347.5 | G42: 5976.29 | H42: 6957.31 | I42: 13699.85 | J42: 4819.01 | K42: 6628.61
A43: Expenses | B43: 3038.52 | C43: 4108.06 | D43: 4625.95 | E43: 8867.49 | F43: 3356.79 | G43: 4336.33 | H43: 5274.8 | I43: 8404.95 | J43: 3536.61 | K43: 5070.72
A44: Other Income | B44: 413.6 | C44: 473.75 | D44: 466.63 | E44: 569.12 | F44: 742.38 | G44: 560.33 | H44: 636.83 | I44: 668.69 | J44: 757.37 | K44: 895.01
A45: Depreciation | B45: 201.38 | C45: 349.65 | D45: 212.17 | E45: 643.97 | F45: 149.23 | G45: 177.57 | H45: 277.08 | I45: 736.49 | J45: 185.16 | K45: 225.56
A46: Interest | B46: 0.02 | C46: 0.32 | D46: 0.36 | E46: 31.41 | F46: 0.14 | G46: 0.02 | H46: 0.08 | I46: 8.44 | J46: 0.3 | K46: 0.36
A47: Profit before tax | B47: 1089.03 | C47: 1651.42 | D47: 1689.43 | E47: 5795 | F47: 1583.72 | G47: 2022.7 | H47: 2042.18 | I47: 5218.66 | J47: 1854.31 | K47: 2226.98
A48: Tax | B48: 274.94 | C48: 414.75 | D48: 427.92 | E48: 1486.32 | F48: 146.58 | G48: 512.21 | H48: 602.39 | I48: 1242.03 | J48: 470.54 | K48: 557.93
A49: Net profit | B49: 814.24 | C49: 1236.7 | D49: 1261.4 | E49: 4308.71 | F49: 1437.16 | G49: 1510.48 | H49: 1439.83 | I49: 3976.66 | J49: 1383.77 | K49: 1669.07
A50: Operating Profit | B50: 876.83 | C50: 1527.64 | D50: 1435.33 | E50: 5901.26 | F50: 990.71 | G50: 1639.96 | H50: 1682.51 | I50: 5294.9 | J50: 1282.4 | K50: 1557.89
A55: BALANCE SHEET
A56: Report Date | B56: 42460 | C56: 42825 | D56: 43190 | E56: 43555 | F56: 43921 | G56: 44286 | H56: 44651 | I56: 45016 | J56: 45382 | K56: 45747
A57: Equity Share Capital | B57: 361.5 | C57: 361.5 | D57: 334.39 | E57: 334.39 | F57: 334.39 | G57: 334.39 | H57: 334.39 | I57: 334.39 | J57: 334.39 | K57: 334.39
A58: Reserves | B58: 10670.9 | C58: 12197.61 | D58: 9176.86 | E58: 11747.73 | F58: 12914.12 | G58: 15089.51 | H58: 18978.74 | I58: 23237.76 | J58: 28803.78 | K58: 34647.22
A59: Borrowings | B59: 79.8 | C59: 1022.03 | D59: 904.52 | E59: 4116.2 | F59: 5926.97 | G59: 53.28 | H59: 49.27 | I59: 51.69 | J59: 50.12 | K59: 51.44
A60: Other Liabilities | B60: 45419.7 | C60: 38162.56 | D60: 38046.84 | E60: 35298.01 | F60: 35027.18 | G60: 37619.24 | H60: 40891.94 | I60: 45652.16 | J60: 51722.55 | K60: 73665.41
A61: Total | B61: 56531.9 | C61: 51743.7 | D61: 48462.61 | E61: 51496.33 | F61: 54202.66 | G61: 53096.42 | H61: 60254.34 | I61: 69276 | J61: 80910.84 | K61: 108698.46
A62: Net Block | B62: 6925.2 | C62: 7349.56 | D62: 7566.22 | E62: 7459.35 | F62: 7357.49 | G62: 7165.88 | H62: 6765.88 | I62: 6834.4 | J62: 6736.89 | K62: 6670.8
A63: Capital Work in Progress | B63: 1025.4 | C63: 1389.4 | D63: 1461.72 | E63: 1502.11 | F63: 2042.69 | G63: 1949.6 | H63: 2472.94 | I63: 1885 | J63: 2493.43 | K63: 3097.75
A64: Investments | B64: 915.8 | C64: 993.99 | D64: 1010.11 | E64: 909.64 | F64: 990.8 | G64: 1121.32 | H64: 1362.7 | I64: 1457.92 | J64: 1591.33 | K64: 1754.2
A65: Other Assets | B65: 47665.5 | C65: 42010.75 | D65: 38424.56 | E65: 41625.23 | F65: 43811.68 | G65: 42859.62 | H65: 49652.82 | I65: 59098.68 | J65: 70089.19 | K65: 97175.71
A66: Total | B66: 56531.9 | C66: 51743.7 | D66: 48462.61 | E66: 51496.33 | F66: 54202.66 | G66: 53096.42 | H66: 60254.34 | I66: 69276 | J66: 80910.84 | K66: 108698.46
A67: Receivables | B67: 4836.9 | C67: 4220.16 | D67: 6751.54 | E67: 12458 | F67: 11234.73 | G67: 5668.05 | H67: 4641.53 | I67: 4719.18 | J67: 4616.85 | K67: 4647.79
... A70: No. of Equity Shares | B70: 361500000 | C70: 361500000 | D70: 334387500 | E70: 334387500 | F70: 334387500 | G70: 334387500 | H70: 334387500 | I70: 334387500 | J70: 668775000 | K70: 668775000
A71: New Bonus Shares
A72: Face value | B72: 10 | C72: 10 | D72: 10 | E72: 10 | F72: 10 | G72: 10 | H72: 10 | I72: 10 | J72: 5 | K72: 5
A80: CASH FLOW:
A81: Report Date | B81: 42460 | C81: 42825 | D81: 43190 | E81: 43555 | F81: 43921 | G81: 44286 | H81: 44651 | I81: 45016 | J81: 45382 | K81: 45747
A82: Cash from Operating Activity | C82: -404.5 | D82: -747.6 | E82: -7700.28 | F82: 1527.39 | G82: 15117 | H82: 10173.13 | I82: 8829.72 | J82: 8222.82 | K82: 13643.46
A83: Cash from Investing Activity | C83: 3011.8 | D83: 597 | E83: 5294.17 | F83: -1338.88 | G83: -1179.99 | H83: -12785.23 | I83: -5728.02 | J83: -6410.05 | K83: -10771.09
A84: Cash from Financing Activity | C84: -164.28 | D84: -2540.35 | E84: 2326.11 | F84: 63.94 | G84: -7070.18 | H84: -1463.68 | I84: -1731.3 | J84: -1998.85 | K84: -2578.51
A85: Net Cash Flow | C85: 2443.02 | D85: -2690.95 | E85: -80 | F85: 252.45 | G85: 6866.83 | H85: -4075.78 | I85: 1370.4 | J85: -186.08 | K85: 293.86
A90: PRICE: | D90: 566.43 | E90: 353.23 | F90: 260.15 | G90: 497.48 | H90: 742.45 | I90: 1365.55 | J90: 3327 | K90: 4177.45
A92: DERIVED:
A93: Adjusted Equity Shares in Cr | B93: 72.3 | C93: 72.3 | D93: 66.88 | E93: 66.88 | F93: 66.88 | G93: 66.88 | H93: 66.88 | I93: 66.88 | J93: 66.88 | K93: 66.88

Sheet Data for Beta >2
B1: ='Data Sheet'!B1 -> HINDUSTAN AERONAUTICS LTD | I1: From Investing.com | K1: Index | S1: =Wacc!B11 -> Bharat Electron | AA1: =Wacc!B12 -> Bharat Dynamics | AI1: =Wacc!B13 -> Data Pattern | AQ1: =Wacc!B14 -> Zen Technologies
B2: Date | C2: Price | D2: Open | E2: High | F2: Low | G2: Vol. | H2: Change % | K2: Date | L2: Price | M2: Open | N2: High | O2: Low | P2: Vol. | Q2: Change % | S2: Date | T2: Price | U2: Open | V2: High | W2: Low | X2: Vol. | Y2: Change % | AA2: Date | AB2: Price | AC2: Open | AD2: High | AE2: Low | AF2: Vol. | AG2: Change % | AI2: Date | AJ2: Price | AK2: Open | AL2: High | AM2: Low | AN2: Vol. | AO2: Change % | AQ2: Date | AR2: Price | AS2: Open | AT2: High | AU2: Low | AV2: Vol. | AW2: Change %
B3: 44200 | C3: 478.63 | D3: 508.5 | E3: 526 | F3: 464.5 | G3: 7.46M | H3: -0.0379 | K3: 44200 | L3: 14631.1 | M3: 14798.4 | N3: 15044.35 | O3: 14151.4 | P3: 9.64B | Q3: -0.0041 | S3: 44200 | T3: 43.92 | U3: 42 | V3: 45.48 | W3: 40.17 | X3: 583.25M | Y3: 0.0532 | AA3: 44200 | AB3: 168.43 | AC3: 166.5 | AD3: 175.95 | AE3: 160.55 | AF3: 5.10M | AG3: 0.0129 | AI3: 44200 | AJ3: 0 | AK3: 0 | AL3: 0 | AM3: 0 | AN3: 0 | AO3: 0 | AQ3: 44200 | AR3: 264.3 | AS3: 275 | AT3: 289.95 | AU3: 254.7 | AV3: 3.49M | AW3: -0.0352
B4: 44201 | C4: 510.27 | D4: 477.85 | E4: 523 | F4: 471 | G4: 8.00M | H4: 0.0661 | K4: 44201 | L4: 15582.8 | M4: 14481.05 | N4: 15606.35 | O4: 14416.25 | P4: 10.27B | Q4: 0.065 | S4: 44201 | T4: 48.47 | U4: 43.67 | V4: 53.33 | W4: 42.95 | X4: 1.51B | Y4: 0.1036 | AA4: 44201 | AB4: 180.85 | AC4: 168.38 | AD4: 188 | AE4: 163 | AF4: 10.26M | AG4: 0.0738 | AI4: 44201 | AJ4: 0 | AK4: 0 | AL4: 0 | AM4: 0 | AN4: 0 | AO4: 0 | AQ4: 44201 | AR4: 285.8 | AS4: 264 | AT4: 306.9 | AU4: 262.3 | AV4: 5.99M | AW4: 0.0813
B5: 44202 | C5: 510.9 | D5: 524.5 | E5: 544.5 | F5: 495.6 | G5: 10.00M | H5: 0.0012 | K5: 44202 | L5: 15721.5 | M5: 15629.65 | N5: 15915.65 | O5: 15450.9 | P5: 8.08B | Q5: 0.0089 | S5: 44202 | T5: 59.33 | U5: 51 | V5: 59.63 | W5: 46.83 | X5: 1.19B | Y5: 0.2242 | AA5: 44202 | AB5: 178.98 | AC5: 186 | AD5: 188.8 | AE5: 172.63 | AF5: 11.82M | AG5: -0.0104 | AI5: 44202 | AJ5: 0 | AK5: 0 | AL5: 0 | AM5: 0 | AN5: 0 | AO5: 0 | AQ5: 44202 | AR5: 311.35 | AS5: 288.4 | AT5: 319.2 | AU5: 279 | AV5: 52.34M | AW5: 0.0894
B6: 44203 | C6: 558.17 | D6: 512.75 | E6: 578.5 | F6: 505 | G6: 24.34M | H6: 0.0925 | K6: 44203 | L6: 15763.05 | M6: 15755.05 | N6: 15962.25 | O6: 15513.45 | P6: 6.00B | Q6: 0.0026 | S6: 44203 | T6: 61.55 | U6: 59.27 | V6: 63.9 | W6: 59.03 | X6: 588.86M | Y6: 0.0374 | AA6: 44203 | AB6: 210.02 | AC6: 181.48 | AD6: 213.3 | AE6: 179.63 | AF6: 28.41M | AG6: 0.1735 | AI6: 44203 | AJ6: 0 | AK6: 0 | AL6: 0 | AM6: 0 | AN6: 0 | AO6: 0 | AQ6: 44203 | AR6: 415.9 | AS6: 317 | AT6: 428.4 | AU6: 312.3 | AV6: 55.09M | AW6: 0.3358
B7: 44204 | C7: 687.9 | D7: 560.03 | E7: 728.5 | F7: 529.55 | G7: 44.98M | H7: 0.2324 | K7: 44204 | L7: 17132.2 | M7: 15874.9 | N7: 17153.5 | O7: 15834.65 | P7: 6.35B | Q7: 0.0869 | S7: 44204 | T7: 62.22 | U7: 61.67 | V7: 62.47 | W7: 54.12 | X7: 573.74M | Y7: 0.0108 | AA7: 44204 | AB7: 196.55 | AC7: 210.4 | AD7: 214.6 | AE7: 183.5 | AF7: 14.89M | AG7: -0.0642 | AI7: 44204 | AJ7: 0 | AK7: 0 | AL7: 0 | AM7: 0 | AN7: 0 | AO7: 0 | AQ7: 44204 | AR7: 450.3 | AS7: 419.65 | AT7: 465.25 | AU7: 377 | AV7: 29.20M | AW7: 0.0827
B8: 44205 | C8: 677.22 | D8: 682 | E8: 743.47 | F8: 658 | G8: 50.51M | H8: -0.0155 | K8: 44205 | L8: 17618.15 | M8: 17185.6 | N8: 17947.65 | O8: 17055.05 | P8: 6.96B | Q8: 0.0284 | S8: 44205 | T8: 67.65 | U8: 62.4 | V8: 70.82 | W8: 62.18 | X8: 472.30M | Y8: 0.0873 | AA8: 44205 | AB8: 191.48 | AC8: 196.52 | AD8: 206.45 | AE8: 188.1 | AF8: 8.96M | AG8: -0.0258 | AI8: 44205 | AJ8: 0 | AK8: 0 | AL8: 0 | AM8: 0 | AN8: 0 | AO8: 0 | AQ8: 44205 | AR8: 477.8 | AS8: 450.3 | AT8: 587 | AU8: 428.15 | AV8: 34.21M | AW8: 0.0611
B9: 44206 | C9: 653.3 | D9: 676.65 | E9: 783 | F9: 616.95 | G9: 40.91M | H9: -0.0353 | K9: 44206 | L9: 17671.65 | M9: 17531.9 | N9: 18604.45 | O9: 17452.9 | P9: 7.65B | Q9: 0.003 | S9: 44206 | T9: 68.95 | U9: 66.67 | V9: 73.83 | W9: 61.15 | X9: 399.39M | Y9: 0.0192 | AA9: 44206 | AB9: 202.73 | AC9: 191 | AD9: 227.5 | AE9: 184.07 | AF9: 21.08M | AG9: 0.0588 | AI9: 44206 | AJ9: 0 | AK9: 0 | AL9: 0 | AM9: 0 | AN9: 0 | AO9: 0 | AQ9: 44206 | AR9: 461.65 | AS9: 473 | AT9: 524.4 | AU9: 432.15 | AV9: 30.93M | AW9: -0.0338
B10: 44207 | C10: 638.45 | D10: 659.83 | E10: 728 | F10: 617.58 | G10: 31.25M | H10: -0.0227 | K10: 44207 | L10: 16983.2 | M10: 17783.15 | N10: 18210.15 | O10: 16782.4 | P10: 5.85B | Q10: -0.039 | S10: 44207 | T10: 67.92 | U10: 69.23 | V10: 76 | W10: 62.93 | X10: 409.65M | Y10: -0.015 | AA10: 44207 | AB10: 207.23 | AC10: 202.73 | AD10: 225.5 | AE10: 185 | AF10: 12.45M | AG10: 0.0222 | AI10: 44207 | AJ10: 0 | AK10: 0 | AL10: 0 | AM10: 0 | AN10: 0 | AO10: 0 | AQ10: 44207 | AR10: 446.55 | AS10: 464 | AT10: 508.6 | AU10: 380.6 | AV10: 39.87M | AW10: -0.0327
B11: 44208 | C11: 605.33 | D11: 638.7 | E11: 664 | F11: 590.6 | G11: 20.14M | H11: -0.0519 | K11: 44208 | L11: 17354.05 | M11: 17104.4 | N11: 17639.5 | O11: 16410.2 | P11: 5.50B | Q11: 0.0218 | S11: 44208 | T11: 69.98 | U11: 68 | V11: 71.57 | W11: 63.88 | X11: 367.60M | Y11: 0.0304 | AA11: 44208 | AB11: 194.77 | AC11: 207.1 | AD11: 219.5 | AE11: 188.6 | AF11: 6.51M | AG11: -0.0601 | AI11: 44208 | AJ11: 0 | AK11: 0 | AL11: 0 | AM11: 0 | AN11: 0 | AO11: 0 | AQ11: 44208 | AR11: 521.55 | AS11: 445 | AT11: 538 | AU11: 420.9 | AV11: 47.09M | AW11: 0.168
B12: 44562 | C12: 721.85 | D12: 607 | E12: 735.5 | F12: 606.03 | G12: 35.43M | H12: 0.1925 | K12: 44562 | L12: 17339.85 | M12: 17387.15 | N12: 18350.95 | O12: 16836.8 | P12: 5.44B | Q12: -0.0008 | S12: 44562 | T12: 69.9 | U12: 69.92 | V12: 74.27 | W12: 64.73 | X12: 408.05M | Y12: -0.0012 | AA12: 44562 | AB12: 248.95 | AC12: 194 | AD12: 255.88 | AE12: 192.82 | AF12: 22.42M | AG12: 0.2781 | AI12: 44562 | AJ12: 721.8 | AK12: 764 | AL12: 834 | AM12: 705.6 | AN12: 12.14M | AO12: -0.0501 | AQ12: 44562 | AR12: 415.5 | AS12: 524.9 | AT12: 539 | AU12: 383.95 | AV12: 30.05M | AW12: -0.2033
B13: 44563 | C13: 693.88 | D13: 728.83 | E13: 737.4 | F13: 620 | G13: 22.45M | H13: -0.0388 | K13: 44563 | L13: 16793.9 | M13: 17529.45 | N13: 17794.6 | O13: 16203.25 | P13: 5.62B | Q13: -0.0315 | S13: 44563 | T13: 70.15 | U13: 70.55 | V13: 70.82 | W13: 62.33 | X13: 382.51M | Y13: 0.0036 | AA13: 44563 | AB13: 224.07 | AC13: 251.95 | AD13: 268.15 | AE13: 203.25 | AF13: 26.45M | AG13: -0.0999 | AI13: 44563 | AJ13: 613.55 | AK13: 727.6 | AL13: 753.85 | AM13: 575 | AN13: 4.42M | AO13: -0.15 | AQ13: 44563 | AR13: 346.35 | AS13: 427 | AT13: 441 | AU13: 313.35 | AV13: 20.60M | AW13: -0.1664
B14: 44564 | C14: 742.45 | D14: 693.45 | E14: 748.15 | F14: 652.28 | G14: 32.60M | H14: 0.07 | K14: 44564 | L14: 17464.75 | M14: 16593.1 | N14: 17559.8 | O14: 15671.45 | P14: 7.96B | Q14: 0.0399 | S14: 44564 | T14: 70.27 | U14: 69.18 | V14: 75.5 | W14: 67.75 | X14: 592.57M | Y14: 0.0017 | AA14: 44564 | AB14: 274.65 | AC14: 229.48 | AD14: 306 | AE14: 219.32 | AF14: 39.96M | AG14: 0.2257 | AI14: 44564 | AJ14: 702.9 | AK14: 610 | AL14: 740.35 | AM14: 603.95 | AN14: 5.07M | AO14: 0.1456 | AQ14: 44564 | AR14: 366.95 | AS14: 346 | AT14: 392.35 | AU14: 331.3 | AV14: 16.05M | AW14: 0.0595
B15: 44565 | C15: 797.55 | D15: 746 | E15: 879 | F15: 740.22 | G15: 46.04M | H15: 0.0742 | K15: 44565 | L15: 17102.55 | M15: 17436.9 | N15: 18114.65 | O15: 16824.7 | P15: 5.66B | Q15: -0.0207 | S15: 44565 | T15: 79.52 | U15: 70.32 | V15: 86.5 | W15: 70.08 | X15: 756.72M | Y15: 0.1316 | AA15: 44565 | AB15: 374.1 | AC15: 274.2 | AD15: 452.45 | AE15: 272.5 | AF15: 132.00M | AG15: 0.3621 | AI15: 44565 | AJ15: 797.9 | AK15: 705 | AL15: 934.8 | AM15: 705 | AN15: 8.81M | AO15: 0.1352 | AQ15: 44565 | AR15: 323.1 | AS15: 366.5 | AT15: 394.7 | AU15: 312.5 | AV15: 15.74M | AW15: -0.1195
B16: 44566 | C16: 919.15 | D16: 789 | E16: 936 | F16: 734 | G16: 38.36M | H16: 0.1525 | K16: 44566 | L16: 16584.55 | M16: 16924.45 | N16: 17132.85 | O16: 15735.75 | P16: 6.34B | Q16: -0.0303 | S16: 44566 | T16: 78.25 | U16: 78.33 | V16: 80.07 | W16: 71.92 | X16: 344.67M | Y16: -0.0159 | AA16: 44566 | AB16: 391.83 | AC16: 371 | AD16: 406.4 | AE16: 304.23 | AF16: 67.36M | AG16: 0.0474 | AI16: 44566 | AJ16: 764.65 | AK16: 780 | AL16: 792.1 | AM16: 650 | AN16: 3.62M | AO16: -0.0417 | AQ16: 44566 | AR16: 305.8 | AS16: 315.2 | AT16: 320.95 | AU16: 262.65 | AV16: 19.62M | AW16: -0.0535
B17: 44567 | C17: 884.9 | D17: 924 | E17: 986.28 | F17: 850 | G17: 46.06M | H17: -0.0373 | K17: 44567 | L17: 15780.25 | M17: 16594.4 | N17: 16793.85 | O17: 15183.4 | P17: 5.51B | Q17: -0.0485 | S17: 44567 | T17: 78.03 | U17: 78.45 | V17: 83.48 | W17: 74.57 | X17: 341.21M | Y17: -0.0028 | AA17: 44567 | AB17: 340.63 | AC17: 404 | AD17: 426.67 | AE17: 323.8 | AF17: 74.09M | AG17: -0.1307 | AI17: 44567 | AJ17: 640.5 | AK17: 765 | AL17: 792 | AM17: 607.75 | AN17: 2.30M | AO17: -0.1624 | AQ17: 44567 | AR17: 272.1 | AS17: 307.45 | AT17: 323.6 | AU17: 246.65 | AV17: 9.02M | AW17: -0.1102
B18: 44568 | C18: 1012.5 | D18: 881.5 | E18: 1033.3 | F18: 860.05 | G18: 38.01M | H18: 0.1442 | K18: 44568 | L18: 17158.25 | M18: 15703.7 | N18: 17172.8 | O18: 15511.05 | P18: 5.48B | Q18: 0.0873 | S18: 44568 | T18: 91.73 | U18: 77.67 | V18: 92.3 | W18: 74.72 | X18: 539.96M | Y18: 0.1756 | AA18: 44568 | AB18: 405.88 | AC18: 338.5 | AD18: 409.7 | AE18: 330.02 | AF18: 35.52M | AG18: 0.1916 | AI18: 44568 | AJ18: 776.15 | AK18: 639.7 | AL18: 789 | AM18: 630.15 | AN18: 2.36M | AO18: 0.2118 | AQ18: 44568 | AR18: 247.55 | AS18: 273.15 | AT18: 275.8 | AU18: 245.1 | AV18: 11.44M | AW18: -0.0902
B19: 44569 | C19: 1147.6 | D19: 1015 | E19: 1174.97 | F19: 987.88 | G19: 50.27M | H19: 0.1334 | K19: 44569 | L19: 17759.3 | M19: 17243.2 | N19: 17992.2 | O19: 17154.8 | P19: 5.59B | Q19: 0.035 | S19: 44569 | T19: 102.17 | U19: 92.07 | V19: 103.95 | W19: 89.08 | X19: 522.63M | Y19: 0.1137 | AA19: 44569 | AB19: 408.9 | AC19: 406.5 | AD19: 448.95 | AE19: 392.88 | AF19: 53.84M | AG19: 0.0075 | AI19: 44569 | AJ19: 1067.2 | AK19: 776.95 | AL19: 1097.55 | AM19: 742.1 | AN19: 6.37M | AO19: 0.375 | AQ19: 44569 | AR19: 230.9 | AS19: 250 | AT19: 255.5 | AU19: 221.75 | AV19: 31.31M | AW19: -0.0673
B20: 44570 | C20: 1172.43 | D20: 1135.5 | E20: 1319.18 | F20: 1120.53 | G20: 58.26M | H20: 0.0216 | K20: 44570 | L20: 17094.35 | M20: 17485.7 | N20: 18096.15 | O20: 16747.7 | P20: 6.90B | Q20: -0.0374 | S20: 44570 | T20: 100.95 | U20: 102.28 | V20: 114.65 | W20: 96.25 | X20: 611.10M | Y20: -0.0119 | AA20: 44570 | AB20: 437.38 | AC20: 409.45 | AD20: 489.55 | AE20: 404 | AF20: 89.91M | AG20: 0.0696 | AI20: 44570 | AJ20: 1129.6 | AK20: 1058.95 | AL20: 1270.4 | AM20: 1050 | AN20: 6.54M | AO20: 0.0585 | AQ20: 44570 | AR20: 211.65 | AS20: 230 | AT20: 245.95 | AU20: 208 | AV20: 21.41M | AW20: -0.0834
B21: 44571 | C21: 1265.03 | D21: 1177.43 | E21: 1278.5 | F21: 1138 | G21: 33.81M | H21: 0.079 | K21: 44571 | L21: 18012.2 | M21: 17102.1 | N21: 18022.8 | O21: 16855.55 | P21: 4.54B | Q21: 0.0537 | S21: 44571 | T21: 106.85 | U21: 101.45 | V21: 109.2 | W21: 98.1 | X21: 301.76M | Y21: 0.0584 | AA21: 44571 | AB21: 479.1 | AC21: 434 | AD21: 513.47 | AE21: 417.98 | AF21: 47.95M | AG21: 0.0954 | AI21: 44571 | AJ21: 1334.95 | AK21: 1128 | AL21: 1465 | AM21: 1077 | AN21: 6.81M | AO21: 0.1818 | AQ21: 44571 | AR21: 223.4 | AS21: 212.4 | AT21: 229.95 | AU21: 208.65 | AV21: 15.69M | AW21: 0.0555
B22: 44572 | C22: 1377.03 | D22: 1269 | E22: 1387.47 | F22: 1205.6 | G22: 51.48M | H22: 0.0885 | K22: 44572 | L22: 18758.35 | M22: 18130.7 | N22: 18816.05 | O22: 17959.2 | P22: 5.26B | Q22: 0.0414 | S22: 44572 | T22: 105.1 | U22: 107.3 | V22: 112.2 | W22: 104.15 | X22: 378.82M | Y22: -0.0164 | AA22: 44572 | AB22: 484.5 | AC22: 479.75 | AD22: 502.5 | AE22: 456.35 | AF22: 41.20M | AG22: 0.0113 | AI22: 44572 | AJ22: 1345.15 | AK22: 1359 | AL22: 1459.9 | AM22: 1267.95 | AN22: 5.25M | AO22: 0.0076 | AQ22: 44572 | AR22: 222.9 | AS22: 223.4 | AT22: 225 | AU22: 209.5 | AV22: 11.41M | AW22: -0.0022
B23: 44573 | C23: 1265.63 | D23: 1380 | E23: 1405.9 | F23: 1207.5 | G23: 30.46M | H23: -0.0809 | K23: 44573 | L23: 18105.3 | M23: 18871.95 | N23: 18887.6 | O23: 17774.25 | P23: 4.74B | Q23: -0.0348 | S23: 44573 | T23: 99.9 | U23: 105.65 | V23: 108.4 | W23: 94.65 | X23: 320.36M | Y23: -0.0495 | AA23: 44573 | AB23: 472.05 | AC23: 486.75 | AD23: 496 | AE23: 398.7 | AF23: 30.51M | AG23: -0.0257 | AI23: 44573 | AJ23: 1095.55 | AK23: 1351.9 | AL23: 1374.35 | AM23: 996.35 | AN23: 3.20M | AO23: -0.1856 | AQ23: 44573 | AR23: 213 | AS23: 225.45 | AT23: 247.4 | AU23: 201.5 | AV23: 23.42M | AW23: -0.0444
... B59: 45669 | C59: 4409.8 | D59: 4562 | E59: 4584 | F59: 4187.1 | G59: 15.49M | H59: -0.0292 | K59: 45669 | L59: 26177.15 | M59: 26325.8 | N59: 26325.8 | O59: 25694.8 | P59: 4.16B | Q59: -0.001 | S59: 45669 | T59: 399.4 | U59: 415.9 | V59: 419.2 | W59: 380.5 | X59: 189.93M | Y59: -0.03 | AA59: 45669 | AB59: 1431.4 | AC59: 1521.3 | AD59: 1560 | AE59: 1306.1 | AF59: 22.15M | AG59: -0.0543 | AI59: 45669 | AJ59: 2657.8 | AK59: 2987 | AL59: 3025 | AM59: 2440.1 | AN59: 5.72M | AO59: -0.1054 | AQ59: 45669 | AR59: 739.85 | AS59: 751 | AT59: 756 | AU59: 709.5 | AV59: 4.79M | AW59: -0.0131

Sheet Raw FS
B2: BALANCE SHEET | C2: 44256 | D2: 44621 | E2: 44986 | F2: 45352 | G2: 45717 | K2: Cash Flow Statement | L2: 44256 | M2: 44621 | N2: 44986 | O2: 45352 | P2: 45717
B3: Equity Capital | C3: 334 | D3: 334 | E3: 334 | F3: 334 | G3: 334 | K3: Cash from Operating Activity - | L3: 15117 | M3: 10173 | N3: 8830 | O3: 8223 | P3: 13643
B4: Reserves | C4: 15090 | D4: 18979 | E4: 23238 | F4: 28804 | G4: 34647 | K4: Profit from operations | L4: 6744 | M4: 9611 | N4: 11134 | O4: 13317 | P4: 12426
B5: Borrowings - | C5: 53 | D5: 49 | E5: 52 | F5: 50 | G5: 51 | K5: Receivables | L5: 4996 | M5: 611 | N5: -1750 | O5: -2474 | P5: -4177
B6: Long term Borrowings | C6: 0 | D6: 0 | E6: 0 | F6: 0 | G6: 0 | K6: Inventory | L6: 2456 | M6: 1766 | N6: 1917 | O6: -2070 | P6: -8535
B7: Short term Borrowings | C7: 9.07 | D7: 0 | E7: 0 | F7: 0 | G7: 0 | K7: Payables | L7: -1836 | M7: 302 | N7: 577 | O7: 278 | P7: 1693
B8: Lease Liabilities | C8: 2.39 | D8: 2.49 | E8: 2.65 | F8: 1.1 | G8: 1.16 | K8: Other WC items | L8: 3633 | M8: -1090 | N8: -293 | O8: 1142 | P8: 15775
B9: Other Borrowings | C9: 41.82 | D9: 46.78 | E9: 49.04 | F9: 49.02 | G9: 50.28 | K9: Working capital changes | L9: 9248 | M9: 1589 | N9: 452 | O9: -3125 | P9: 4756
B10: Other Liabilities - | C10: 37619 | D10: 40892 | E10: 45652 | F10: 51723 | G10: 73665 | K10: Direct taxes | L10: -875 | M10: -1027 | N10: -2756 | O10: -1969 | P10: -3538
B11: Non controlling int | C11: 4 | D11: 4 | E11: 4 | F11: 4 | G11: 4 | K11: Cash from Investing Activity - | L11: -1180 | M11: -12785 | N11: -5728 | O11: -6410 | P11: -10771
B12: Trade Payables | C12: 2256 | D12: 2558 | E12: 3135 | F12: 3413 | G12: 5106 | K12: Fixed assets purchased | L12: -1209 | M12: -1501 | N12: -1781 | O12: -1755 | P12: -1757
B13: Advance from Customers | C13: 16553 | D13: 4352 | E13: 5540 | F13: 7363 | G13: 9789 | K13: Fixed assets sold | L13: 1 | M13: 3 | N13: 5 | O13: 8 | P13: 3
... B27: Accumulated Depreciation | C27: 6006 | D27: 7237 | E27: 9023 | F27: 10431 | G27: 11774 | K27: Net Cash Flow | L27: 6867 | M27: -4076 | N27: 1370 | O27: -186 | P27: 294
B28: CWIP | C28: 1950 | D28: 2473 | E28: 1885 | F28: 2493 | G28: 3098
B29: Investments | C29: 1121 | D29: 1363 | E29: 1458 | F29: 1591 | G29: 1754
B30: Other Assets - | C30: 42860 | D30: 49653 | E30: 59099 | F30: 70089 | G30: 97176
B31: Inventories | C31: 18005 | D31: 16210 | E31: 14221 | F31: 16033 | G31: 24107
B32: Trade receivables | C32: 5668 | D32: 4642 | E32: 4719 | F32: 4617 | G32: 4648
B33: Cash Equivalents | C33: 7177 | D33: 14348 | E33: 20317 | F33: 26432 | G33: 38182
B34: Loans n Advances | C34: 951 | D34: -962 | E34: -1093 | F34: -41 | G34: -186
B35: Other asset items | C35: 11058 | D35: 15416 | E35: 20935 | F35: 23049 | G35: 30424
B36: Total Assets | C36: 53096 | D36: 60254 | E36: 69276 | F36: 80911 | G36: 108698

Sheet Peer data
B2: S.No. | C2: Name | D2: CMP Rs. | E2: Mar Cap Rs.Cr. | F2: Debt Rs.Cr. | G2: No. Eq. Shares Cr. | H2: Cash End Rs.Cr. | I2: EV Rs.Cr. | J2: Eq Cap Rs.Cr. | K2: Sales Rs.Cr. | L2: EBIT 12M Rs.Cr. | M2: Dep 12M Rs.Cr. | N2: NP 12M Rs.Cr.
B3: 1 | C3: Hind.Aeronautics | D3: 4421.3 | E3: 295685.49 | F3: 11.4 | G3: 66.88 | H3: 38182.25 | I3: 251225.42 | J3: 334.39 | K3: 32104.78 | L3: 11351.31 | M3: 1424.29 | N3: 8469.24
B4: 2 | C4: Bharat Electron | D4: 400 | E4: 292391.15 | F4: 58.89 | G4: 730.98 | H4: 9545.1 | I4: 284333.52 | J4: 730.98 | K4: 25152.11 | L4: 7628.46 | M4: 495.79 | N4: 5694.83
B5: 3 | C5: Bharat Dynamics | D5: 1481.2 | E5: 54295.24 | F5: 1.24 | G5: 36.66 | H5: 4190.37 | I5: 50114.84 | J5: 182.38 | K5: 4004.08 | L5: 885.27 | M5: 74.13 | N5: 654.13
B6: 4 | C6: Data Pattern | D6: 2672.3 | E6: 14960.6 | F6: 5.81 | G6: 5.6 | H6: 126.4 | I6: 14893.07 | J6: 11.2 | K6: 920.04 | L6: 324.07 | M6: 18.49 | N6: 233.43
B7: 5 | C7: Zen Technologies | D7: 1391.6 | E7: 12564.81 | F7: 17.95 | G7: 9.03 | H7: 965.78 | I7: 11750.03 | J7: 9.03 | K7: 808.97 | L7: 384.28 | M7: 20.61 | N7: 271.4
B8: 6 | C8: Apollo Micro Sys | D8: 263 | E8: 9396.79 | F8: 311.03 | G8: 35.73 | H8: 22.42 | I8: 9650.43 | J8: 33.56 | K8: 669 | L8: 163.73 | M8: 17.36 | N8: 85.24

Sheet List of Stocks
A2: COMPANY_NAME | B2: BSE | C2: NSE | D2: Industry
A3: 20 MICRONS LTD | B3: 533022 | C3: 20MICRONS | D3: Mining
A4: 21ST CENTURY MANAGEMENT SERVICES LTD | B4: 526921 | C4: 21STCENMGM | D4: Other Financial Services
A5: 3I INFOTECH LTD | B5: 532628 | C5: 3IINFOTECH | D5: IT Consulting & Software
A6: 3M (INDIA) LTD | B6: 523395 | C6: 3M(INDIA) | D6: Diversified
A7: 3M INDIA LTD | B7: 523395 | C7: 3MINDIA | D7: Diversified
A8: 3P LAND HOLDINGS LTD | B8: 516092 | C8: 3PLAND | D8: Paper & Paper Products
A9: 5PAISA CAPITAL LTD | B9: 540776 | C9: 5PAISA | D9: Other Financial Services
A10: 63 MOONS TECHNOLOGIES LTD | B10: 526881 | C10: 63MOONS | D10: IT Consulting & Software
A11: 7NR RETAIL LTD | B11: 540615 | C11: Not Listed | D11: Specialty Retail
A12: 7SEAS ENTERTAINMENT LTD | B12: 540874 | C12: Not Listed | D12: Movies & Entertainment
A13: 8K MILES SOFTWARE SERVICES LTD | B13: 512161 | C13: 8KMILES | D13: Internet Software & Services
A14: A & M FEBCON LTD | B14: 540697 | C14: Not Listed | D14: Industrial Machinery
A15: A AND M JUMBO BAGS LTD | B15: Not Listed | C15: AMJUMBO | D15: SME
A16: A INFRASTRUCTURE LTD | B16: 539620 | C16: Not Listed | D16: Cement & Cement Products
A17: A K SPINTEX LTD | B17: 539300 | C17: Not Listed | D17: Textiles
A18: A K CAPITAL SERVICES LTD | B18: 530499 | C18: Not Listed | D18: Finance (including NBFCs)
A19: A.F. Enterprises Ltd | B19: 538351 | C19: AFEL | D19: Investment Companies
A20: A-1 ACID LTD | B20: 542012 | C20: Not Listed | D20: Comm.Trading & Distribution
A21: A2Z INFRA ENGINEERING LTD | B21: 533292 | C21: A2ZINFRA | D21: Utilities:Non-Elec.
A22: AADHAAR VENTURES (INDIA) LTD | B22: 531611 | C22: Not Listed | D22: Finance (including NBFCs)
A23: AADHAAR VENTURES INDIA LTD | B23: 531611 | C23: Not Listed | D23: Finance (including NBFCs)
A24: AAKASH EXPLORATION SERVICES LTD | B24: Not Listed | C24: AAKASH | D24: SME
A25: AANANDA LAKSHMI SPINNING MILLS LTD | B25: 539096 | C25: Not Listed | D25: Textiles
A26: AANCHAL ISPAT LTD | B26: 538812 | C26: Not Listed | D26: Iron & Steel/Interm.Products
A27: AAR COMMERCIAL COMPANY LTD | B27: 539632 | C27: Not Listed | D27: Distributors
A28: Aar Shyam India Investment Company Ltd | B28: 542377 | C28: AARSHYAM | D28: Finance (including NBFCs)
A29: AAREY DRUGS & PHARMACEUTICALS LTD | B29: 524412 | C29: Not Listed | D29: Pharmaceuticals
A30: AARON INDUSTRIES LTD | B30: Not Listed | C30: AARON | D30: SME
A31: Aartech Solonics Ltd | B31: 542580 | C31: AARTECH | D31: Heavy Electrical Equipment
A32: AARTI DRUGS LTD | B32: 524348 | C32: AARTIDRUGS | D32: Pharmaceuticals
A33: AARTI INDUSTRIES LTD | B33: 524208 | C33: AARTIIND | D33: Commodity Chemicals
A34: AARV INFRATEL LTD | B34: 526488 | C34: Not Listed | D34: Textiles
A35: AARVEE DENIMS & EXPORTS LTD | B35: 514274 | C35: AARVEEDEN | D35: Textiles
A36: AARVI ENCON LTD | B36: Not Listed | C36: AARVI | D36: SME
A37: AASHEE INFOTECH LTD | B37: 519319 | C37: Not Listed | D37: Internet Software & Services
A38: AASWA TRADING & EXPORTS LTD | B38: 512038 | C38: Not Listed | D38: Comm.Trading & Distribution
A39: AAVAS FINANCIERS LTD | B39: 541988 | C39: AAVAS | D39: Housing Finance
A40: AAYUSH FOOD AND HERBS LTD | B40: 539528 | C40: Not Listed | D40: Packaged Foods
A41: ABAN OFFSHORE LTD | B41: 523204 | C41: ABAN | D41: Exploration & Production
A42: ABANS ENTERPRISES LTD | B42: 512165 | C42: Not Listed | D42: Comm.Trading & Distribution
A43: ABB INDIA LTD | B43: 500002 | C43: ABB | D43: Heavy Electrical Equipment
A44: ABBOTT (INDIA) LTD | B44: 500488 | C44: ABBOT(INDIA) | D44: Pharmaceuticals
A45: ABBOTT INDIA LTD | B45: 500488 | C45: ABBOTINDIA | D45: Pharmaceuticals
A46: ABC (INDIA) LTD | B46: 520123 | C46: Not Listed | D46: Surface Transportation
A47: ABC GAS INTERNATIONAL LTD | B47: 513119 | C47: Not Listed | D47: Copper
A48: ABC INDIA LTD | B48: 520123 | C48: Not Listed | D48: Surface Transportation
... A56: ABIRAMI FINANCIAL SERVICES INDIA LTD | B56: 511756 | C56: Not Listed | D56: Finance (including NBFCs)
A57: ABM INTERNATIONAL LTD | B57: Not Listed | C57: ABMINTLTD | D57: Others
A58: ABM KNOWLEDGEWARE LTD | B58: 531161 | C58: Not Listed | D58: IT Software Products
A59: ACC LTD | B59: 500410 | C59: ACC | D59: Cement & Cement Products
A60: ACCEL LTD | B60: 517494 | C60: Not Listed | D60: Storage Media & Peripherals
A61: ACCELYA KALE SOLUTIONS LTD | B61: 532268 | C61: ACCELYA | D61: IT Consulting & Software
A62: ACCORD SYNERGY LTD | B62: Not Listed | C62: ACCORD | D62: SME
A63: ACCURACY SHIPPING LTD | B63: Not Listed | C63: ACCURACY | D63: SME
A64: ACE EDUTREND LTD | B64: 530093 | C64: Not Listed | D64: Education
A65: ACE INTEGRATED SOLUTIONS LTD | B65: Not Listed | C65: ACEINTEG | D65: SME
A66: ACE MEN ENGG WORKS LTD | B66: 539661 | C66: Not Listed | D66: Distributors
A67: ACE SOFTWARE EXPORTS LTD | B67: 531525 | C67: Not Listed | D67: IT Software Products
A68: Achal Investments Ltd | B68: 538570 | C68: ACHAL | D68: Other Financial Services
A69: ACI INFOCOM LTD | B69: 517356 | C69: Not Listed | D69: Storage Media & Peripherals
A70: ACKNIT INDUSTRIES LTD | B70: 530043 | C70: Not Listed | D70: Other Apparels & Accessories
A71: ACME RESOURCES LTD | B71: 539391 | C71: Not Listed | D71: Finance (including NBFCs)
A72: ACROW INDIA LTD. | B72: 513149 | C72: ACROW | D72: Iron &amp; Steel Products
A73: ACRYSIL LTD | B73: 524091 | C73: Not Listed | D73: Plastic Products
A74: ACTION CONSTRUCTION EQUIPMENT LTD | B74: 532762 | C74: ACE | D74: Transport Related Services
A75: ACTION FINANCIAL SERVICES (INDIA) LTD | B75: 511706 | C75: Not Listed | D75: Other Financial Services
A76: ACTION FINANCIAL SERVICES INDIA LTD | B76: 511706 | C76: Not Listed | D76: Other Financial Services
A77: ACTIVE CLOTHING CO LTD | B77: 541144 | C77: Not Listed | D77: Other Apparels & Accessories
... A135: AGRI-TECH INDIA LTD | B135: 537292 | C135: AGRITECH | D135: Other Agricultural Products
A136: AGRO PHOS (INDIA) LTD | B136: Not Listed | C136: AGROPHOS | D136: SME
A137: AGRO PHOS INDIA LTD | B137: Not Listed | C137: AGROPHOS | D137: SME
A138: AGRO TECH FOODS LTD | B138: 500215 | C138: ATFL | D138: Other Agricultural Products
A139: AHIMSA INDUSTRIES LTD | B139: Not Listed | C139: AHIMSA | D139: SME
A140: AHLADA ENGINEERS LTD | B140: Not Listed | C140: AHLADA | D140: SME
A141: AHLUWALIA CONTRACTS (INDIA) LTD | B141: 532811 | C141: AHLUCONT | D141: Realty
A142: AHLUWALIA CONTRACTS INDIA LTD | B142: 532811 | C142: AHLUCONT | D142: Realty
A143: AHMEDABAD STEELCRAFT LTD | B143: 522273 | C143: Not Listed | D143: Iron & Steel/Interm.Products
A144: AI CHAMPDANY INDUSTRIES LTD | B144: 532806 | C144: Not Listed | D144: Jute & Jute Products
A145: AIA ENGINEERING LTD | B145: 532683 | C145: AIAENG | D145: Other Industrial Goods
A146: AIMCO PESTICIDES LTD | B146: 524288 | C146: Not Listed | D146: Agrochemicals
A147: AIRAN LTD | B147: Not Listed | C147: AIRAN | D147: SME
A148: AIRO LAM LTD | B148: Not Listed | C148: AIROLAM | D148: SME
A149: AISHWARYA TELECOM LTD | B149: 532975 | C149: Not Listed | D149: Telecom Equipment
A150: AJANTA PHARMA LTD | B150: 532331 | C150: AJANTPHARM | D150: Pharmaceuticals
A151: AJANTA SOYA LTD | B151: 519216 | C151: Not Listed | D151: Edible Oils
A152: AJCON GLOBAL SERVICES LTD | B152: 511692 | C152: Not Listed | D152: Other Financial Services
A153: AJEL LTD | B153: 530713 | C153: Not Listed | D153: IT Consulting & Software
A154: AJMERA REALTY & INFRA (INDIA) LTD | B154: 513349 | C154: AJMERA | D154: Realty
A155: AJMERA REALTY & INFRA INDIA LTD | B155: 513349 | C155: AJMERA | D155: Realty
A156: AJOONI BIOTECH LTD | B156: Not Listed | C156: AJOONI | D156: SME
A157: AJWA FUN WORLD & RESORT LTD | B157: 526628 | C157: Not Listed | D157: Other Leisure Facilities
A158: AKAR AUTO INDUSTRIES LTD | B158: 530621 | C158: Not Listed | D158: Industrial Machinery
A159: AKASH INFRA PROJECTS LTD | B159: Not Listed | C159: AKASH | D159: SME
A160: AKASHDEEP METAL INDUSTRIES LTD | B160: 538778 | C160: Not Listed | D160: Finance (including NBFCs)
A161: AKG EXIM LTD | B161: Not Listed | C161: AKG | D161: SME
A162: AKI (INDIA) LTD | B162: 542020 | C162: Not Listed | D162: Other Apparels & Accessories
A163: AKI INDIA LTD | B163: 542020 | C163: Not Listed | D163: Other Apparels & Accessories
A164: AKM LACE AND EMBROTEX LTD | B164: 540718 | C164: Not Listed | D164: Textiles
A165: AKME STAR HOUSING FINANCE LTD | B165: 539017 | C165: Not Listed | D165: Housing Finance
...

Sheet Cash Flow Data
C2: 42430 | D2: 42795 | E2: 43160 | F2: 43525 | G2: 43891 | H2: 44256 | I2: 44621 | J2: 44986 | K2: 45352 | L2: 45717
B3: Cash from Operating Activity - | D3: -404 | E3: -748 | F3: -7700 | G3: 1527 | H3: 15117 | I3: 10173 | J3: 8830 | K3: 8223 | L3: 13643
B4: Profit from operations | D4: 5143 | E4: 5329 | F4: 6206 | G4: 6531 | H4: 6744 | I4: 9611 | J4: 11134 | K4: 13317 | L4: 12426
B5: Receivables | D5: 571 | E5: -3563 | F5: -9334 | G5: -1884 | H5: 4996 | I5: 611 | J5: -1750 | K5: -2474 | L5: -4177
B6: Inventory | D6: 2666 | E6: 1835 | F6: 201 | G6: 46 | H6: 2456 | I6: 1766 | J6: 1917 | K6: -2070 | L6: -8535
B7: Payables | D7: -347 | E7: -98 | F7: 960 | G7: 1454 | H7: -1836 | I7: 302 | J7: 577 | K7: 278 | L7: 1693
B8: Other WC items | D8: -7400 | E8: -2740 | F8: -4641 | G8: -2800 | H8: 3633 | I8: -1090 | J8: -293 | K8: 1142 | L8: 15775
B9: Working capital changes | D9: -4510 | E9: -4566 | F9: -12814 | G9: -3183 | H9: 9248 | I9: 1589 | J9: 452 | K9: -3125 | L9: 4756
B10: Direct taxes | D10: -1037 | E10: -1510 | F10: -1092 | G10: -1820 | H10: -875 | I10: -1027 | J10: -2756 | K10: -1969 | L10: -3538
B11: Cash from Investing Activity - | D11: 3012 | E11: 597 | F11: 5294 | G11: -1339 | H11: -1180 | I11: -12785 | J11: -5728 | K11: -6410 | L11: -10771
B12: Fixed assets purchased | D12: -1514 | E12: -1254 | F12: -1395 | G12: -1381 | H12: -1209 | I12: -1501 | J12: -1781 | K12: -1755 | L12: -1757
B13: Fixed assets sold | D13: 12 | E13: 1 | F13: 2 | G13: 2 | H13: 1 | I13: 3 | J13: 5 | K13: 8 | L13: 3
B14: Investments purchased | D14: -64 | E14: -64 | F14: 0 | G14: -76 | H14: -67 | I14: -235 | J14: -95 | K14: -100 | L14: -107
... B27: Net Cash Flow | D27: 2443 | E27: -2691 | F27: -80 | G27: 252 | H27: 6867 | I27: -4076 | J27: 1370 | K27: -186 | L27: 294
